//Deobfuscated with https://github.com/SimplyProgrammer/Minecraft-Deobfuscator3000 using mappings "C:\Users\32302\Desktop\新建文件夹 (2)"!

//Decompiled by Procyon!

package chrriis.dj.nativeswing.swtimpl.core;

final class llIIlIl extends Thread
{
    @Override
    public void run() {
        // 
        // This method could not be decompiled.
        // 
        // Original Bytecode:
        // 
        //     3: dup            
        //     4: aload_0         /* this */
        //     5: ldc             "Forced VM termination thread"
        //     7: invokespecial   chrriis/dj/nativeswing/swtimpl/core/llIlIII.<init>:(Lchrriis/dj/nativeswing/swtimpl/core/llIIlIl;Ljava/lang/String;)V
        //    10: astore_1        /* t */
        //    11: aload_1         /* t */
        //    12: iconst_0       
        //    13: invokevirtual   java/lang/Thread.setDaemon:(Z)V
        //    16: aload_1         /* t */
        //    17: invokevirtual   java/lang/Thread.start:()V
        //    20: invokestatic    chrriis/dj/nativeswing/swtimpl/core/SWTNativeInterface.access$1100:()V
        //    23: return         
        // 
        // The error that occurred was:
        // 
        // java.lang.NullPointerException
        // 
        throw new IllegalStateException("An error occurred while decompiling this method.");
    }
}
