//Deobfuscated with https://github.com/SimplyProgrammer/Minecraft-Deobfuscator3000 using mappings "C:\Users\32302\Desktop\新建文件夹 (2)"!

//Decompiled by Procyon!

package chrriis.dj.nativeswing.swtimpl.components;

import chrriis.dj.nativeswing.swtimpl.*;
import java.util.concurrent.atomic.*;

class lIIIlIIl extends LocalMessage
{
    final /* synthetic */ JHTMLEditor this$0;
    
    lIIIlIIl(final JHTMLEditor this$0) {
        this.this$0 = this$0;
    }
    
    @Override
    public Object run(final Object[] args) {
        // 
        // This method could not be decompiled.
        // 
        // Original Bytecode:
        // 
        //     1: iconst_0       
        //     2: aaload         
        //     3: checkcast       Lchrriis/dj/nativeswing/swtimpl/components/JHTMLEditor$InitializationListener;
        //     6: astore_2        /* initializationListener */
        //     7: aload_1         /* args */
        //     8: iconst_1       
        //     9: aaload         
        //    10: checkcast       Ljava/util/concurrent/atomic/AtomicBoolean;
        //    13: astore_3        /* result */
        //    14: new             Lchrriis/dj/nativeswing/swtimpl/components/lIlIIIIl;
        //    17: dup            
        //    18: aload_0         /* this */
        //    19: aload_3         /* result */
        //    20: invokespecial   chrriis/dj/nativeswing/swtimpl/components/lIlIIIIl.<init>:(Lchrriis/dj/nativeswing/swtimpl/components/lIIIlIIl;Ljava/util/concurrent/atomic/AtomicBoolean;)V
        //    23: sipush          4000
        //    26: invokestatic    chrriis/dj/nativeswing/swtimpl/EventDispatchUtils.sleepWithEventDispatch:(Lchrriis/dj/nativeswing/swtimpl/EventDispatchUtils$Condition;I)V
        //    29: aload_0         /* this */
        //    30: getfield        chrriis/dj/nativeswing/swtimpl/components/lIIIlIIl.this$0:Lchrriis/dj/nativeswing/swtimpl/components/JHTMLEditor;
        //    33: aload_2         /* initializationListener */
        //    34: invokestatic    chrriis/dj/nativeswing/swtimpl/components/JHTMLEditor.access$200:(Lchrriis/dj/nativeswing/swtimpl/components/JHTMLEditor;Lchrriis/dj/nativeswing/swtimpl/components/JHTMLEditor$InitializationListener;)V
        //    37: aconst_null    
        //    38: areturn        
        // 
        // The error that occurred was:
        // 
        // java.lang.NullPointerException
        // 
        throw new IllegalStateException("An error occurred while decompiling this method.");
    }
}
