//Deobfuscated with https://github.com/SimplyProgrammer/Minecraft-Deobfuscator3000 using mappings "C:\Users\32302\Desktop\新建文件夹 (2)"!

//Decompiled by Procyon!

package xyz.Melody;

import by.radioegor146.nativeobfuscator.*;
import xyz.Melody.GUI.CustomUI.*;
import xyz.Melody.Performance.FoamFix.*;
import xyz.Melody.System.Melody.Chat.*;
import org.apache.logging.log4j.*;
import net.minecraft.client.*;
import xyz.Melody.System.Managers.Dungeons.*;
import xyz.Melody.Utils.*;
import xyz.Melody.ClientLib.*;
import xyz.Melody.System.Managers.Client.*;
import net.minecraftforge.common.config.*;
import xyz.Melody.System.Melody.Account.*;
import xyz.Melody.Performance.Math.*;
import xyz.Melody.Event.value.*;
import xyz.Melody.System.Melody.Authentication.*;
import xyz.Melody.System.Managers.Gaming.*;
import net.minecraft.entity.*;
import net.minecraftforge.client.*;
import net.minecraft.client.settings.*;
import net.minecraft.client.gui.*;
import xyz.Melody.Performance.FoamFix.shared.*;
import xyz.Melody.Performance.FoamFix.api.*;
import net.minecraft.util.*;
import xyz.Melody.module.*;
import net.minecraft.client.multiplayer.*;
import java.nio.charset.*;
import javax.crypto.spec.*;
import javax.crypto.*;
import java.security.*;
import net.minecraft.client.renderer.entity.*;
import xyz.Melody.module.FMLModules.*;
import xyz.Melody.System.Commands.FML.*;
import net.minecraftforge.client.event.*;
import net.minecraft.client.entity.*;
import net.minecraftforge.fml.common.eventhandler.*;
import java.util.*;
import java.lang.invoke.*;
import java.lang.reflect.*;
import java.io.*;
import net.minecraftforge.fml.common.*;
import xyz.Melody.module.modules.QOL.Swappings.*;
import net.minecraftforge.fml.common.event.*;
import xyz.Melody.Performance.FoamFix.common.*;
import xyz.Melody.Event.events.world.*;
import xyz.Melody.module.modules.render.*;
import xyz.Melody.module.modules.QOL.*;
import xyz.Melody.module.modules.others.*;
import xyz.Melody.Event.*;

@Mod(modid = "melodysky", useMetadata = true, clientSideOnly = true, acceptedMinecraftVersions = "[1.8.9]")
@Native
public class Client
{
    private static /* synthetic */ String[] lIlllII;
    private static /* synthetic */ String[] lIlIIII;
    private static final /* synthetic */ int[] lIllllI;
    private static final /* synthetic */ String[] lIlIllI;
    private static /* synthetic */ Class[] lIlIIIl;
    
    private void readModValues() {
        // invokedynamic(13:(Lorg/apache/logging/log4j/Logger;Ljava/lang/String;)V, invokedynamic(12:(Lxyz/Melody/Client;)Lorg/apache/logging/log4j/Logger;, this), Client.lIlIllI[Client.lIllllI[124]])
        final List<String> lllIIllIIIIllII = invokedynamic(203:(Ljava/lang/String;)Ljava/util/List;, Client.lIlIllI[Client.lIllllI[125]]);
        final float lllIIllIIIIlIIl = invokedynamic(120:(Ljava/util/List;)Ljava/util/Iterator;, lllIIllIIIIllII);
        while (llllllIl(invokedynamic(121:(Ljava/util/Iterator;)Z, lllIIllIIIIlIIl))) {
            final String lllIIllIIIIlllI = (String)invokedynamic(122:(Ljava/util/Iterator;)Ljava/lang/Object;, lllIIllIIIIlIIl);
            final String lllIIllIIIlIIIl = invokedynamic(224:(Ljava/lang/String;Ljava/lang/String;)[Ljava/lang/String;, lllIIllIIIIlllI, Client.lIlIllI[Client.lIllllI[126]])[Client.lIllllI[0]];
            final String lllIIllIIIlIIII = invokedynamic(224:(Ljava/lang/String;Ljava/lang/String;)[Ljava/lang/String;, lllIIllIIIIlllI, Client.lIlIllI[Client.lIllllI[127]])[Client.lIllllI[2]];
            final Module lllIIllIIIIllll = invokedynamic(225:(Ljava/lang/String;)Lxyz/Melody/module/Module;, lllIIllIIIlIIIl);
            if (lIIIIIlIl(lllIIllIIIIllll)) {
                "".length();
                if (-((0x18 ^ 0x55) << " ".length() ^ (0xD0 ^ 0x9F) << " ".length()) >= 0) {
                    return;
                }
                continue;
            }
            else {
                final Exception lllIIllIIIIIlII = invokedynamic(120:(Ljava/util/List;)Ljava/util/Iterator;, invokedynamic(230:(Lxyz/Melody/module/Module;)Ljava/util/List;, lllIIllIIIIllll));
                while (llllllIl(invokedynamic(121:(Ljava/util/Iterator;)Z, lllIIllIIIIIlII))) {
                    final Value lllIIllIIIlIIlI = (Value)invokedynamic(122:(Ljava/util/Iterator;)Ljava/lang/Object;, lllIIllIIIIIlII);
                    if (lllllllI(invokedynamic(232:(Ljava/lang/String;Ljava/lang/String;)Z, invokedynamic(231:(Lxyz/Melody/Event/value/Value;)Ljava/lang/String;, lllIIllIIIlIIlI), lllIIllIIIlIIII))) {
                        "".length();
                        if (" ".length() << (" ".length() << " ".length()) != " ".length() << (" ".length() << " ".length())) {
                            return;
                        }
                        continue;
                    }
                    else if (llllllIl((lllIIllIIIlIIlI instanceof Option) ? 1 : 0)) {
                        // invokedynamic(235:(Lxyz/Melody/Event/value/Value;Ljava/lang/Object;)V, lllIIllIIIlIIlI, invokedynamic(234:(Z)Ljava/lang/Boolean;, invokedynamic(233:(Ljava/lang/String;)Z, invokedynamic(224:(Ljava/lang/String;Ljava/lang/String;)[Ljava/lang/String;, lllIIllIIIIlllI, Client.lIlIllI[Client.lIllllI[128]])[Client.lIllllI[4]])))
                        // invokedynamic(13:(Lorg/apache/logging/log4j/Logger;Ljava/lang/String;)V, invokedynamic(12:(Lxyz/M...
                        "".length();
                        if (" ".length() << (" ".length() << " ".length()) != " ".length() << (" ".length() << " ".length())) {
                            return;
                        }
                        continue;
                    }
                    else if (llllllIl((lllIIllIIIlIIlI instanceof Numbers) ? 1 : 0)) {
                        // invokedynamic(235:(Lxyz/Melody/Event/value/Value;Ljava/lang/Object;)V, lllIIllIIIlIIlI, invokedynamic(143:(D)Ljava/lang/Double;, invokedynamic(236:(Ljava/lang/String;)D, invokedynamic(224:(Ljava/lang/String;Ljava/lang/String;)[Ljava/lang/String;, lllIIllIIIIlllI, Client.lIlIllI[Client.lIllllI[133]])[Client.lIllllI[4]])))
                        // invokedynamic(13:(Lorg/apache/logging/log4j/Logger;Ljava/lang/String;)V, invokedynamic(12:(Lxyz/M...
                        "".length();
                        if (" ".length() << (" ".length() << " ".length()) <= "   ".length()) {
                            return;
                        }
                        continue;
                    }
                    else {
                        // invokedynamic(238:(Lxyz/Melody/Event/value/Mode;Ljava/lang/String;)V, (Mode)lllIIllIIIlIIlI, invokedynamic(224:(Ljava/lang/String;Ljava/lang/String;)[Ljava/lang/String;, lllIIllIIIIlllI, Client.lIlIllI[Client.lIllllI[138]])[Client.lIllllI[4]])
                        "".length();
                        if ("   ".length() == -" ".length()) {
                            return;
                        }
                        continue;
                    }
                }
                "".length();
                if (null != null) {
                    return;
                }
                continue;
            }
        }
    }
    // invokedynamic(13:(Lorg/apache/logging/log4j/Logger;Ljava/lang/String;)V, invokedynamic(12:(Lxyz/Melody/Client;)Lorg/apache/logging/log4j/Logger;, this), Client.lIlIllI[Client.lIllllI[139]])
    
    private void readUISettings() {
        // invokedynamic(13:(Lorg/apache/logging/log4j/Logger;Ljava/lang/String;)V, invokedynamic(12:(Lxyz/Melody/Client;)Lorg/apache/logging/log4j/Logger;, this), Client.lIlIllI[Client.lIllllI[89]])
        final List<String> lllIIllIllIIlII = invokedynamic(203:(Ljava/lang/String;)Ljava/util/List;, Client.lIlIllI[Client.lIllllI[90]]);
        final char lllIIllIllIIIIl = invokedynamic(120:(Ljava/util/List;)Ljava/util/Iterator;, lllIIllIllIIlII);
        while (llllllIl(invokedynamic(121:(Ljava/util/Iterator;)Z, lllIIllIllIIIIl))) {
            final char lllIIllIlIlllll;
            final String lllIIllIllIIllI = (String)(lllIIllIlIlllll = (char)(String)invokedynamic(122:(Ljava/util/Iterator;)Ljava/lang/Object;, lllIIllIllIIIIl));
            char lllIIllIlIllllI = (char)Client.lIllllI[91];
            switch (invokedynamic(211:(Ljava/lang/String;)I, lllIIllIlIlllll)) {
                case -2072873435: {
                    if (!llllllIl(invokedynamic(79:(Ljava/lang/String;Ljava/lang/Object;)Z, lllIIllIlIlllll, Client.lIlIllI[Client.lIllllI[92]]))) {
                        break;
                    }
                    lllIIllIlIllllI = (char)Client.lIllllI[0];
                    "".length();
                    if (" ".length() << (" ".length() << " ".length()) <= 0) {
                        return;
                    }
                    break;
                }
                case -950372698: {
                    if (!llllllIl(invokedynamic(79:(Ljava/lang/String;Ljava/lang/Object;)Z, lllIIllIlIlllll, Client.lIlIllI[Client.lIllllI[93]]))) {
                        break;
                    }
                    lllIIllIlIllllI = (char)Client.lIllllI[2];
                    "".length();
                    if (" ".length() < 0) {
                        return;
                    }
                    break;
                }
                case 783533026: {
                    if (llllllIl(invokedynamic(79:(Ljava/lang/String;Ljava/lang/Object;)Z, lllIIllIlIlllll, Client.lIlIllI[Client.lIllllI[94]]))) {
                        lllIIllIlIllllI = (char)Client.lIllllI[4];
                        break;
                    }
                    break;
                }
            }
            switch (lllIIllIlIllllI) {
                case '\0': {
                    // invokedynamic(212:(Z)V, Client.lIllllI[0])
                    "".length();
                    if (((0x2 ^ 0x29 ^ (0xB0 ^ 0xB7) << "   ".length()) & ((0xAF ^ 0x88) << " ".length() ^ (0xD5 ^ 0x88) ^ -" ".length())) != 0x0) {
                        return;
                    }
                    break;
                }
                case '\u0001': {
                    // invokedynamic(213:(Z)V, Client.lIllllI[0])
                    "".length();
                    if (" ".length() > " ".length()) {
                        return;
                    }
                    break;
                }
                case '\u0002': {
                    // invokedynamic(214:(Z)V, Client.lIllllI[0])
                    break;
                }
            }
            "".length();
            if (null != null) {
                return;
            }
        }
    }
    // invokedynamic(13:(Lorg/apache/logging/log4j/Logger;Ljava/lang/String;)V, invokedynamic(12:(Lxyz/Melody/Client;)Lorg/apache/logging/log4j/Logger;, this), Client.lIlIllI[Client.lIllllI[95]])
    
    public void start() {
        class ll extends TimerTask
        {
            final /* synthetic */ Client this$0;
            
            ll(final Client this$0) {
                this.this$0 = this$0;
            }
            
            @Override
            public void run() {
                if (!Client.access$000(this.this$0).enabledNeededMod) {
                    this.this$0.saveConfig(false);
                    this.this$0.saveCustomName();
                    this.this$0.saveMenuMode();
                    this.this$0.saveUISettings(false);
                }
            }
        }
        // 
        // This method could not be decompiled.
        // 
        // Original Bytecode:
        // 
        //     1: ldc             ""
        //     3: invokevirtual   java/lang/String.length:()I
        //     6: pop2           
        //     7: getstatic       xyz/Melody/Client.lIllllI:[I
        //    10: iconst_0       
        //    11: iaload         
        //    12: invokedynamic   BootstrapMethod #0, 11:(Z)V
        //    17: aload_0         /* lllIlIIIlIIIlII */
        //    18: invokedynamic   BootstrapMethod #0, 12:(Lxyz/Melody/Client;)Lorg/apache/logging/log4j/Logger;
        //    23: getstatic       xyz/Melody/Client.lIlIllI:[Ljava/lang/String;
        //    26: getstatic       xyz/Melody/Client.lIllllI:[I
        //    29: bipush          7
        //    31: iaload         
        //    32: aaload         
        //    33: invokedynamic   BootstrapMethod #0, 13:(Lorg/apache/logging/log4j/Logger;Ljava/lang/String;)V
        //    38: aload_0         /* lllIlIIIlIIIlII */
        //    39: invokedynamic   BootstrapMethod #0, 12:(Lxyz/Melody/Client;)Lorg/apache/logging/log4j/Logger;
        //    44: new             Ljava/lang/StringBuilder;
        //    47: dup            
        //    48: invokespecial   java/lang/StringBuilder.<init>:()V
        //    51: getstatic       xyz/Melody/Client.lIlIllI:[Ljava/lang/String;
        //    54: getstatic       xyz/Melody/Client.lIllllI:[I
        //    57: bipush          8
        //    59: iaload         
        //    60: aaload         
        //    61: invokedynamic   BootstrapMethod #0, 14:(Ljava/lang/StringBuilder;Ljava/lang/String;)Ljava/lang/StringBuilder;
        //    66: aload_0         /* lllIlIIIlIIIlII */
        //    67: ldc             ""
        //    69: invokevirtual   java/lang/String.length:()I
        //    72: pop2           
        //    73: invokedynamic   BootstrapMethod #0, 15:()Ljava/nio/charset/Charset;
        //    78: invokedynamic   BootstrapMethod #0, 16:(Ljava/lang/StringBuilder;Ljava/lang/Object;)Ljava/lang/StringBuilder;
        //    83: getstatic       xyz/Melody/Client.lIlIllI:[Ljava/lang/String;
        //    86: getstatic       xyz/Melody/Client.lIllllI:[I
        //    89: bipush          9
        //    91: iaload         
        //    92: aaload         
        //    93: invokedynamic   BootstrapMethod #0, 14:(Ljava/lang/StringBuilder;Ljava/lang/String;)Ljava/lang/StringBuilder;
        //    98: invokedynamic   BootstrapMethod #0, 17:(Ljava/lang/StringBuilder;)Ljava/lang/String;
        //   103: invokedynamic   BootstrapMethod #0, 13:(Lorg/apache/logging/log4j/Logger;Ljava/lang/String;)V
        //   108: invokedynamic   BootstrapMethod #0, 18:()V
        //   113: aload_0         /* lllIlIIIlIIIlII */
        //   114: invokedynamic   BootstrapMethod #0, 12:(Lxyz/Melody/Client;)Lorg/apache/logging/log4j/Logger;
        //   119: getstatic       xyz/Melody/Client.lIlIllI:[Ljava/lang/String;
        //   122: getstatic       xyz/Melody/Client.lIllllI:[I
        //   125: bipush          10
        //   127: iaload         
        //   128: aaload         
        //   129: invokedynamic   BootstrapMethod #0, 13:(Lorg/apache/logging/log4j/Logger;Ljava/lang/String;)V
        //   134: aload_0         /* lllIlIIIlIIIlII */
        //   135: invokedynamic   BootstrapMethod #0, 12:(Lxyz/Melody/Client;)Lorg/apache/logging/log4j/Logger;
        //   140: getstatic       xyz/Melody/Client.lIlIllI:[Ljava/lang/String;
        //   143: getstatic       xyz/Melody/Client.lIllllI:[I
        //   146: bipush          11
        //   148: iaload         
        //   149: aaload         
        //   150: invokedynamic   BootstrapMethod #0, 13:(Lorg/apache/logging/log4j/Logger;Ljava/lang/String;)V
        //   155: aload_0         /* lllIlIIIlIIIlII */
        //   156: ldc             ""
        //   158: invokevirtual   java/lang/String.length:()I
        //   161: pop2           
        //   162: invokedynamic   BootstrapMethod #0, 19:()Lnet/minecraft/client/Minecraft;
        //   167: invokedynamic   BootstrapMethod #0, 20:(Lnet/minecraft/client/Minecraft;)Lnet/minecraft/util/Session;
        //   172: invokedynamic   BootstrapMethod #0, 21:(Lnet/minecraft/util/Session;)V
        //   177: aload_0         /* lllIlIIIlIIIlII */
        //   178: ldc             ""
        //   180: invokevirtual   java/lang/String.length:()I
        //   183: pop2           
        //   184: aload_0         /* lllIlIIIlIIIlII */
        //   185: ldc             ""
        //   187: invokevirtual   java/lang/String.length:()I
        //   190: pop2           
        //   191: invokedynamic   BootstrapMethod #0, 22:()Lnet/minecraft/util/Session;
        //   196: invokedynamic   BootstrapMethod #0, 23:(Lnet/minecraft/util/Session;)V
        //   201: aload_0         /* lllIlIIIlIIIlII */
        //   202: new             Lxyz/Melody/System/Melody/Authentication/AuthManager;
        //   205: dup            
        //   206: invokespecial   xyz/Melody/System/Melody/Authentication/AuthManager.<init>:()V
        //   209: invokedynamic   BootstrapMethod #0, 24:(Lxyz/Melody/Client;Lxyz/Melody/System/Melody/Authentication/AuthManager;)V
        //   214: aload_0         /* lllIlIIIlIIIlII */
        //   215: invokedynamic   BootstrapMethod #0, 25:(Lxyz/Melody/Client;)Lxyz/Melody/System/Melody/Authentication/AuthManager;
        //   220: new             Lxyz/Melody/System/Melody/Authentication/UserObj;
        //   223: dup            
        //   224: invokedynamic   BootstrapMethod #0, 19:()Lnet/minecraft/client/Minecraft;
        //   229: invokedynamic   BootstrapMethod #0, 20:(Lnet/minecraft/client/Minecraft;)Lnet/minecraft/util/Session;
        //   234: invokedynamic   BootstrapMethod #0, 26:(Lnet/minecraft/util/Session;)Ljava/lang/String;
        //   239: invokedynamic   BootstrapMethod #0, 19:()Lnet/minecraft/client/Minecraft;
        //   244: invokedynamic   BootstrapMethod #0, 20:(Lnet/minecraft/client/Minecraft;)Lnet/minecraft/util/Session;
        //   249: invokedynamic   BootstrapMethod #0, 27:(Lnet/minecraft/util/Session;)Lcom/mojang/authlib/GameProfile;
        //   254: invokedynamic   BootstrapMethod #0, 28:(Lcom/mojang/authlib/GameProfile;)Ljava/util/UUID;
        //   259: invokedynamic   BootstrapMethod #0, 29:(Ljava/util/UUID;)Ljava/lang/String;
        //   264: invokedynamic   BootstrapMethod #0, 19:()Lnet/minecraft/client/Minecraft;
        //   269: invokedynamic   BootstrapMethod #0, 20:(Lnet/minecraft/client/Minecraft;)Lnet/minecraft/util/Session;
        //   274: invokedynamic   BootstrapMethod #0, 30:(Lnet/minecraft/util/Session;)Ljava/lang/String;
        //   279: invokespecial   xyz/Melody/System/Melody/Authentication/UserObj.<init>:(Ljava/lang/String;Ljava/lang/String;Ljava/lang/String;)V
        //   282: invokedynamic   BootstrapMethod #0, 31:(Lxyz/Melody/System/Melody/Authentication/AuthManager;Lxyz/Melody/System/Melody/Authentication/UserObj;)V
        //   287: aload_0         /* lllIlIIIlIIIlII */
        //   288: invokedynamic   BootstrapMethod #0, 25:(Lxyz/Melody/Client;)Lxyz/Melody/System/Melody/Authentication/AuthManager;
        //   293: invokedynamic   BootstrapMethod #0, 32:(Lxyz/Melody/System/Melody/Authentication/AuthManager;)V
        //   298: getstatic       xyz/Melody/Client.lIlIllI:[Ljava/lang/String;
        //   301: getstatic       xyz/Melody/Client.lIllllI:[I
        //   304: bipush          12
        //   306: iaload         
        //   307: aaload         
        //   308: invokedynamic   BootstrapMethod #0, 33:(Ljava/lang/String;)V
        //   313: invokedynamic   BootstrapMethod #0, 34:()V
        //   318: aload_0         /* lllIlIIIlIIIlII */
        //   319: invokedynamic   BootstrapMethod #0, 12:(Lxyz/Melody/Client;)Lorg/apache/logging/log4j/Logger;
        //   324: new             Ljava/lang/StringBuilder;
        //   327: dup            
        //   328: invokespecial   java/lang/StringBuilder.<init>:()V
        //   331: getstatic       xyz/Melody/Client.lIlIllI:[Ljava/lang/String;
        //   334: getstatic       xyz/Melody/Client.lIllllI:[I
        //   337: bipush          13
        //   339: iaload         
        //   340: aaload         
        //   341: invokedynamic   BootstrapMethod #0, 14:(Ljava/lang/StringBuilder;Ljava/lang/String;)Ljava/lang/StringBuilder;
        //   346: aload_0         /* lllIlIIIlIIIlII */
        //   347: invokedynamic   BootstrapMethod #0, 25:(Lxyz/Melody/Client;)Lxyz/Melody/System/Melody/Authentication/AuthManager;
        //   352: invokedynamic   BootstrapMethod #0, 35:(Lxyz/Melody/System/Melody/Authentication/AuthManager;)Z
        //   357: invokedynamic   BootstrapMethod #0, 36:(Ljava/lang/StringBuilder;Z)Ljava/lang/StringBuilder;
        //   362: invokedynamic   BootstrapMethod #0, 17:(Ljava/lang/StringBuilder;)Ljava/lang/String;
        //   367: invokedynamic   BootstrapMethod #0, 13:(Lorg/apache/logging/log4j/Logger;Ljava/lang/String;)V
        //   372: invokedynamic   BootstrapMethod #0, 37:()V
        //   377: aload_0         /* lllIlIIIlIIIlII */
        //   378: invokedynamic   BootstrapMethod #0, 12:(Lxyz/Melody/Client;)Lorg/apache/logging/log4j/Logger;
        //   383: getstatic       xyz/Melody/Client.lIlIllI:[Ljava/lang/String;
        //   386: getstatic       xyz/Melody/Client.lIllllI:[I
        //   389: bipush          14
        //   391: iaload         
        //   392: aaload         
        //   393: invokedynamic   BootstrapMethod #0, 13:(Lorg/apache/logging/log4j/Logger;Ljava/lang/String;)V
        //   398: aload_0         /* lllIlIIIlIIIlII */
        //   399: invokedynamic   BootstrapMethod #0, 12:(Lxyz/Melody/Client;)Lorg/apache/logging/log4j/Logger;
        //   404: getstatic       xyz/Melody/Client.lIlIllI:[Ljava/lang/String;
        //   407: getstatic       xyz/Melody/Client.lIllllI:[I
        //   410: bipush          15
        //   412: iaload         
        //   413: aaload         
        //   414: invokedynamic   BootstrapMethod #0, 13:(Lorg/apache/logging/log4j/Logger;Ljava/lang/String;)V
        //   419: aload_0         /* lllIlIIIlIIIlII */
        //   420: invokespecial   xyz/Melody/Client.initModHider:()V
        //   423: aload_0         /* lllIlIIIlIIIlII */
        //   424: invokedynamic   BootstrapMethod #0, 12:(Lxyz/Melody/Client;)Lorg/apache/logging/log4j/Logger;
        //   429: getstatic       xyz/Melody/Client.lIlIllI:[Ljava/lang/String;
        //   432: getstatic       xyz/Melody/Client.lIllllI:[I
        //   435: bipush          16
        //   437: iaload         
        //   438: aaload         
        //   439: invokedynamic   BootstrapMethod #0, 13:(Lorg/apache/logging/log4j/Logger;Ljava/lang/String;)V
        //   444: new             Lxyz/Melody/System/Managers/Gaming/GameListenerHook;
        //   447: dup            
        //   448: invokespecial   xyz/Melody/System/Managers/Gaming/GameListenerHook.<init>:()V
        //   451: invokedynamic   BootstrapMethod #0, 38:(Lxyz/Melody/System/Managers/Gaming/GameListenerHook;)V
        //   456: getstatic       xyz/Melody/Client.lIllllI:[I
        //   459: iconst_2       
        //   460: iaload         
        //   461: invokedynamic   BootstrapMethod #0, 39:(Z)V
        //   466: getstatic       xyz/Melody/Client.lIllllI:[I
        //   469: iconst_0       
        //   470: iaload         
        //   471: invokedynamic   BootstrapMethod #0, 40:(Z)V
        //   476: getstatic       xyz/Melody/Client.lIllllI:[I
        //   479: iconst_0       
        //   480: iaload         
        //   481: invokedynamic   BootstrapMethod #0, 41:(Z)V
        //   486: aload_0         /* lllIlIIIlIIIlII */
        //   487: getstatic       xyz/Melody/Client.lIllllI:[I
        //   490: iconst_0       
        //   491: iaload         
        //   492: invokedynamic   BootstrapMethod #0, 42:(Lxyz/Melody/Client;Z)V
        //   497: aload_0         /* lllIlIIIlIIIlII */
        //   498: new             Lxyz/Melody/System/Managers/Client/CommandManager;
        //   501: dup            
        //   502: invokespecial   xyz/Melody/System/Managers/Client/CommandManager.<init>:()V
        //   505: invokedynamic   BootstrapMethod #0, 43:(Lxyz/Melody/Client;Lxyz/Melody/System/Managers/Client/CommandManager;)V
        //   510: aload_0         /* lllIlIIIlIIIlII */
        //   511: invokedynamic   BootstrapMethod #0, 44:(Lxyz/Melody/Client;)Lxyz/Melody/System/Managers/Client/CommandManager;
        //   516: invokedynamic   BootstrapMethod #0, 45:(Lxyz/Melody/System/Managers/Client/CommandManager;)V
        //   521: aload_0         /* lllIlIIIlIIIlII */
        //   522: invokedynamic   BootstrapMethod #0, 12:(Lxyz/Melody/Client;)Lorg/apache/logging/log4j/Logger;
        //   527: getstatic       xyz/Melody/Client.lIlIllI:[Ljava/lang/String;
        //   530: getstatic       xyz/Melody/Client.lIllllI:[I
        //   533: bipush          17
        //   535: iaload         
        //   536: aaload         
        //   537: invokedynamic   BootstrapMethod #0, 13:(Lorg/apache/logging/log4j/Logger;Ljava/lang/String;)V
        //   542: aload_0         /* lllIlIIIlIIIlII */
        //   543: new             Lxyz/Melody/System/Managers/Client/FriendManager;
        //   546: dup            
        //   547: invokespecial   xyz/Melody/System/Managers/Client/FriendManager.<init>:()V
        //   550: invokedynamic   BootstrapMethod #0, 46:(Lxyz/Melody/Client;Lxyz/Melody/System/Managers/Client/FriendManager;)V
        //   555: aload_0         /* lllIlIIIlIIIlII */
        //   556: invokedynamic   BootstrapMethod #0, 47:(Lxyz/Melody/Client;)Lxyz/Melody/System/Managers/Client/FriendManager;
        //   561: invokedynamic   BootstrapMethod #0, 48:(Lxyz/Melody/System/Managers/Client/FriendManager;)V
        //   566: aload_0         /* lllIlIIIlIIIlII */
        //   567: invokedynamic   BootstrapMethod #0, 12:(Lxyz/Melody/Client;)Lorg/apache/logging/log4j/Logger;
        //   572: getstatic       xyz/Melody/Client.lIlIllI:[Ljava/lang/String;
        //   575: getstatic       xyz/Melody/Client.lIllllI:[I
        //   578: bipush          18
        //   580: iaload         
        //   581: aaload         
        //   582: invokedynamic   BootstrapMethod #0, 13:(Lorg/apache/logging/log4j/Logger;Ljava/lang/String;)V
        //   587: aload_0         /* lllIlIIIlIIIlII */
        //   588: new             Lxyz/Melody/System/Melody/Account/AltManager;
        //   591: dup            
        //   592: invokespecial   xyz/Melody/System/Melody/Account/AltManager.<init>:()V
        //   595: invokedynamic   BootstrapMethod #0, 49:(Lxyz/Melody/Client;Lxyz/Melody/System/Melody/Account/AltManager;)V
        //   600: aload_0         /* lllIlIIIlIIIlII */
        //   601: invokedynamic   BootstrapMethod #0, 50:(Lxyz/Melody/Client;)Lxyz/Melody/System/Melody/Account/AltManager;
        //   606: invokedynamic   BootstrapMethod #0, 51:(Lxyz/Melody/System/Melody/Account/AltManager;)V
        //   611: aload_0         /* lllIlIIIlIIIlII */
        //   612: invokedynamic   BootstrapMethod #0, 12:(Lxyz/Melody/Client;)Lorg/apache/logging/log4j/Logger;
        //   617: getstatic       xyz/Melody/Client.lIlIllI:[Ljava/lang/String;
        //   620: getstatic       xyz/Melody/Client.lIllllI:[I
        //   623: bipush          19
        //   625: iaload         
        //   626: aaload         
        //   627: invokedynamic   BootstrapMethod #0, 13:(Lorg/apache/logging/log4j/Logger;Ljava/lang/String;)V
        //   632: aload_0         /* lllIlIIIlIIIlII */
        //   633: new             Lxyz/Melody/GUI/CustomUI/HUDManager;
        //   636: dup            
        //   637: invokespecial   xyz/Melody/GUI/CustomUI/HUDManager.<init>:()V
        //   640: invokedynamic   BootstrapMethod #0, 52:(Lxyz/Melody/Client;Lxyz/Melody/GUI/CustomUI/HUDManager;)V
        //   645: aload_0         /* lllIlIIIlIIIlII */
        //   646: invokedynamic   BootstrapMethod #0, 53:(Lxyz/Melody/Client;)Lxyz/Melody/GUI/CustomUI/HUDManager;
        //   651: invokedynamic   BootstrapMethod #0, 54:(Lxyz/Melody/GUI/CustomUI/HUDManager;)V
        //   656: aload_0         /* lllIlIIIlIIIlII */
        //   657: invokedynamic   BootstrapMethod #0, 12:(Lxyz/Melody/Client;)Lorg/apache/logging/log4j/Logger;
        //   662: getstatic       xyz/Melody/Client.lIlIllI:[Ljava/lang/String;
        //   665: getstatic       xyz/Melody/Client.lIllllI:[I
        //   668: bipush          20
        //   670: iaload         
        //   671: aaload         
        //   672: invokedynamic   BootstrapMethod #0, 13:(Lorg/apache/logging/log4j/Logger;Ljava/lang/String;)V
        //   677: new             Ljava/lang/Thread;
        //   680: dup            
        //   681: aload_0         /* lllIlIIIlIIIlII */
        //   682: invokedynamic   BootstrapMethod #1, run:(Lxyz/Melody/Client;)Ljava/lang/Runnable;
        //   687: invokespecial   java/lang/Thread.<init>:(Ljava/lang/Runnable;)V
        //   690: invokedynamic   BootstrapMethod #0, 55:(Ljava/lang/Thread;)V
        //   695: aload_0         /* lllIlIIIlIIIlII */
        //   696: invokedynamic   BootstrapMethod #0, 12:(Lxyz/Melody/Client;)Lorg/apache/logging/log4j/Logger;
        //   701: getstatic       xyz/Melody/Client.lIlIllI:[Ljava/lang/String;
        //   704: getstatic       xyz/Melody/Client.lIllllI:[I
        //   707: bipush          21
        //   709: iaload         
        //   710: aaload         
        //   711: invokedynamic   BootstrapMethod #0, 13:(Lorg/apache/logging/log4j/Logger;Ljava/lang/String;)V
        //   716: new             Ljava/lang/Thread;
        //   719: dup            
        //   720: aload_0         /* lllIlIIIlIIIlII */
        //   721: invokedynamic   BootstrapMethod #2, run:(Lxyz/Melody/Client;)Ljava/lang/Runnable;
        //   726: getstatic       xyz/Melody/Client.lIlIllI:[Ljava/lang/String;
        //   729: getstatic       xyz/Melody/Client.lIllllI:[I
        //   732: bipush          22
        //   734: iaload         
        //   735: aaload         
        //   736: invokespecial   java/lang/Thread.<init>:(Ljava/lang/Runnable;Ljava/lang/String;)V
        //   739: invokedynamic   BootstrapMethod #0, 55:(Ljava/lang/Thread;)V
        //   744: aload_0         /* lllIlIIIlIIIlII */
        //   745: new             Lxyz/Melody/System/Managers/Client/ModuleManager;
        //   748: dup            
        //   749: invokespecial   xyz/Melody/System/Managers/Client/ModuleManager.<init>:()V
        //   752: invokedynamic   BootstrapMethod #0, 56:(Lxyz/Melody/Client;Lxyz/Melody/System/Managers/Client/ModuleManager;)V
        //   757: aload_0         /* lllIlIIIlIIIlII */
        //   758: invokedynamic   BootstrapMethod #0, 57:(Lxyz/Melody/Client;)Lxyz/Melody/System/Managers/Client/ModuleManager;
        //   763: invokedynamic   BootstrapMethod #0, 58:(Lxyz/Melody/System/Managers/Client/ModuleManager;)V
        //   768: aload_0         /* lllIlIIIlIIIlII */
        //   769: invokedynamic   BootstrapMethod #0, 12:(Lxyz/Melody/Client;)Lorg/apache/logging/log4j/Logger;
        //   774: getstatic       xyz/Melody/Client.lIlIllI:[Ljava/lang/String;
        //   777: getstatic       xyz/Melody/Client.lIllllI:[I
        //   780: bipush          23
        //   782: iaload         
        //   783: aaload         
        //   784: invokedynamic   BootstrapMethod #0, 13:(Lorg/apache/logging/log4j/Logger;Ljava/lang/String;)V
        //   789: aload_0         /* lllIlIIIlIIIlII */
        //   790: new             Lxyz/Melody/System/Managers/Dungeons/DungeonListener;
        //   793: dup            
        //   794: invokespecial   xyz/Melody/System/Managers/Dungeons/DungeonListener.<init>:()V
        //   797: invokedynamic   BootstrapMethod #0, 59:(Lxyz/Melody/Client;Lxyz/Melody/System/Managers/Dungeons/DungeonListener;)V
        //   802: aload_0         /* lllIlIIIlIIIlII */
        //   803: invokedynamic   BootstrapMethod #0, 60:(Lxyz/Melody/Client;)Lxyz/Melody/System/Managers/Dungeons/DungeonListener;
        //   808: invokedynamic   BootstrapMethod #0, 61:(Lxyz/Melody/System/Managers/Dungeons/DungeonListener;)V
        //   813: aload_0         /* lllIlIIIlIIIlII */
        //   814: new             Lxyz/Melody/System/Managers/Dungeons/MimicListener;
        //   817: dup            
        //   818: invokespecial   xyz/Melody/System/Managers/Dungeons/MimicListener.<init>:()V
        //   821: invokedynamic   BootstrapMethod #0, 62:(Lxyz/Melody/Client;Lxyz/Melody/System/Managers/Dungeons/MimicListener;)V
        //   826: aload_0         /* lllIlIIIlIIIlII */
        //   827: invokedynamic   BootstrapMethod #0, 63:(Lxyz/Melody/Client;)Lxyz/Melody/System/Managers/Dungeons/MimicListener;
        //   832: invokedynamic   BootstrapMethod #0, 64:(Lxyz/Melody/System/Managers/Dungeons/MimicListener;)V
        //   837: invokedynamic   BootstrapMethod #0, 65:()Lxyz/Melody/Client;
        //   842: invokedynamic   BootstrapMethod #0, 12:(Lxyz/Melody/Client;)Lorg/apache/logging/log4j/Logger;
        //   847: getstatic       xyz/Melody/Client.lIlIllI:[Ljava/lang/String;
        //   850: getstatic       xyz/Melody/Client.lIllllI:[I
        //   853: bipush          24
        //   855: iaload         
        //   856: aaload         
        //   857: invokedynamic   BootstrapMethod #0, 13:(Lorg/apache/logging/log4j/Logger;Ljava/lang/String;)V
        //   862: aload_0         /* lllIlIIIlIIIlII */
        //   863: invokedynamic   BootstrapMethod #0, 12:(Lxyz/Melody/Client;)Lorg/apache/logging/log4j/Logger;
        //   868: getstatic       xyz/Melody/Client.lIlIllI:[Ljava/lang/String;
        //   871: getstatic       xyz/Melody/Client.lIllllI:[I
        //   874: bipush          25
        //   876: iaload         
        //   877: aaload         
        //   878: invokedynamic   BootstrapMethod #0, 13:(Lorg/apache/logging/log4j/Logger;Ljava/lang/String;)V
        //   883: invokedynamic   BootstrapMethod #0, 66:()V
        //   888: invokedynamic   BootstrapMethod #0, 67:()V
        //   893: aload_0         /* lllIlIIIlIIIlII */
        //   894: invokedynamic   BootstrapMethod #0, 68:(Lxyz/Melody/Client;)Ljava/util/Timer;
        //   899: new             Lxyz/Melody/ll;
        //   902: dup            
        //   903: aload_0         /* lllIlIIIlIIIlII */
        //   904: invokespecial   xyz/Melody/ll.<init>:(Lxyz/Melody/Client;)V
        //   907: lconst_1       
        //   908: ldc2_w          60000
        //   911: invokedynamic   BootstrapMethod #0, 69:(Ljava/util/Timer;Ljava/util/TimerTask;JJ)V
        //   916: aload_0         /* lllIlIIIlIIIlII */
        //   917: new             Lxyz/Melody/ClientLib/SkyblockArea;
        //   920: dup            
        //   921: invokespecial   xyz/Melody/ClientLib/SkyblockArea.<init>:()V
        //   924: invokedynamic   BootstrapMethod #0, 70:(Lxyz/Melody/Client;Lxyz/Melody/ClientLib/SkyblockArea;)V
        //   929: aload_0         /* lllIlIIIlIIIlII */
        //   930: ldc             ""
        //   932: invokevirtual   java/lang/String.length:()I
        //   935: pop2           
        //   936: getstatic       xyz/Melody/Client.lIllllI:[I
        //   939: iconst_0       
        //   940: iaload         
        //   941: invokedynamic   BootstrapMethod #0, 71:(Z)V
        //   946: aload_0         /* lllIlIIIlIIIlII */
        //   947: invokedynamic   BootstrapMethod #0, 72:(Lxyz/Melody/Client;)Lxyz/Melody/System/Managers/Client/ModuleManager;
        //   952: ldc_w           Lxyz/Melody/module/modules/render/ClickGui;.class
        //   955: invokedynamic   BootstrapMethod #0, 73:(Lxyz/Melody/System/Managers/Client/ModuleManager;Ljava/lang/Class;)Lxyz/Melody/module/Module;
        //   960: getstatic       xyz/Melody/Client.lIllllI:[I
        //   963: bipush          26
        //   965: iaload         
        //   966: invokedynamic   BootstrapMethod #0, 74:(Lxyz/Melody/module/Module;I)V
        //   971: aload_0         /* lllIlIIIlIIIlII */
        //   972: invokedynamic   BootstrapMethod #0, 75:(Lxyz/Melody/Client;)I
        //   977: getstatic       xyz/Melody/Client.lIllllI:[I
        //   980: iconst_2       
        //   981: iaload         
        //   982: invokestatic    xyz/Melody/Client.llllllII:(II)Z
        //   985: ifeq            1078
        //   988: new             Ljava/lang/Throwable;
        //   991: dup            
        //   992: new             Ljava/lang/StringBuilder;
        //   995: dup            
        //   996: invokespecial   java/lang/StringBuilder.<init>:()V
        //   999: getstatic       xyz/Melody/Client.lIlIllI:[Ljava/lang/String;
        //  1002: getstatic       xyz/Melody/Client.lIllllI:[I
        //  1005: bipush          27
        //  1007: iaload         
        //  1008: aaload         
        //  1009: invokedynamic   BootstrapMethod #0, 14:(Ljava/lang/StringBuilder;Ljava/lang/String;)Ljava/lang/StringBuilder;
        //  1014: aload_0         /* lllIlIIIlIIIlII */
        //  1015: invokedynamic   BootstrapMethod #0, 75:(Lxyz/Melody/Client;)I
        //  1020: invokedynamic   BootstrapMethod #0, 76:(Ljava/lang/StringBuilder;I)Ljava/lang/StringBuilder;
        //  1025: invokedynamic   BootstrapMethod #0, 17:(Ljava/lang/StringBuilder;)Ljava/lang/String;
        //  1030: invokespecial   java/lang/Throwable.<init>:(Ljava/lang/String;)V
        //  1033: astore_1        /* lllIlIIIlIIIlll */
        //  1034: getstatic       xyz/Melody/Client.lIllllI:[I
        //  1037: iconst_0       
        //  1038: iaload         
        //  1039: anewarray       Ljava/lang/StackTraceElement;
        //  1042: astore_2        /* lllIlIIIlIIIllI */
        //  1043: aload_1         /* lllIlIIIlIIIlll */
        //  1044: aload_2         /* lllIlIIIlIIIllI */
        //  1045: invokedynamic   BootstrapMethod #0, 77:(Ljava/lang/Throwable;[Ljava/lang/StackTraceElement;)V
        //  1050: invokedynamic   BootstrapMethod #0, 19:()Lnet/minecraft/client/Minecraft;
        //  1055: new             Lnet/minecraft/crash/CrashReport;
        //  1058: dup            
        //  1059: getstatic       xyz/Melody/Client.lIlIllI:[Ljava/lang/String;
        //  1062: getstatic       xyz/Melody/Client.lIllllI:[I
        //  1065: bipush          28
        //  1067: iaload         
        //  1068: aaload         
        //  1069: aload_1         /* lllIlIIIlIIIlll */
        //  1070: invokespecial   net/minecraft/crash/CrashReport.<init>:(Ljava/lang/String;Ljava/lang/Throwable;)V
        //  1073: invokedynamic   BootstrapMethod #0, 78:(Lnet/minecraft/client/Minecraft;Lnet/minecraft/crash/CrashReport;)V
        //  1078: aload_0         /* lllIlIIIlIIIlII */
        //  1079: invokedynamic   BootstrapMethod #0, 12:(Lxyz/Melody/Client;)Lorg/apache/logging/log4j/Logger;
        //  1084: getstatic       xyz/Melody/Client.lIlIllI:[Ljava/lang/String;
        //  1087: getstatic       xyz/Melody/Client.lIllllI:[I
        //  1090: bipush          29
        //  1092: iaload         
        //  1093: aaload         
        //  1094: invokedynamic   BootstrapMethod #0, 13:(Lorg/apache/logging/log4j/Logger;Ljava/lang/String;)V
        //  1099: return         
        //    StackMapTable: 00 01 FB 04 36
        // 
        // The error that occurred was:
        // 
        // java.lang.NullPointerException
        // 
        throw new IllegalStateException("An error occurred while decompiling this method.");
    }
    
    public Client() {
        // invokedynamic(2:(Lxyz/Melody/Client;Lorg/apache/logging/log4j/Logger;)V, this, invokedynamic(1:(Ljava/lang/Class;)Lorg/apache/logging/log4j/Logger;, invokedynamic(0:(Ljava/lang/Object;)Ljava/lang/Class;, this)))
        // invokedynamic(3:(Lxyz/Melody/Client;Lnet/minecraft/client/settings/KeyBinding;)V, this, new KeyBinding(Client.lIlIllI[Client.lIllllI[0]], Client.lIllllI[1], Client.lIlIllI[Client.lIllllI[2]]))
        // invokedynamic(4:(Lxyz/Melody/Client;Ljava/util/Timer;)V, this, new Timer())
        final String[] array = new String[Client.lIllllI[3]];
        array[Client.lIllllI[0]] = Client.lIlIllI[Client.lIllllI[4]];
        array[Client.lIllllI[2]] = Client.lIlIllI[Client.lIllllI[5]];
        array[Client.lIllllI[4]] = Client.lIlIllI[Client.lIllllI[3]];
        array[Client.lIllllI[5]] = Client.lIlIllI[Client.lIllllI[6]];
    }
    // invokedynamic(5:(Lxyz/Melody/Client;[Ljava/lang/String;)V, this, array)
    // invokedynamic(6:(Lxyz/Melody/Client;Z)V, this, Client.lIllllI[0])
    // invokedynamic(7:(Lxyz/Melody/Client;I)V, this, Client.lIllllI[0])
    // invokedynamic(8:(Lxyz/Melody/Client;Lxyz/Melody/Performance/Math/AIImprovements;)V, this, new AIImprovements())
    // invokedynamic(9:(Lxyz/Melody/Client;Lxyz/Melody/MelodyInitializer;)V, this, new MelodyInitializer())
    // invokedynamic(10:(Lxyz/Melody/Client;Lxyz/Melody/Utils/TimerUtil;)V, this, new TimerUtil())
    
    public void stop() {
        // invokedynamic(13:(Lorg/apache/logging/log4j/Logger;Ljava/lang/String;)V, invokedynamic(12:(Lxyz/Melody/Client;)Lorg/apache/logging/log4j/Logger;, this), Client.lIlIllI[Client.lIllllI[60]])
        // invokedynamic(13:(Lorg/apache/logging/log4j/Logger;Ljava/lang/String;)V, invokedynamic(12:(Lxyz/Melody/Client;)Lorg/apache/logging/log4j/Logger;, this), Client.lIlIllI[Client.lIllllI[61]])
        if (lIIIIIIII(invokedynamic(176:(Lxyz/Melody/Client;)Lxyz/Melody/System/Melody/Chat/IRC;, this))) {
        }
        // invokedynamic(177:(Lxyz/Melody/System/Melody/Chat/IRC;Ljava/lang/String;)V, invokedynamic(176:(Lxyz/Melody/Client;)Lxyz/Melody/System/Melody/Chat/IRC;, this), Client.lIlIllI[Client.lIllllI[62]])
        "".length();
        // invokedynamic(11:(Z)V, Client.lIllllI[2])
        // invokedynamic(13:(Lorg/apache/logging/log4j/Logger;Ljava/lang/String;)V, invokedynamic(12:(Lxyz/Melody/Client;)Lorg/apache/logging/log4j/Logger;, this), Client.lIlIllI[Client.lIllllI[63]])
        // invokedynamic(13:(Lorg/apache/logging/log4j/Logger;Ljava/lang/String;)V, invokedynamic(12:(Lxyz/Melody/Client;)Lorg/apache/logging/log4j/Logger;, this), Client.lIlIllI[Client.lIllllI[64]])
        if (lllllllI(invokedynamic(178:(Lxyz/Melody/System/Managers/Client/ModuleManager;)Z, invokedynamic(57:(Lxyz/Melody/Client;)Lxyz/Melody/System/Managers/Client/ModuleManager;, this)))) {
        }
        // invokedynamic(13:(Lorg/apache/logging/log4j/Logger;Ljava/lang/String;)V, invokedynamic(12:(Lxyz/Melody/Client;)Lorg/apache/logging/log4j/Logger;, this), Client.lIlIllI[Client.lIllllI[65]])
        // invokedynamic(179:(Lxyz/Melody/Client;Z)V, this, Client.lIllllI[2])
        // invokedynamic(180:(Lxyz/Melody/Client;)V, this)
        // invokedynamic(181:(Lxyz/Melody/Client;)V, this)
        // invokedynamic(182:(Lxyz/Melody/Client;)V, this)
        // invokedynamic(183:(Lxyz/Melody/Client;Z)V, this, Client.lIllllI[2])
        // invokedynamic(13:(Lorg/apache/logging/log4j/Logger;Ljava/lang/String;)V, invokedynamic(12:(Lxyz/Melody/Client;)Lorg/apache/logging/log4j/Logger;, this), Client.lIlIllI[Client.lIllllI[66]])
    }
    // invokedynamic(184:(Lxyz/Melody/System/Melody/Account/AltManager;)V, invokedynamic(50:(Lxyz/Melody/Client;)Lxyz/Melody/System/Melody/Account/AltManager;, this))
    // invokedynamic(185:()V)
    // invokedynamic(13:(Lorg/apache/logging/log4j/Logger;Ljava/lang/String;)V, invokedynamic(12:(Lxyz/Melody/Client;)Lorg/apache/logging/log4j/Logger;, this), Client.lIlIllI[Client.lIllllI[45]])
    
    private static void llIllIll() {
        (Client.lIlIIII = new String[Client.lIllllI[162]])[Client.lIllllI[163]] = Client.lIlIllI[Client.lIllllI[164]];
        Client.lIlIIII[Client.lIllllI[158]] = Client.lIlIllI[Client.lIllllI[165]];
        Client.lIlIIII[Client.lIllllI[46]] = Client.lIlIllI[Client.lIllllI[166]];
        Client.lIlIIII[Client.lIllllI[42]] = Client.lIlIllI[Client.lIllllI[167]];
        Client.lIlIIII[Client.lIllllI[168]] = Client.lIlIllI[Client.lIllllI[169]];
        Client.lIlIIII[Client.lIllllI[165]] = Client.lIlIllI[Client.lIllllI[170]];
        Client.lIlIIII[Client.lIllllI[146]] = Client.lIlIllI[Client.lIllllI[171]];
        Client.lIlIIII[Client.lIllllI[8]] = Client.lIlIllI[Client.lIllllI[172]];
        Client.lIlIIII[Client.lIllllI[44]] = Client.lIlIllI[Client.lIllllI[173]];
        Client.lIlIIII[Client.lIllllI[92]] = Client.lIlIllI[Client.lIllllI[174]];
        Client.lIlIIII[Client.lIllllI[166]] = Client.lIlIllI[Client.lIllllI[175]];
        Client.lIlIIII[Client.lIllllI[156]] = Client.lIlIllI[Client.lIllllI[176]];
        Client.lIlIIII[Client.lIllllI[65]] = Client.lIlIllI[Client.lIllllI[177]];
        Client.lIlIIII[Client.lIllllI[178]] = Client.lIlIllI[Client.lIllllI[179]];
        Client.lIlIIII[Client.lIllllI[175]] = Client.lIlIllI[Client.lIllllI[180]];
        Client.lIlIIII[Client.lIllllI[67]] = Client.lIlIllI[Client.lIllllI[181]];
        Client.lIlIIII[Client.lIllllI[182]] = Client.lIlIllI[Client.lIllllI[183]];
        Client.lIlIIII[Client.lIllllI[184]] = Client.lIlIllI[Client.lIllllI[185]];
        Client.lIlIIII[Client.lIllllI[186]] = Client.lIlIllI[Client.lIllllI[187]];
        Client.lIlIIII[Client.lIllllI[110]] = Client.lIlIllI[Client.lIllllI[188]];
        Client.lIlIIII[Client.lIllllI[189]] = Client.lIlIllI[Client.lIllllI[190]];
        Client.lIlIIII[Client.lIllllI[187]] = Client.lIlIllI[Client.lIllllI[191]];
        Client.lIlIIII[Client.lIllllI[192]] = Client.lIlIllI[Client.lIllllI[193]];
        Client.lIlIIII[Client.lIllllI[194]] = Client.lIlIllI[Client.lIllllI[195]];
        Client.lIlIIII[Client.lIllllI[83]] = Client.lIlIllI[Client.lIllllI[196]];
        Client.lIlIIII[Client.lIllllI[108]] = Client.lIlIllI[Client.lIllllI[197]];
        Client.lIlIIII[Client.lIllllI[15]] = Client.lIlIllI[Client.lIllllI[198]];
        Client.lIlIIII[Client.lIllllI[80]] = Client.lIlIllI[Client.lIllllI[199]];
        Client.lIlIIII[Client.lIllllI[200]] = Client.lIlIllI[Client.lIllllI[201]];
        Client.lIlIIII[Client.lIllllI[202]] = Client.lIlIllI[Client.lIllllI[203]];
        Client.lIlIIII[Client.lIllllI[199]] = Client.lIlIllI[Client.lIllllI[204]];
        Client.lIlIIII[Client.lIllllI[34]] = Client.lIlIllI[Client.lIllllI[205]];
        Client.lIlIIII[Client.lIllllI[97]] = Client.lIlIllI[Client.lIllllI[200]];
        Client.lIlIIII[Client.lIllllI[169]] = Client.lIlIllI[Client.lIllllI[206]];
        Client.lIlIIII[Client.lIllllI[78]] = Client.lIlIllI[Client.lIllllI[207]];
        Client.lIlIIII[Client.lIllllI[140]] = Client.lIlIllI[Client.lIllllI[208]];
        Client.lIlIIII[Client.lIllllI[209]] = Client.lIlIllI[Client.lIllllI[210]];
        Client.lIlIIII[Client.lIllllI[145]] = Client.lIlIllI[Client.lIllllI[202]];
        Client.lIlIIII[Client.lIllllI[29]] = Client.lIlIllI[Client.lIllllI[211]];
        Client.lIlIIII[Client.lIllllI[212]] = Client.lIlIllI[Client.lIllllI[213]];
        Client.lIlIIII[Client.lIllllI[135]] = Client.lIlIllI[Client.lIllllI[214]];
        Client.lIlIIII[Client.lIllllI[31]] = Client.lIlIllI[Client.lIllllI[215]];
        Client.lIlIIII[Client.lIllllI[39]] = Client.lIlIllI[Client.lIllllI[209]];
        Client.lIlIIII[Client.lIllllI[58]] = Client.lIlIllI[Client.lIllllI[216]];
        Client.lIlIIII[Client.lIllllI[33]] = Client.lIlIllI[Client.lIllllI[163]];
        Client.lIlIIII[Client.lIllllI[7]] = Client.lIlIllI[Client.lIllllI[217]];
        Client.lIlIIII[Client.lIllllI[20]] = Client.lIlIllI[Client.lIllllI[218]];
        Client.lIlIIII[Client.lIllllI[150]] = Client.lIlIllI[Client.lIllllI[219]];
        Client.lIlIIII[Client.lIllllI[220]] = Client.lIlIllI[Client.lIllllI[221]];
        Client.lIlIIII[Client.lIllllI[181]] = Client.lIlIllI[Client.lIllllI[222]];
        Client.lIlIIII[Client.lIllllI[106]] = Client.lIlIllI[Client.lIllllI[223]];
        Client.lIlIIII[Client.lIllllI[143]] = Client.lIlIllI[Client.lIllllI[224]];
        Client.lIlIIII[Client.lIllllI[30]] = Client.lIlIllI[Client.lIllllI[184]];
        Client.lIlIIII[Client.lIllllI[130]] = Client.lIlIllI[Client.lIllllI[225]];
        Client.lIlIIII[Client.lIllllI[37]] = Client.lIlIllI[Client.lIllllI[168]];
        Client.lIlIIII[Client.lIllllI[144]] = Client.lIlIllI[Client.lIllllI[226]];
        Client.lIlIIII[Client.lIllllI[227]] = Client.lIlIllI[Client.lIllllI[228]];
        Client.lIlIIII[Client.lIllllI[19]] = Client.lIlIllI[Client.lIllllI[229]];
        Client.lIlIIII[Client.lIllllI[3]] = Client.lIlIllI[Client.lIllllI[230]];
        Client.lIlIIII[Client.lIllllI[77]] = Client.lIlIllI[Client.lIllllI[231]];
        Client.lIlIIII[Client.lIllllI[232]] = Client.lIlIllI[Client.lIllllI[233]];
        Client.lIlIIII[Client.lIllllI[132]] = Client.lIlIllI[Client.lIllllI[234]];
        Client.lIlIIII[Client.lIllllI[216]] = Client.lIlIllI[Client.lIllllI[212]];
        Client.lIlIIII[Client.lIllllI[137]] = Client.lIlIllI[Client.lIllllI[235]];
        Client.lIlIIII[Client.lIllllI[236]] = Client.lIlIllI[Client.lIllllI[237]];
        Client.lIlIIII[Client.lIllllI[41]] = Client.lIlIllI[Client.lIllllI[238]];
        Client.lIlIIII[Client.lIllllI[174]] = Client.lIlIllI[Client.lIllllI[192]];
        Client.lIlIIII[Client.lIllllI[48]] = Client.lIlIllI[Client.lIllllI[178]];
        Client.lIlIIII[Client.lIllllI[56]] = Client.lIlIllI[Client.lIllllI[194]];
        Client.lIlIIII[Client.lIllllI[201]] = Client.lIlIllI[Client.lIllllI[239]];
        Client.lIlIIII[Client.lIllllI[24]] = Client.lIlIllI[Client.lIllllI[240]];
        Client.lIlIIII[Client.lIllllI[157]] = Client.lIlIllI[Client.lIllllI[241]];
        Client.lIlIIII[Client.lIllllI[102]] = Client.lIlIllI[Client.lIllllI[242]];
        Client.lIlIIII[Client.lIllllI[45]] = Client.lIlIllI[Client.lIllllI[189]];
        Client.lIlIIII[Client.lIllllI[205]] = Client.lIlIllI[Client.lIllllI[227]];
        Client.lIlIIII[Client.lIllllI[243]] = Client.lIlIllI[Client.lIllllI[244]];
        Client.lIlIIII[Client.lIllllI[245]] = Client.lIlIllI[Client.lIllllI[246]];
        Client.lIlIIII[Client.lIllllI[142]] = Client.lIlIllI[Client.lIllllI[247]];
        Client.lIlIIII[Client.lIllllI[154]] = Client.lIlIllI[Client.lIllllI[248]];
        Client.lIlIIII[Client.lIllllI[217]] = Client.lIlIllI[Client.lIllllI[249]];
        Client.lIlIIII[Client.lIllllI[72]] = Client.lIlIllI[Client.lIllllI[186]];
        Client.lIlIIII[Client.lIllllI[161]] = Client.lIlIllI[Client.lIllllI[236]];
        Client.lIlIIII[Client.lIllllI[237]] = Client.lIlIllI[Client.lIllllI[250]];
        Client.lIlIIII[Client.lIllllI[147]] = Client.lIlIllI[Client.lIllllI[251]];
        Client.lIlIIII[Client.lIllllI[249]] = Client.lIlIllI[Client.lIllllI[252]];
        Client.lIlIIII[Client.lIllllI[190]] = Client.lIlIllI[Client.lIllllI[253]];
        Client.lIlIIII[Client.lIllllI[234]] = Client.lIlIllI[Client.lIllllI[243]];
        Client.lIlIIII[Client.lIllllI[239]] = Client.lIlIllI[Client.lIllllI[232]];
        Client.lIlIIII[Client.lIllllI[9]] = Client.lIlIllI[Client.lIllllI[254]];
        Client.lIlIIII[Client.lIllllI[241]] = Client.lIlIllI[Client.lIllllI[255]];
        Client.lIlIIII[Client.lIllllI[152]] = Client.lIlIllI[Client.lIllllI[256]];
        Client.lIlIIII[Client.lIllllI[185]] = Client.lIlIllI[Client.lIllllI[182]];
        Client.lIlIIII[Client.lIllllI[253]] = Client.lIlIllI[Client.lIllllI[220]];
        Client.lIlIIII[Client.lIllllI[229]] = Client.lIlIllI[Client.lIllllI[257]];
        Client.lIlIIII[Client.lIllllI[255]] = Client.lIlIllI[Client.lIllllI[258]];
        Client.lIlIIII[Client.lIllllI[226]] = Client.lIlIllI[Client.lIllllI[245]];
        Client.lIlIIII[Client.lIllllI[122]] = Client.lIlIllI[Client.lIllllI[162]];
        Client.lIlIIII[Client.lIllllI[116]] = Client.lIlIllI[Client.lIllllI[259]];
        Client.lIlIIII[Client.lIllllI[111]] = Client.lIlIllI[Client.lIllllI[260]];
        Client.lIlIIII[Client.lIllllI[61]] = Client.lIlIllI[Client.lIllllI[261]];
        Client.lIlIIII[Client.lIllllI[131]] = Client.lIlIllI[Client.lIllllI[262]];
        Client.lIlIIII[Client.lIllllI[223]] = Client.lIlIllI[Client.lIllllI[263]];
        Client.lIlIIII[Client.lIllllI[95]] = Client.lIlIllI[Client.lIllllI[264]];
        Client.lIlIIII[Client.lIllllI[17]] = Client.lIlIllI[Client.lIllllI[265]];
        Client.lIlIIII[Client.lIllllI[43]] = Client.lIlIllI[Client.lIllllI[266]];
        Client.lIlIIII[Client.lIllllI[167]] = Client.lIlIllI[Client.lIllllI[267]];
        Client.lIlIIII[Client.lIllllI[76]] = Client.lIlIllI[Client.lIllllI[268]];
        Client.lIlIIII[Client.lIllllI[4]] = Client.lIlIllI[Client.lIllllI[269]];
        Client.lIlIIII[Client.lIllllI[89]] = Client.lIlIllI[Client.lIllllI[270]];
        Client.lIlIIII[Client.lIllllI[250]] = Client.lIlIllI[Client.lIllllI[271]];
        Client.lIlIIII[Client.lIllllI[197]] = Client.lIlIllI[Client.lIllllI[272]];
        Client.lIlIIII[Client.lIllllI[125]] = Client.lIlIllI[Client.lIllllI[273]];
        Client.lIlIIII[Client.lIllllI[160]] = Client.lIlIllI[Client.lIllllI[274]];
        Client.lIlIIII[Client.lIllllI[71]] = Client.lIlIllI[Client.lIllllI[275]];
        Client.lIlIIII[Client.lIllllI[134]] = Client.lIlIllI[Client.lIllllI[276]];
        Client.lIlIIII[Client.lIllllI[62]] = Client.lIlIllI[Client.lIllllI[277]];
        Client.lIlIIII[Client.lIllllI[248]] = Client.lIlIllI[Client.lIllllI[278]];
        Client.lIlIIII[Client.lIllllI[127]] = Client.lIlIllI[Client.lIllllI[279]];
        Client.lIlIIII[Client.lIllllI[128]] = Client.lIlIllI[Client.lIllllI[280]];
        Client.lIlIIII[Client.lIllllI[53]] = Client.lIlIllI[Client.lIllllI[281]];
        Client.lIlIIII[Client.lIllllI[94]] = Client.lIlIllI[Client.lIllllI[282]];
        Client.lIlIIII[Client.lIllllI[112]] = Client.lIlIllI[Client.lIllllI[283]];
        Client.lIlIIII[Client.lIllllI[141]] = Client.lIlIllI[Client.lIllllI[284]];
        Client.lIlIIII[Client.lIllllI[193]] = Client.lIlIllI[Client.lIllllI[285]];
        Client.lIlIIII[Client.lIllllI[16]] = Client.lIlIllI[Client.lIllllI[286]];
        Client.lIlIIII[Client.lIllllI[119]] = Client.lIlIllI[Client.lIllllI[287]];
        Client.lIlIIII[Client.lIllllI[26]] = Client.lIlIllI[Client.lIllllI[288]];
        Client.lIlIIII[Client.lIllllI[2]] = Client.lIlIllI[Client.lIllllI[289]];
        Client.lIlIIII[Client.lIllllI[13]] = Client.lIlIllI[Client.lIllllI[290]];
        Client.lIlIIII[Client.lIllllI[10]] = Client.lIlIllI[Client.lIllllI[291]];
        Client.lIlIIII[Client.lIllllI[155]] = Client.lIlIllI[Client.lIllllI[292]];
        Client.lIlIIII[Client.lIllllI[96]] = Client.lIlIllI[Client.lIllllI[293]];
        Client.lIlIIII[Client.lIllllI[129]] = Client.lIlIllI[Client.lIllllI[294]];
        Client.lIlIIII[Client.lIllllI[228]] = Client.lIlIllI[Client.lIllllI[295]];
        Client.lIlIIII[Client.lIllllI[171]] = Client.lIlIllI[Client.lIllllI[296]];
        Client.lIlIIII[Client.lIllllI[27]] = Client.lIlIllI[Client.lIllllI[297]];
        Client.lIlIIII[Client.lIllllI[120]] = Client.lIlIllI[Client.lIllllI[298]];
        Client.lIlIIII[Client.lIllllI[153]] = Client.lIlIllI[Client.lIllllI[299]];
        Client.lIlIIII[Client.lIllllI[176]] = Client.lIlIllI[Client.lIllllI[300]];
        Client.lIlIIII[Client.lIllllI[74]] = Client.lIlIllI[Client.lIllllI[301]];
        Client.lIlIIII[Client.lIllllI[215]] = Client.lIlIllI[Client.lIllllI[302]];
        Client.lIlIIII[Client.lIllllI[124]] = Client.lIlIllI[Client.lIllllI[303]];
        Client.lIlIIII[Client.lIllllI[66]] = Client.lIlIllI[Client.lIllllI[304]];
        Client.lIlIIII[Client.lIllllI[225]] = Client.lIlIllI[Client.lIllllI[305]];
        Client.lIlIIII[Client.lIllllI[257]] = Client.lIlIllI[Client.lIllllI[306]];
        Client.lIlIIII[Client.lIllllI[69]] = Client.lIlIllI[Client.lIllllI[307]];
        Client.lIlIIII[Client.lIllllI[101]] = Client.lIlIllI[Client.lIllllI[308]];
        Client.lIlIIII[Client.lIllllI[70]] = Client.lIlIllI[Client.lIllllI[309]];
        Client.lIlIIII[Client.lIllllI[54]] = Client.lIlIllI[Client.lIllllI[310]];
        Client.lIlIIII[Client.lIllllI[204]] = Client.lIlIllI[Client.lIllllI[311]];
        Client.lIlIIII[Client.lIllllI[103]] = Client.lIlIllI[Client.lIllllI[312]];
        Client.lIlIIII[Client.lIllllI[28]] = Client.lIlIllI[Client.lIllllI[313]];
        Client.lIlIIII[Client.lIllllI[188]] = Client.lIlIllI[Client.lIllllI[314]];
        Client.lIlIIII[Client.lIllllI[244]] = Client.lIlIllI[Client.lIllllI[315]];
        Client.lIlIIII[Client.lIllllI[36]] = Client.lIlIllI[Client.lIllllI[316]];
        Client.lIlIIII[Client.lIllllI[73]] = Client.lIlIllI[Client.lIllllI[317]];
        Client.lIlIIII[Client.lIllllI[87]] = Client.lIlIllI[Client.lIllllI[318]];
        Client.lIlIIII[Client.lIllllI[139]] = Client.lIlIllI[Client.lIllllI[319]];
        Client.lIlIIII[Client.lIllllI[149]] = Client.lIlIllI[Client.lIllllI[320]];
        Client.lIlIIII[Client.lIllllI[231]] = Client.lIlIllI[Client.lIllllI[321]];
        Client.lIlIIII[Client.lIllllI[173]] = Client.lIlIllI[Client.lIllllI[322]];
        Client.lIlIIII[Client.lIllllI[18]] = Client.lIlIllI[Client.lIllllI[323]];
        Client.lIlIIII[Client.lIllllI[235]] = Client.lIlIllI[Client.lIllllI[324]];
        Client.lIlIIII[Client.lIllllI[224]] = Client.lIlIllI[Client.lIllllI[325]];
        Client.lIlIIII[Client.lIllllI[117]] = Client.lIlIllI[Client.lIllllI[326]];
        Client.lIlIIII[Client.lIllllI[203]] = Client.lIlIllI[Client.lIllllI[327]];
        Client.lIlIIII[Client.lIllllI[113]] = Client.lIlIllI[Client.lIllllI[328]];
        Client.lIlIIII[Client.lIllllI[191]] = Client.lIlIllI[Client.lIllllI[329]];
        Client.lIlIIII[Client.lIllllI[238]] = Client.lIlIllI[Client.lIllllI[330]];
        Client.lIlIIII[Client.lIllllI[55]] = Client.lIlIllI[Client.lIllllI[331]];
        Client.lIlIIII[Client.lIllllI[230]] = Client.lIlIllI[Client.lIllllI[332]];
        Client.lIlIIII[Client.lIllllI[104]] = Client.lIlIllI[Client.lIllllI[333]];
        Client.lIlIIII[Client.lIllllI[242]] = Client.lIlIllI[Client.lIllllI[334]];
        Client.lIlIIII[Client.lIllllI[49]] = Client.lIlIllI[Client.lIllllI[335]];
        Client.lIlIIII[Client.lIllllI[60]] = Client.lIlIllI[Client.lIllllI[336]];
        Client.lIlIIII[Client.lIllllI[219]] = Client.lIlIllI[Client.lIllllI[337]];
        Client.lIlIIII[Client.lIllllI[256]] = Client.lIlIllI[Client.lIllllI[338]];
        Client.lIlIIII[Client.lIllllI[59]] = Client.lIlIllI[Client.lIllllI[339]];
        Client.lIlIIII[Client.lIllllI[50]] = Client.lIlIllI[Client.lIllllI[340]];
        Client.lIlIIII[Client.lIllllI[68]] = Client.lIlIllI[Client.lIllllI[341]];
        Client.lIlIIII[Client.lIllllI[47]] = Client.lIlIllI[Client.lIllllI[342]];
        Client.lIlIIII[Client.lIllllI[180]] = Client.lIlIllI[Client.lIllllI[343]];
        Client.lIlIIII[Client.lIllllI[105]] = Client.lIlIllI[Client.lIllllI[344]];
        Client.lIlIIII[Client.lIllllI[82]] = Client.lIlIllI[Client.lIllllI[345]];
        Client.lIlIIII[Client.lIllllI[170]] = Client.lIlIllI[Client.lIllllI[346]];
        Client.lIlIIII[Client.lIllllI[118]] = Client.lIlIllI[Client.lIllllI[347]];
        Client.lIlIIII[Client.lIllllI[213]] = Client.lIlIllI[Client.lIllllI[348]];
        Client.lIlIIII[Client.lIllllI[109]] = Client.lIlIllI[Client.lIllllI[349]];
        Client.lIlIIII[Client.lIllllI[52]] = Client.lIlIllI[Client.lIllllI[350]];
        Client.lIlIIII[Client.lIllllI[179]] = Client.lIlIllI[Client.lIllllI[351]];
        Client.lIlIIII[Client.lIllllI[246]] = Client.lIlIllI[Client.lIllllI[352]];
        Client.lIlIIII[Client.lIllllI[85]] = Client.lIlIllI[Client.lIllllI[353]];
        Client.lIlIIII[Client.lIllllI[240]] = Client.lIlIllI[Client.lIllllI[354]];
        Client.lIlIIII[Client.lIllllI[148]] = Client.lIlIllI[Client.lIllllI[355]];
        Client.lIlIIII[Client.lIllllI[5]] = Client.lIlIllI[Client.lIllllI[356]];
        Client.lIlIIII[Client.lIllllI[11]] = Client.lIlIllI[Client.lIllllI[357]];
        Client.lIlIIII[Client.lIllllI[114]] = Client.lIlIllI[Client.lIllllI[358]];
        Client.lIlIIII[Client.lIllllI[233]] = Client.lIlIllI[Client.lIllllI[359]];
        Client.lIlIIII[Client.lIllllI[222]] = Client.lIlIllI[Client.lIllllI[360]];
        Client.lIlIIII[Client.lIllllI[25]] = Client.lIlIllI[Client.lIllllI[361]];
        Client.lIlIIII[Client.lIllllI[98]] = Client.lIlIllI[Client.lIllllI[362]];
        Client.lIlIIII[Client.lIllllI[177]] = Client.lIlIllI[Client.lIllllI[363]];
        Client.lIlIIII[Client.lIllllI[6]] = Client.lIlIllI[Client.lIllllI[364]];
        Client.lIlIIII[Client.lIllllI[172]] = Client.lIlIllI[Client.lIllllI[365]];
        Client.lIlIIII[Client.lIllllI[22]] = Client.lIlIllI[Client.lIllllI[366]];
        Client.lIlIIII[Client.lIllllI[32]] = Client.lIlIllI[Client.lIllllI[367]];
        Client.lIlIIII[Client.lIllllI[79]] = Client.lIlIllI[Client.lIllllI[368]];
        Client.lIlIIII[Client.lIllllI[100]] = Client.lIlIllI[Client.lIllllI[369]];
        Client.lIlIIII[Client.lIllllI[1]] = Client.lIlIllI[Client.lIllllI[370]];
        Client.lIlIIII[Client.lIllllI[14]] = Client.lIlIllI[Client.lIllllI[371]];
        Client.lIlIIII[Client.lIllllI[99]] = Client.lIlIllI[Client.lIllllI[372]];
        Client.lIlIIII[Client.lIllllI[93]] = Client.lIlIllI[Client.lIllllI[373]];
        Client.lIlIIII[Client.lIllllI[218]] = Client.lIlIllI[Client.lIllllI[374]];
        Client.lIlIIII[Client.lIllllI[90]] = Client.lIlIllI[Client.lIllllI[375]];
        Client.lIlIIII[Client.lIllllI[211]] = Client.lIlIllI[Client.lIllllI[376]];
        Client.lIlIIII[Client.lIllllI[207]] = Client.lIlIllI[Client.lIllllI[377]];
        Client.lIlIIII[Client.lIllllI[35]] = Client.lIlIllI[Client.lIllllI[378]];
        Client.lIlIIII[Client.lIllllI[75]] = Client.lIlIllI[Client.lIllllI[379]];
        Client.lIlIIII[Client.lIllllI[126]] = Client.lIlIllI[Client.lIllllI[380]];
        Client.lIlIIII[Client.lIllllI[196]] = Client.lIlIllI[Client.lIllllI[381]];
        Client.lIlIIII[Client.lIllllI[40]] = Client.lIlIllI[Client.lIllllI[382]];
        Client.lIlIIII[Client.lIllllI[107]] = Client.lIlIllI[Client.lIllllI[383]];
        Client.lIlIIII[Client.lIllllI[133]] = Client.lIlIllI[Client.lIllllI[384]];
        Client.lIlIIII[Client.lIllllI[151]] = Client.lIlIllI[Client.lIllllI[385]];
        Client.lIlIIII[Client.lIllllI[88]] = Client.lIlIllI[Client.lIllllI[386]];
        Client.lIlIIII[Client.lIllllI[81]] = Client.lIlIllI[Client.lIllllI[387]];
        Client.lIlIIII[Client.lIllllI[0]] = Client.lIlIllI[Client.lIllllI[388]];
        Client.lIlIIII[Client.lIllllI[123]] = Client.lIlIllI[Client.lIllllI[389]];
        Client.lIlIIII[Client.lIllllI[38]] = Client.lIlIllI[Client.lIllllI[390]];
        Client.lIlIIII[Client.lIllllI[159]] = Client.lIlIllI[Client.lIllllI[391]];
        Client.lIlIIII[Client.lIllllI[86]] = Client.lIlIllI[Client.lIllllI[392]];
        Client.lIlIIII[Client.lIllllI[51]] = Client.lIlIllI[Client.lIllllI[393]];
        Client.lIlIIII[Client.lIllllI[183]] = Client.lIlIllI[Client.lIllllI[394]];
        Client.lIlIIII[Client.lIllllI[84]] = Client.lIlIllI[Client.lIllllI[395]];
        Client.lIlIIII[Client.lIllllI[115]] = Client.lIlIllI[Client.lIllllI[396]];
        Client.lIlIIII[Client.lIllllI[136]] = Client.lIlIllI[Client.lIllllI[397]];
        Client.lIlIIII[Client.lIllllI[258]] = Client.lIlIllI[Client.lIllllI[398]];
        Client.lIlIIII[Client.lIllllI[210]] = Client.lIlIllI[Client.lIllllI[399]];
        Client.lIlIIII[Client.lIllllI[198]] = Client.lIlIllI[Client.lIllllI[400]];
        Client.lIlIIII[Client.lIllllI[252]] = Client.lIlIllI[Client.lIllllI[401]];
        Client.lIlIIII[Client.lIllllI[251]] = Client.lIlIllI[Client.lIllllI[402]];
        Client.lIlIIII[Client.lIllllI[21]] = Client.lIlIllI[Client.lIllllI[403]];
        Client.lIlIIII[Client.lIllllI[12]] = Client.lIlIllI[Client.lIllllI[404]];
        Client.lIlIIII[Client.lIllllI[221]] = Client.lIlIllI[Client.lIllllI[405]];
        Client.lIlIIII[Client.lIllllI[208]] = Client.lIlIllI[Client.lIllllI[406]];
        Client.lIlIIII[Client.lIllllI[164]] = Client.lIlIllI[Client.lIllllI[407]];
        Client.lIlIIII[Client.lIllllI[247]] = Client.lIlIllI[Client.lIllllI[408]];
        Client.lIlIIII[Client.lIllllI[254]] = Client.lIlIllI[Client.lIllllI[409]];
        Client.lIlIIII[Client.lIllllI[64]] = Client.lIlIllI[Client.lIllllI[410]];
        Client.lIlIIII[Client.lIllllI[195]] = Client.lIlIllI[Client.lIllllI[411]];
        Client.lIlIIII[Client.lIllllI[138]] = Client.lIlIllI[Client.lIllllI[412]];
        Client.lIlIIII[Client.lIllllI[214]] = Client.lIlIllI[Client.lIllllI[413]];
        Client.lIlIIII[Client.lIllllI[206]] = Client.lIlIllI[Client.lIllllI[414]];
        Client.lIlIIII[Client.lIllllI[23]] = Client.lIlIllI[Client.lIllllI[415]];
        Client.lIlIIII[Client.lIllllI[121]] = Client.lIlIllI[Client.lIllllI[416]];
        Client.lIlIIII[Client.lIllllI[63]] = Client.lIlIllI[Client.lIllllI[417]];
        (Client.lIlIIIl = new Class[Client.lIllllI[50]])[Client.lIllllI[39]] = Option.class;
        Client.lIlIIIl[Client.lIllllI[47]] = MouseHelper.class;
        Client.lIlIIIl[Client.lIllllI[7]] = AIImprovements.class;
        Client.lIlIIIl[Client.lIllllI[24]] = EventBus.class;
        Client.lIlIIIl[Client.lIllllI[22]] = SkyblockArea.class;
        Client.lIlIIIl[Client.lIllllI[34]] = EntityLivingBase.class;
        Client.lIlIIIl[Client.lIllllI[49]] = ArrayList.class;
        Client.lIlIIIl[Client.lIllllI[42]] = HashMap.class;
        Client.lIlIIIl[Client.lIllllI[43]] = List.class;
        Client.lIlIIIl[Client.lIllllI[0]] = Logger.class;
        Client.lIlIIIl[Client.lIllllI[25]] = ClientCommandHandler.class;
        Client.lIlIIIl[Client.lIllllI[46]] = IRC.class;
        Client.lIlIIIl[Client.lIllllI[40]] = String.class;
        Client.lIlIIIl[Client.lIllllI[35]] = Double.TYPE;
        Client.lIlIIIl[Client.lIllllI[14]] = CommandManager.class;
        Client.lIlIIIl[Client.lIllllI[48]] = GameSettings.class;
        Client.lIlIIIl[Client.lIllllI[3]] = Boolean.TYPE;
        Client.lIlIIIl[Client.lIllllI[17]] = HUDManager.class;
        Client.lIlIIIl[Client.lIllllI[12]] = Session.class;
        Client.lIlIIIl[Client.lIllllI[9]] = TimerUtil.class;
        Client.lIlIIIl[Client.lIllllI[44]] = GuiIngame.class;
        Client.lIlIIIl[Client.lIllllI[18]] = ModuleManager.class;
        Client.lIlIIIl[Client.lIllllI[10]] = Charset.class;
        Client.lIlIIIl[Client.lIllllI[36]] = FontRenderer.class;
        Client.lIlIIIl[Client.lIllllI[32]] = Float.TYPE;
        Client.lIlIIIl[Client.lIllllI[5]] = String[].class;
        Client.lIlIIIl[Client.lIllllI[23]] = Thread.class;
        Client.lIlIIIl[Client.lIllllI[28]] = FoamFixConfig.class;
        Client.lIlIIIl[Client.lIllllI[21]] = Client.class;
        Client.lIlIIIl[Client.lIllllI[2]] = KeyBinding.class;
        Client.lIlIIIl[Client.lIllllI[20]] = MimicListener.class;
        Client.lIlIIIl[Client.lIllllI[37]] = RendererLivingEntity.class;
        Client.lIlIIIl[Client.lIllllI[30]] = EntityPlayerSP.class;
        Client.lIlIIIl[Client.lIllllI[6]] = Integer.TYPE;
        Client.lIlIIIl[Client.lIllllI[41]] = Configuration.class;
        Client.lIlIIIl[Client.lIllllI[13]] = AuthManager.class;
        Client.lIlIIIl[Client.lIllllI[27]] = IFoamFixHelper.class;
        Client.lIlIIIl[Client.lIllllI[11]] = Minecraft.class;
        Client.lIlIIIl[Client.lIllllI[4]] = Timer.class;
        Client.lIlIIIl[Client.lIllllI[38]] = EnumChatFormatting.class;
        Client.lIlIIIl[Client.lIllllI[19]] = DungeonListener.class;
        Client.lIlIIIl[Client.lIllllI[16]] = AltManager.class;
        Client.lIlIIIl[Client.lIllllI[8]] = MelodyInitializer.class;
        Client.lIlIIIl[Client.lIllllI[33]] = ModuleType.class;
        Client.lIlIIIl[Client.lIllllI[29]] = ProxyCommon.class;
        Client.lIlIIIl[Client.lIllllI[31]] = WorldClient.class;
        Client.lIlIIIl[Client.lIllllI[15]] = FriendManager.class;
    }
    
    public void saveUISettings(final boolean lllIIllIlIlIIIl) {
        String lllIIllIlIlIIll = Client.lIlIllI[Client.lIllllI[96]];
        final byte lllIIllIlIIllll = invokedynamic(216:(Ljava/util/ArrayList;)Ljava/util/Iterator;, invokedynamic(215:()Ljava/util/ArrayList;));
        while (llllllIl(invokedynamic(121:(Ljava/util/Iterator;)Z, lllIIllIlIIllll))) {
            final long lllIIllIlIIllIl;
            final String lllIIllIlIlIllI = (String)(lllIIllIlIIllIl = (long)(String)invokedynamic(122:(Ljava/util/Iterator;)Ljava/lang/Object;, lllIIllIlIIllll));
            int lllIIllIlIIllII = Client.lIllllI[91];
            switch (invokedynamic(211:(Ljava/lang/String;)I, lllIIllIlIIllIl)) {
                case -2072873435: {
                    if (!llllllIl(invokedynamic(79:(Ljava/lang/String;Ljava/lang/Object;)Z, lllIIllIlIIllIl, Client.lIlIllI[Client.lIllllI[97]]))) {
                        break;
                    }
                    lllIIllIlIIllII = Client.lIllllI[0];
                    "".length();
                    if (-" ".length() >= 0) {
                        return;
                    }
                    break;
                }
                case -950372698: {
                    if (!llllllIl(invokedynamic(79:(Ljava/lang/String;Ljava/lang/Object;)Z, lllIIllIlIIllIl, Client.lIlIllI[Client.lIllllI[98]]))) {
                        break;
                    }
                    lllIIllIlIIllII = Client.lIllllI[2];
                    "".length();
                    if (" ".length() << (" ".length() << " ".length()) > " ".length() << (" ".length() << " ".length())) {
                        return;
                    }
                    break;
                }
                case 783533026: {
                    if (llllllIl(invokedynamic(79:(Ljava/lang/String;Ljava/lang/Object;)Z, lllIIllIlIIllIl, Client.lIlIllI[Client.lIllllI[99]]))) {
                        lllIIllIlIIllII = Client.lIllllI[4];
                        break;
                    }
                    break;
                }
            }
            switch (lllIIllIlIIllII) {
                case 0: {
                    if (!lllllllI(invokedynamic(217:()Z))) {
                        break;
                    }
                    final StringBuilder sb = invokedynamic(14:(Ljava/lang/StringBuilder;Ljava/lang/String;)Ljava/lang/StringBuilder;, new StringBuilder(), invokedynamic(218:(Ljava/lang/Object;)Ljava/lang/String;, lllIIllIlIlIIll));
                    final String s = Client.lIlIllI[Client.lIllllI[100]];
                    final Object[] array = new Object[Client.lIllllI[4]];
                    array[Client.lIllllI[0]] = Client.lIlIllI[Client.lIllllI[101]];
                    array[Client.lIllllI[2]] = invokedynamic(219:()Ljava/lang/String;);
                    lllIIllIlIlIIll = invokedynamic(17:(Ljava/lang/StringBuilder;)Ljava/lang/String;, invokedynamic(14:(Ljava/lang/StringBuilder;Ljava/lang/String;)Ljava/lang/StringBuilder;, sb, invokedynamic(220:(Ljava/lang/String;[Ljava/lang/Object;)Ljava/lang/String;, s, array)));
                    "".length();
                    if (-" ".length() == " ".length() << (" ".length() << " ".length())) {
                        return;
                    }
                    break;
                }
                case 1: {
                    if (!lllllllI(invokedynamic(221:()Z))) {
                        break;
                    }
                    final StringBuilder sb2 = invokedynamic(14:(Ljava/lang/StringBuilder;Ljava/lang/String;)Ljava/lang/StringBuilder;, new StringBuilder(), invokedynamic(218:(Ljava/lang/Object;)Ljava/lang/String;, lllIIllIlIlIIll));
                    final String s2 = Client.lIlIllI[Client.lIllllI[102]];
                    final Object[] array2 = new Object[Client.lIllllI[4]];
                    array2[Client.lIllllI[0]] = Client.lIlIllI[Client.lIllllI[58]];
                    array2[Client.lIllllI[2]] = invokedynamic(219:()Ljava/lang/String;);
                    lllIIllIlIlIIll = invokedynamic(17:(Ljava/lang/StringBuilder;)Ljava/lang/String;, invokedynamic(14:(Ljava/lang/StringBuilder;Ljava/lang/String;)Ljava/lang/StringBuilder;, sb2, invokedynamic(220:(Ljava/lang/String;[Ljava/lang/Object;)Ljava/lang/String;, s2, array2)));
                    "".length();
                    if ("   ".length() == 0) {
                        return;
                    }
                    break;
                }
                case 2: {
                    if (lllllllI(invokedynamic(222:()Z))) {
                        final StringBuilder sb3 = invokedynamic(14:(Ljava/lang/StringBuilder;Ljava/lang/String;)Ljava/lang/StringBuilder;, new StringBuilder(), invokedynamic(218:(Ljava/lang/Object;)Ljava/lang/String;, lllIIllIlIlIIll));
                        final String s3 = Client.lIlIllI[Client.lIllllI[103]];
                        final Object[] array3 = new Object[Client.lIllllI[4]];
                        array3[Client.lIllllI[0]] = Client.lIlIllI[Client.lIllllI[104]];
                        array3[Client.lIllllI[2]] = invokedynamic(219:()Ljava/lang/String;);
                        lllIIllIlIlIIll = invokedynamic(17:(Ljava/lang/StringBuilder;)Ljava/lang/String;, invokedynamic(14:(Ljava/lang/StringBuilder;Ljava/lang/String;)Ljava/lang/StringBuilder;, sb3, invokedynamic(220:(Ljava/lang/String;[Ljava/lang/Object;)Ljava/lang/String;, s3, array3)));
                        break;
                    }
                    break;
                }
            }
            "".length();
            if (((0xB8 ^ 0xA1) << " ".length() & ~((0x5A ^ 0x43) << " ".length())) >= "   ".length()) {
                return;
            }
        }
        // invokedynamic(207:(Ljava/lang/String;Ljava/lang/String;Z)V, Client.lIlIllI[Client.lIllllI[105]], lllIIllIlIlIIll, Client.lIllllI[0])
        if (llllllIl(lllIIllIlIlIIIl ? 1 : 0)) {
        }
        // invokedynamic(13:(Lorg/apache/logging/log4j/Logger;Ljava/lang/String;)V, invokedynamic(12:(Lxyz/Melody/Client;)Lorg/apache/logging/log4j/Logger;, this), Client.lIlIllI[Client.lIllllI[106]])
    }
    
    public void auth() {
        this.superAss();
    }
    
    private static void lllIlIIl() {
        final long lllIIlIlIllIllI = (long)new Exception().getStackTrace()[Client.lIllllI[0]].getFileName();
        Client.lIlllII = ((String)lllIIlIlIllIllI).substring(((String)lllIIlIlIllIllI).indexOf("\u00e4") + Client.lIllllI[2], ((String)lllIIlIlIllIllI).lastIndexOf("\u00fc")).split("\u00f6");
    }
    
    public static void ungrabMouse() {
        final class lI extends MouseHelper
        {
            public void mouseXYChange() {
            }
            
            public void grabMouseCursor() {
                Client.access$102(false);
            }
            
            public void ungrabMouseCursor() {
                Client.access$102(true);
            }
        }
        // 
        // This method could not be decompiled.
        // 
        // Original Bytecode:
        // 
        //     5: invokedynamic   BootstrapMethod #0, 191:(Lnet/minecraft/client/Minecraft;)Z
        //    10: invokestatic    xyz/Melody/Client.llllllIl:(I)Z
        //    13: ifeq            27
        //    16: invokedynamic   BootstrapMethod #0, 192:()Z
        //    21: invokestatic    xyz/Melody/Client.llllllIl:(I)Z
        //    24: ifeq            28
        //    27: return         
        //    28: invokedynamic   BootstrapMethod #0, 193:()Lnet/minecraft/util/MouseHelper;
        //    33: invokestatic    xyz/Melody/Client.lIIIIIlIl:(Ljava/lang/Object;)Z
        //    36: ifeq            54
        //    39: invokedynamic   BootstrapMethod #0, 19:()Lnet/minecraft/client/Minecraft;
        //    44: invokedynamic   BootstrapMethod #0, 194:(Lnet/minecraft/client/Minecraft;)Lnet/minecraft/util/MouseHelper;
        //    49: invokedynamic   BootstrapMethod #0, 195:(Lnet/minecraft/util/MouseHelper;)V
        //    54: invokedynamic   BootstrapMethod #0, 19:()Lnet/minecraft/client/Minecraft;
        //    59: invokedynamic   BootstrapMethod #0, 196:(Lnet/minecraft/client/Minecraft;)Lnet/minecraft/client/settings/GameSettings;
        //    64: getstatic       xyz/Melody/Client.lIllllI:[I
        //    67: iconst_0       
        //    68: iaload         
        //    69: putfield        net/minecraft/client/settings/GameSettings.pauseOnLostFocus:Z
        //    72: invokedynamic   BootstrapMethod #0, 197:()Z
        //    77: invokestatic    xyz/Melody/Client.lllllllI:(I)Z
        //    80: ifeq            124
        //    83: getstatic       xyz/Melody/Client.lIllllI:[I
        //    86: iconst_2       
        //    87: iaload         
        //    88: ldc             ""
        //    90: invokevirtual   java/lang/String.length:()I
        //    93: pop            
        //    94: sipush          207
        //    97: sipush          192
        //   100: ixor           
        //   101: bipush          70
        //   103: bipush          73
        //   105: ixor           
        //   106: iconst_m1      
        //   107: ixor           
        //   108: iand           
        //   109: ldc             " "
        //   111: invokevirtual   java/lang/String.length:()I
        //   114: ldc             " "
        //   116: invokevirtual   java/lang/String.length:()I
        //   119: ishl           
        //   120: if_icmple       129
        //   123: return         
        //   124: getstatic       xyz/Melody/Client.lIllllI:[I
        //   127: iconst_0       
        //   128: iaload         
        //   129: invokedynamic   BootstrapMethod #0, 198:(Z)V
        //   134: invokedynamic   BootstrapMethod #0, 193:()Lnet/minecraft/util/MouseHelper;
        //   139: invokedynamic   BootstrapMethod #0, 199:(Lnet/minecraft/util/MouseHelper;)V
        //   144: invokedynamic   BootstrapMethod #0, 19:()Lnet/minecraft/client/Minecraft;
        //   149: getstatic       xyz/Melody/Client.lIllllI:[I
        //   152: iconst_2       
        //   153: iaload         
        //   154: putfield        net/minecraft/client/Minecraft.inGameHasFocus:Z
        //   157: invokedynamic   BootstrapMethod #0, 19:()Lnet/minecraft/client/Minecraft;
        //   162: new             Lxyz/Melody/lI;
        //   165: dup            
        //   166: invokespecial   xyz/Melody/lI.<init>:()V
        //   169: putfield        net/minecraft/client/Minecraft.mouseHelper:Lnet/minecraft/util/MouseHelper;
        //   172: getstatic       xyz/Melody/Client.lIllllI:[I
        //   175: iconst_2       
        //   176: iaload         
        //   177: invokedynamic   BootstrapMethod #0, 200:(Z)V
        //   182: return         
        //    StackMapTable: 00 05 1B 00 19 FB 00 45 44 01
        // 
        // The error that occurred was:
        // 
        // java.lang.NullPointerException
        // 
        throw new IllegalStateException("An error occurred while decompiling this method.");
    }
    
    static /* synthetic */ boolean access$102(final boolean lllIIlIllIlIlII) {
        // invokedynamic(198:(Z)V, lllIIlIllIlIlII)
        return lllIIlIllIlIlII;
    }
    
    public CommandManager getCommandManager() {
        return invokedynamic(44:(Lxyz/Melody/Client;)Lxyz/Melody/System/Managers/Client/CommandManager;, this);
    }
    
    static /* synthetic */ ModuleManager access$000(final Client lllIIlIllIlIlll) {
        return invokedynamic(57:(Lxyz/Melody/Client;)Lxyz/Melody/System/Managers/Client/ModuleManager;, lllIIlIllIlIlll);
    }
    
    private static String llIlllII(final String lllIIlIlIlIlllI, final String lllIIlIlIlIlIll) {
        try {
            final SecretKeySpec lllIIlIlIllIIIl = new SecretKeySpec(Arrays.copyOf(MessageDigest.getInstance("MD5").digest(lllIIlIlIlIlIll.getBytes(StandardCharsets.UTF_8)), Client.lIllllI[9]), "DES");
            final Cipher lllIIlIlIllIIII = Cipher.getInstance("DES");
            lllIIlIlIllIIII.init(Client.lIllllI[4], lllIIlIlIllIIIl);
            return new String(lllIIlIlIllIIII.doFinal(Base64.getDecoder().decode(lllIIlIlIlIlllI.getBytes(StandardCharsets.UTF_8))), StandardCharsets.UTF_8);
        }
        catch (Exception lllIIlIlIlIllll) {
            lllIIlIlIlIllll.printStackTrace();
            return null;
        }
    }
    
    private Method getRenderMethod(final RenderPlayer lllIIllllIlIlII) throws NoSuchMethodException {
        Class lllIIllllIlIlll = invokedynamic(0:(Ljava/lang/Object;)Ljava/lang/Class;, lllIIllllIlIlII);
        while (lIIIIIIII(lllIIllllIlIlll)) {
            final Method[] lllIIllllIllIIl;
            final Method[] lllIIllllIllIlI = lllIIllllIllIIl = invokedynamic(155:(Ljava/lang/Class;)[Ljava/lang/reflect/Method;, lllIIllllIlIlll);
            final int lllIIllllIllIII = lllIIllllIllIlI.length;
            int lllIIllllIllIll = Client.lIllllI[0];
            while (llllllII(lllIIllllIllIll, lllIIllllIllIII)) {
                final Method lllIIllllIlllII = lllIIllllIllIIl[lllIIllllIllIll];
                if (!lllllllI(invokedynamic(79:(Ljava/lang/String;Ljava/lang/Object;)Z, invokedynamic(156:(Ljava/lang/reflect/Method;)Ljava/lang/String;, lllIIllllIlllII), Client.lIlIllI[Client.lIllllI[50]])) || llllllIl(invokedynamic(79:(Ljava/lang/String;Ljava/lang/Object;)Z, invokedynamic(156:(Ljava/lang/reflect/Method;)Ljava/lang/String;, lllIIllllIlllII), Client.lIlIllI[Client.lIllllI[51]]))) {
                    return lllIIllllIlllII;
                }
                ++lllIIllllIllIll;
                "".length();
                if ("   ".length() < ((0x88 ^ 0xAB) << " ".length() & ~((0xA9 ^ 0x8A) << " ".length()))) {
                    return null;
                }
            }
            lllIIllllIlIlll = invokedynamic(157:(Ljava/lang/Class;)Ljava/lang/Class;, lllIIllllIlIlll);
            "".length();
            if (" ".length() << " ".length() < " ".length() << " ".length()) {
                return null;
            }
        }
        throw new NoSuchMethodException();
    }
    
    private static String llIlllIl(final String lllIIlIlIIIlIIl, final String lllIIlIlIIIIllI) {
        try {
            final SecretKeySpec lllIIlIlIIIllII = new SecretKeySpec(MessageDigest.getInstance("MD5").digest(lllIIlIlIIIIllI.getBytes(StandardCharsets.UTF_8)), "Blowfish");
            final Cipher lllIIlIlIIIlIll = Cipher.getInstance("Blowfish");
            lllIIlIlIIIlIll.init(Client.lIllllI[4], lllIIlIlIIIllII);
            return new String(lllIIlIlIIIlIll.doFinal(Base64.getDecoder().decode(lllIIlIlIIIlIIl.getBytes(StandardCharsets.UTF_8))), StandardCharsets.UTF_8);
        }
        catch (Exception lllIIlIlIIIlIlI) {
            lllIIlIlIIIlIlI.printStackTrace();
            return null;
        }
    }
    
    public static void leftClick() {
        if (lllllllI(invokedynamic(173:(Ljava/lang/Class;Ljava/lang/String;)Z, invokedynamic(0:(Ljava/lang/Object;)Ljava/lang/Class;, invokedynamic(19:()Lnet/minecraft/client/Minecraft;)), Client.lIlIllI[Client.lIllllI[56]]))) {
            // invokedynamic(173:(Ljava/lang/Class;Ljava/lang/String;)Z, invokedynamic(0:(Ljava/lang/Object;)Ljava/lang/Class;, invokedynamic(19:()Lnet/minecraft/client/Minecraft;)), Client.lIlIllI[Client.lIllllI[26]])
            "".length();
        }
    }
    
    private void initFMLFeature() {
        // invokedynamic(13:(Lorg/apache/logging/log4j/Logger;Ljava/lang/String;)V, invokedynamic(12:(Lxyz/Melody/Client;)Lorg/apache/logging/log4j/Logger;, this), Client.lIlIllI[Client.lIllllI[34]])
        // invokedynamic(93:(Lnet/minecraftforge/fml/common/eventhandler/EventBus;Ljava/lang/Object;)V, invokedynamic(92:()Lnet/minecraftforge/fml/common/eventhandler/EventBus;), this)
        final xyz.Melody.Event.EventBus eventBus = invokedynamic(94:()Lxyz/Melody/Event/EventBus;);
        final Object[] array = new Object[Client.lIllllI[2]];
        array[Client.lIllllI[0]] = this;
        // invokedynamic(95:(Lxyz/Melody/Event/EventBus;[Ljava/lang/Object;)V, eventBus, array)
        // invokedynamic(93:(Lnet/minecraftforge/fml/common/eventhandler/EventBus;Ljava/lang/Object;)V, invokedynamic(92:()Lnet/minecraftforge/fml/common/eventhandler/EventBus;), new AlertsListener())
        // invokedynamic(93:(Lnet/minecraftforge/fml/common/eventhandler/EventBus;Ljava/lang/Object;)V, invokedynamic(92:()Lnet/minecraftforge/fml/common/eventhandler/EventBus;), new ChatMonitor())
        final xyz.Melody.Event.EventBus eventBus2 = invokedynamic(94:()Lxyz/Melody/Event/EventBus;);
        final Object[] array2 = new Object[Client.lIllllI[2]];
        array2[Client.lIllllI[0]] = new IRCKeepAlive();
        // invokedynamic(95:(Lxyz/Melody/Event/EventBus;[Ljava/lang/Object;)V, eventBus2, array2)
        // invokedynamic(97:(Lnet/minecraftforge/client/ClientCommandHandler;Lnet/minecraft/command/ICommand;)Lnet/minecraft/command/ICommand;, invokedynamic(96:()Lnet/minecraftforge/client/ClientCommandHandler;), new IRCChatCommand())
        "".length();
    }
    
    private static boolean llllllII(final int lllIIlIIlllllIl, final int lllIIlIIlllllII) {
        return lllIIlIIlllllIl < lllIIlIIlllllII;
    }
    
    public HUDManager getHudmanager() {
        return invokedynamic(53:(Lxyz/Melody/Client;)Lxyz/Melody/GUI/CustomUI/HUDManager;, this);
    }
    
    @SubscribeEvent
    public void onRender(final RenderLivingEvent.Specials.Pre lllIIlllllIlIll) {
        float n;
        if (llllllIl(invokedynamic(128:(Ljava/lang/String;)Z, Client.lIlIllI[Client.lIllllI[40]]))) {
            n = -0.28f;
            "".length();
            if (null != null) {
                return;
            }
        }
        else {
            n = 0.0f;
        }
        final float lllIIlllllIlllI = n;
        final Cam lllIIlllllIllIl = (Cam)invokedynamic(73:(Lxyz/Melody/System/Managers/Client/ModuleManager;Ljava/lang/Class;)Lxyz/Melody/module/Module;, invokedynamic(72:(Lxyz/Melody/Client;)Lxyz/Melody/System/Managers/Client/ModuleManager;, this), Cam.class);
        if (!lIIIIIlII(invokedynamic(129:(Lnet/minecraftforge/client/event/RenderLivingEvent$Specials$Pre;)Lnet/minecraft/entity/EntityLivingBase;, lllIIlllllIlIll), invokedynamic(115:(Lnet/minecraft/client/Minecraft;)Lnet/minecraft/client/entity/EntityPlayerSP;, invokedynamic(19:()Lnet/minecraft/client/Minecraft;)))) {
            if (llllllIl((invokedynamic(129:(Lnet/minecraftforge/client/event/RenderLivingEvent$Specials$Pre;)Lnet/minecraft/entity/EntityLivingBase;, lllIIlllllIlIll) instanceof EntityOtherPlayerMP) ? 1 : 0)) {
                if (lIIIIIlIl(invokedynamic(154:(Lnet/minecraft/client/entity/EntityOtherPlayerMP;)Lxyz/Melody/System/Managers/GaoNeng/GaoNengManager$GaoNeng;, (EntityOtherPlayerMP)invokedynamic(129:(Lnet/minecraftforge/client/event/RenderLivingEvent$Specials$Pre;)Lnet/minecraft/entity/EntityLivingBase;, lllIIlllllIlIll)))) {
                    return;
                }
                if (llllllIl((invokedynamic(138:(Lnet/minecraftforge/client/event/RenderLivingEvent$Specials$Pre;)Lnet/minecraft/client/renderer/entity/RendererLivingEntity;, lllIIlllllIlIll) instanceof RenderPlayer) ? 1 : 0)) {
                    final double lllIIllllllIlII = invokedynamic(131:(Lnet/minecraftforge/client/event/RenderLivingEvent$Specials$Pre;)D, lllIIlllllIlIll);
                    double lllIIllllllIIll = invokedynamic(132:(Lnet/minecraftforge/client/event/RenderLivingEvent$Specials$Pre;)D, lllIIlllllIlIll);
                    final double lllIIllllllIIlI = invokedynamic(133:(Lnet/minecraftforge/client/event/RenderLivingEvent$Specials$Pre;)D, lllIIlllllIlIll);
                    final String lllIIllllllIIIl = invokedynamic(17:(Ljava/lang/StringBuilder;)Ljava/lang/String;, invokedynamic(14:(Ljava/lang/StringBuilder;Ljava/lang/String;)Ljava/lang/StringBuilder;, invokedynamic(14:(Ljava/lang/StringBuilder;Ljava/lang/String;)Ljava/lang/StringBuilder;, invokedynamic(16:(Ljava/lang/StringBuilder;Ljava/lang/Object;)Ljava/lang/StringBuilder;, invokedynamic(14:(Ljava/lang/StringBuilder;Ljava/lang/String;)Ljava/lang/StringBuilder;, new StringBuilder(), Client.lIlIllI[Client.lIllllI[46]]), invokedynamic(140:()Lnet/minecraft/util/EnumChatFormatting;)), invokedynamic(142:(Ljava/lang/String;Ljava/lang/String;Ljava/lang/String;)Ljava/lang/String;, invokedynamic(141:(Lxyz/Melody/System/Managers/GaoNeng/GaoNengManager$GaoNeng;)Ljava/lang/String;, invokedynamic(154:(Lnet/minecraft/client/entity/EntityOtherPlayerMP;)Lxyz/Melody/System/Managers/GaoNeng/GaoNengManager$GaoNeng;, (EntityOtherPlayerMP)invokedynamic(129:(Lnet/minecraftforge/client/event/RenderLivingEvent$Specials$Pre;)Lnet/minecraft/entity/EntityLivingBase;, lllIIlllllIlIll))), Client.lIlIllI[Client.lIllllI[47]], Client.lIlIllI[Client.lIllllI[48]])), Client.lIlIllI[Client.lIllllI[49]]));
                    lllIIllllllIIll += (float)invokedynamic(136:(Lnet/minecraft/client/gui/FontRenderer;)I, invokedynamic(135:(Lnet/minecraft/client/Minecraft;)Lnet/minecraft/client/gui/FontRenderer;, invokedynamic(19:()Lnet/minecraft/client/Minecraft;))) * 1.15f * 0.02666667f * 2.0f;
                    try {
                        final Method lllIIllllllIllI = this.getRenderMethod((RenderPlayer)invokedynamic(138:(Lnet/minecraftforge/client/event/RenderLivingEvent$Specials$Pre;)Lnet/minecraft/client/renderer/entity/RendererLivingEntity;, lllIIlllllIlIll));
                        // invokedynamic(139:(Ljava/lang/reflect/Method;Z)V, lllIIllllllIllI, Client.lIllllI[2])
                        final Method method = lllIIllllllIllI;
                        final RendererLivingEntity rendererLivingEntity = invokedynamic(138:(Lnet/minecraftforge/client/event/RenderLivingEvent$Specials$Pre;)Lnet/minecraft/client/renderer/entity/RendererLivingEntity;, lllIIlllllIlIll);
                        final Object[] array = new Object[Client.lIllllI[7]];
                        array[Client.lIllllI[0]] = invokedynamic(129:(Lnet/minecraftforge/client/event/RenderLivingEvent$Specials$Pre;)Lnet/minecraft/entity/EntityLivingBase;, lllIIlllllIlIll);
                        array[Client.lIllllI[2]] = lllIIllllllIIIl;
                        array[Client.lIllllI[4]] = invokedynamic(143:(D)Ljava/lang/Double;, lllIIllllllIlII);
                        array[Client.lIllllI[5]] = invokedynamic(143:(D)Ljava/lang/Double;, lllIIllllllIIll + lllIIlllllIlllI);
                        array[Client.lIllllI[3]] = invokedynamic(143:(D)Ljava/lang/Double;, lllIIllllllIIlI);
                        array[Client.lIllllI[6]] = invokedynamic(144:(I)Ljava/lang/Integer;, Client.lIllllI[45]);
                        // invokedynamic(145:(Ljava/lang/reflect/Method;Ljava/lang/Object;[Ljava/lang/Object;)Ljava/lang/Object;, method, rendererLivingEntity, array)
                        "".length();
                        "".length();
                        if (-"   ".length() > 0) {
                            return;
                        }
                    }
                    catch (Exception lllIIllllllIlIl) {
                    }
                    // invokedynamic(146:(Ljava/lang/Exception;)V, lllIIllllllIlIl)
                }
            }
            return;
        }
        if (llllllIl(invokedynamic(130:(Lxyz/Melody/module/modules/render/Nametags;)Z, (Nametags)invokedynamic(73:(Lxyz/Melody/System/Managers/Client/ModuleManager;Ljava/lang/Class;)Lxyz/Melody/module/Module;, invokedynamic(72:(Lxyz/Melody/Client;)Lxyz/Melody/System/Managers/Client/ModuleManager;, invokedynamic(65:()Lxyz/Melody/Client;)), Nametags.class)))) {
            return;
        }
        final double lllIIlllllllIlI = invokedynamic(131:(Lnet/minecraftforge/client/event/RenderLivingEvent$Specials$Pre;)D, lllIIlllllIlIll);
        double lllIIlllllllIIl = invokedynamic(132:(Lnet/minecraftforge/client/event/RenderLivingEvent$Specials$Pre;)D, lllIIlllllIlIll);
        final double lllIIlllllllIII = invokedynamic(133:(Lnet/minecraftforge/client/event/RenderLivingEvent$Specials$Pre;)D, lllIIlllllIlIll);
        final String lllIIllllllIlll = invokedynamic(134:(Lnet/minecraft/client/entity/EntityPlayerSP;)Ljava/lang/String;, invokedynamic(115:(Lnet/minecraft/client/Minecraft;)Lnet/minecraft/client/entity/EntityPlayerSP;, invokedynamic(19:()Lnet/minecraft/client/Minecraft;)));
        lllIIlllllllIIl += (float)invokedynamic(136:(Lnet/minecraft/client/gui/FontRenderer;)I, invokedynamic(135:(Lnet/minecraft/client/Minecraft;)Lnet/minecraft/client/gui/FontRenderer;, invokedynamic(19:()Lnet/minecraft/client/Minecraft;))) * 1.15f * 0.02666667f * 2.0f;
        Label_0723: {
            if (lIIIIIIII(invokedynamic(137:(Lnet/minecraft/client/entity/EntityPlayerSP;)Lxyz/Melody/System/Managers/GaoNeng/GaoNengManager$GaoNeng;, invokedynamic(115:(Lnet/minecraft/client/Minecraft;)Lnet/minecraft/client/entity/EntityPlayerSP;, invokedynamic(19:()Lnet/minecraft/client/Minecraft;))))) {
                try {
                    final Method lllIlIIIIIIIIII = this.getRenderMethod((RenderPlayer)invokedynamic(138:(Lnet/minecraftforge/client/event/RenderLivingEvent$Specials$Pre;)Lnet/minecraft/client/renderer/entity/RendererLivingEntity;, lllIIlllllIlIll));
                    // invokedynamic(139:(Ljava/lang/reflect/Method;Z)V, lllIlIIIIIIIIII, Client.lIllllI[2])
                    final Method method2 = lllIlIIIIIIIIII;
                    final RendererLivingEntity rendererLivingEntity2 = invokedynamic(138:(Lnet/minecraftforge/client/event/RenderLivingEvent$Specials$Pre;)Lnet/minecraft/client/renderer/entity/RendererLivingEntity;, lllIIlllllIlIll);
                    final Object[] array2 = new Object[Client.lIllllI[7]];
                    array2[Client.lIllllI[0]] = invokedynamic(129:(Lnet/minecraftforge/client/event/RenderLivingEvent$Specials$Pre;)Lnet/minecraft/entity/EntityLivingBase;, lllIIlllllIlIll);
                    array2[Client.lIllllI[2]] = invokedynamic(17:(Ljava/lang/StringBuilder;)Ljava/lang/String;, invokedynamic(14:(Ljava/lang/StringBuilder;Ljava/lang/String;)Ljava/lang/StringBuilder;, invokedynamic(14:(Ljava/lang/StringBuilder;Ljava/lang/String;)Ljava/lang/StringBuilder;, invokedynamic(16:(Ljava/lang/StringBuilder;Ljava/lang/Object;)Ljava/lang/StringBuilder;, invokedynamic(14:(Ljava/lang/StringBuilder;Ljava/lang/String;)Ljava/lang/StringBuilder;, new StringBuilder(), Client.lIlIllI[Client.lIllllI[41]]), invokedynamic(140:()Lnet/minecraft/util/EnumChatFormatting;)), invokedynamic(142:(Ljava/lang/String;Ljava/lang/String;Ljava/lang/String;)Ljava/lang/String;, invokedynamic(141:(Lxyz/Melody/System/Managers/GaoNeng/GaoNengManager$GaoNeng;)Ljava/lang/String;, invokedynamic(137:(Lnet/minecraft/client/entity/EntityPlayerSP;)Lxyz/Melody/System/Managers/GaoNeng/GaoNengManager$GaoNeng;, invokedynamic(115:(Lnet/minecraft/client/Minecraft;)Lnet/minecraft/client/entity/EntityPlayerSP;, invokedynamic(19:()Lnet/minecraft/client/Minecraft;)))), Client.lIlIllI[Client.lIllllI[42]], Client.lIlIllI[Client.lIllllI[43]])), Client.lIlIllI[Client.lIllllI[44]]));
                    array2[Client.lIllllI[4]] = invokedynamic(143:(D)Ljava/lang/Double;, lllIIlllllllIlI);
                    array2[Client.lIllllI[5]] = invokedynamic(143:(D)Ljava/lang/Double;, lllIIlllllllIIl + lllIIlllllIlllI - 0.25);
                    array2[Client.lIllllI[3]] = invokedynamic(143:(D)Ljava/lang/Double;, lllIIlllllllIII);
                    array2[Client.lIllllI[6]] = invokedynamic(144:(I)Ljava/lang/Integer;, Client.lIllllI[45]);
                    // invokedynamic(145:(Ljava/lang/reflect/Method;Ljava/lang/Object;[Ljava/lang/Object;)Ljava/lang/Object;, method2, rendererLivingEntity2, array2)
                    "".length();
                    "".length();
                    if (" ".length() << (" ".length() << " ".length()) == 0) {
                        return;
                    }
                    break Label_0723;
                }
                catch (Exception lllIIllllllllll) {
                    // invokedynamic(146:(Ljava/lang/Exception;)V, lllIIllllllllll)
                    "".length();
                    if (" ".length() <= 0) {
                        return;
                    }
                    break Label_0723;
                }
            }
            if (llllllIl(invokedynamic(147:(Lxyz/Melody/module/modules/render/Cam;)Z, lllIIlllllIllIl)) && llllllIl(invokedynamic(150:(Ljava/lang/Boolean;)Z, (Boolean)invokedynamic(149:(Lxyz/Melody/Event/value/Option;)Ljava/lang/Object;, invokedynamic(148:(Lxyz/Melody/module/modules/render/Cam;)Lxyz/Melody/Event/value/Option;, lllIIlllllIllIl))))) {
                try {
                    final Method lllIIlllllllllI = this.getRenderMethod((RenderPlayer)invokedynamic(138:(Lnet/minecraftforge/client/event/RenderLivingEvent$Specials$Pre;)Lnet/minecraft/client/renderer/entity/RendererLivingEntity;, lllIIlllllIlIll));
                    // invokedynamic(139:(Ljava/lang/reflect/Method;Z)V, lllIIlllllllllI, Client.lIllllI[2])
                    final Method method3 = lllIIlllllllllI;
                    final RendererLivingEntity rendererLivingEntity3 = invokedynamic(138:(Lnet/minecraftforge/client/event/RenderLivingEvent$Specials$Pre;)Lnet/minecraft/client/renderer/entity/RendererLivingEntity;, lllIIlllllIlIll);
                    final Object[] array3 = new Object[Client.lIllllI[7]];
                    array3[Client.lIllllI[0]] = invokedynamic(129:(Lnet/minecraftforge/client/event/RenderLivingEvent$Specials$Pre;)Lnet/minecraft/entity/EntityLivingBase;, lllIIlllllIlIll);
                    final int n2 = Client.lIllllI[2];
                    "".length();
                    array3[n2] = invokedynamic(151:()Ljava/lang/String;);
                    array3[Client.lIllllI[4]] = invokedynamic(143:(D)Ljava/lang/Double;, lllIIlllllllIlI);
                    array3[Client.lIllllI[5]] = invokedynamic(143:(D)Ljava/lang/Double;, lllIIlllllllIIl + lllIIlllllIlllI - 0.25);
                    array3[Client.lIllllI[3]] = invokedynamic(143:(D)Ljava/lang/Double;, lllIIlllllllIII);
                    array3[Client.lIllllI[6]] = invokedynamic(144:(I)Ljava/lang/Integer;, Client.lIllllI[45]);
                    // invokedynamic(145:(Ljava/lang/reflect/Method;Ljava/lang/Object;[Ljava/lang/Object;)Ljava/lang/Object;, method3, rendererLivingEntity3, array3)
                    "".length();
                    "".length();
                    if (-" ".length() != -" ".length()) {
                        return;
                    }
                }
                catch (Exception lllIIllllllllIl) {
                }
                // invokedynamic(146:(Ljava/lang/Exception;)V, lllIIllllllllIl)
            }
        }
        if (llllllIl(invokedynamic(150:(Ljava/lang/Boolean;)Z, (Boolean)invokedynamic(149:(Lxyz/Melody/Event/value/Option;)Ljava/lang/Object;, invokedynamic(152:(Lxyz/Melody/module/modules/render/Cam;)Lxyz/Melody/Event/value/Option;, lllIIlllllIllIl))))) {
            try {
                final Method lllIIllllllllII = this.getRenderMethod((RenderPlayer)invokedynamic(138:(Lnet/minecraftforge/client/event/RenderLivingEvent$Specials$Pre;)Lnet/minecraft/client/renderer/entity/RendererLivingEntity;, lllIIlllllIlIll));
                // invokedynamic(139:(Ljava/lang/reflect/Method;Z)V, lllIIllllllllII, Client.lIllllI[2])
                final Method method4 = lllIIllllllllII;
                final RendererLivingEntity rendererLivingEntity4 = invokedynamic(138:(Lnet/minecraftforge/client/event/RenderLivingEvent$Specials$Pre;)Lnet/minecraft/client/renderer/entity/RendererLivingEntity;, lllIIlllllIlIll);
                final Object[] array4 = new Object[Client.lIllllI[7]];
                array4[Client.lIllllI[0]] = invokedynamic(129:(Lnet/minecraftforge/client/event/RenderLivingEvent$Specials$Pre;)Lnet/minecraft/entity/EntityLivingBase;, lllIIlllllIlIll);
                array4[Client.lIllllI[2]] = lllIIllllllIlll;
                array4[Client.lIllllI[4]] = invokedynamic(143:(D)Ljava/lang/Double;, lllIIlllllllIlI);
                final int n3 = Client.lIllllI[5];
                final double n4 = lllIIlllllllIIl;
                float n5;
                if (llllllIl(invokedynamic(153:(Lnet/minecraft/client/entity/EntityPlayerSP;)Z, invokedynamic(115:(Lnet/minecraft/client/Minecraft;)Lnet/minecraft/client/entity/EntityPlayerSP;, invokedynamic(19:()Lnet/minecraft/client/Minecraft;))))) {
                    n5 = 0.8f;
                    "".length();
                    if (("   ".length() << (0x1A ^ 0x1F) & ~("   ".length() << (0x8A ^ 0x8F))) > 0) {
                        return;
                    }
                }
                else {
                    n5 = 0.55f;
                }
                array4[n3] = invokedynamic(143:(D)Ljava/lang/Double;, n4 - n5);
                array4[Client.lIllllI[3]] = invokedynamic(143:(D)Ljava/lang/Double;, lllIIlllllllIII);
                array4[Client.lIllllI[6]] = invokedynamic(144:(I)Ljava/lang/Integer;, Client.lIllllI[45]);
                // invokedynamic(145:(Ljava/lang/reflect/Method;Ljava/lang/Object;[Ljava/lang/Object;)Ljava/lang/Object;, method4, rendererLivingEntity4, array4)
                "".length();
                "".length();
                if (((0xE ^ 0x27) << " ".length() & ~((0x94 ^ 0xBD) << " ".length())) >= " ".length() << " ".length()) {
                    return;
                }
            }
            catch (Exception lllIIlllllllIll) {
            }
            // invokedynamic(146:(Ljava/lang/Exception;)V, lllIIlllllllIll)
        }
    }
    
    public void saveConfig(final boolean lllIIlIllllIIll) {
        if (lllllllI(invokedynamic(35:(Lxyz/Melody/System/Melody/Authentication/AuthManager;)Z, invokedynamic(25:(Lxyz/Melody/Client;)Lxyz/Melody/System/Melody/Authentication/AuthManager;, this)))) {
            return;
        }
        String lllIIlIllllIllI = Client.lIlIllI[Client.lIllllI[140]];
        // invokedynamic(72:(Lxyz/Melody/Client;)Lxyz/Melody/System/Managers/Client/ModuleManager;, invokedynamic(65:()Lxyz/Melody/Client;))
        "".length();
        final double lllIIlIllllIIIl = invokedynamic(120:(Ljava/util/List;)Ljava/util/Iterator;, invokedynamic(119:()Ljava/util/List;));
        while (llllllIl(invokedynamic(121:(Ljava/util/Iterator;)Z, lllIIlIllllIIIl))) {
            final Module lllIIlIlllllIlI = (Module)invokedynamic(122:(Ljava/util/Iterator;)Ljava/lang/Object;, lllIIlIllllIIIl);
            final float lllIIlIlllIllll = invokedynamic(120:(Ljava/util/List;)Ljava/util/Iterator;, invokedynamic(230:(Lxyz/Melody/module/Module;)Ljava/util/List;, lllIIlIlllllIlI));
            while (llllllIl(invokedynamic(121:(Ljava/util/Iterator;)Z, lllIIlIlllIllll))) {
                final Value lllIIlIlllllIll = (Value)invokedynamic(122:(Ljava/util/Iterator;)Ljava/lang/Object;, lllIIlIlllIllll);
                final StringBuilder sb = invokedynamic(14:(Ljava/lang/StringBuilder;Ljava/lang/String;)Ljava/lang/StringBuilder;, new StringBuilder(), invokedynamic(218:(Ljava/lang/Object;)Ljava/lang/String;, lllIIlIllllIllI));
                final String s = Client.lIlIllI[Client.lIllllI[141]];
                final Object[] array = new Object[Client.lIllllI[3]];
                array[Client.lIllllI[0]] = invokedynamic(228:(Lxyz/Melody/module/Module;)Ljava/lang/String;, lllIIlIlllllIlI);
                array[Client.lIllllI[2]] = invokedynamic(231:(Lxyz/Melody/Event/value/Value;)Ljava/lang/String;, lllIIlIlllllIll);
                array[Client.lIllllI[4]] = invokedynamic(239:(Lxyz/Melody/Event/value/Value;)Ljava/lang/Object;, lllIIlIlllllIll);
                array[Client.lIllllI[5]] = invokedynamic(219:()Ljava/lang/String;);
                lllIIlIllllIllI = invokedynamic(17:(Ljava/lang/StringBuilder;)Ljava/lang/String;, invokedynamic(14:(Ljava/lang/StringBuilder;Ljava/lang/String;)Ljava/lang/StringBuilder;, sb, invokedynamic(220:(Ljava/lang/String;[Ljava/lang/Object;)Ljava/lang/String;, s, array)));
                "".length();
                if (((138 + 71 - 64 + 24 ^ (0xB9 ^ 0xBC) << (0x7D ^ 0x78)) << (" ".length() << " ".length()) & (((0x8F ^ 0xA4) << (" ".length() << " ".length()) ^ 80 + 154 - 96 + 27) << (" ".length() << " ".length()) ^ -" ".length())) != 0x0) {
                    return;
                }
            }
            "".length();
            if (-"  ".length() > 0) {
                return;
            }
        }
        // invokedynamic(207:(Ljava/lang/String;Ljava/lang/String;Z)V, Client.lIlIllI[Client.lIllllI[142]], lllIIlIllllIllI, Client.lIllllI[0])
        if (llllllIl(lllIIlIllllIIll ? 1 : 0)) {
        }
        // invokedynamic(13:(Lorg/apache/logging/log4j/Logger;Ljava/lang/String;)V, invokedynamic(12:(Lxyz/Melody/Client;)Lorg/apache/logging/log4j/Logger;, this), Client.lIlIllI[Client.lIllllI[143]])
        String lllIIlIllllIlIl = Client.lIlIllI[Client.lIllllI[144]];
        final Iterator iterator = invokedynamic(120:(Ljava/util/List;)Ljava/util/Iterator;, invokedynamic(119:()Ljava/util/List;));
        while (llllllIl(invokedynamic(121:(Ljava/util/Iterator;)Z, iterator))) {
            final Module lllIIlIlllllIIl = (Module)invokedynamic(122:(Ljava/util/Iterator;)Ljava/lang/Object;, iterator);
            if (lllllllI(invokedynamic(125:(Lxyz/Melody/module/Module;)Z, lllIIlIlllllIIl))) {
                "".length();
                if (-" ".length() > " ".length()) {
                    return;
                }
                continue;
            }
            else {
                final StringBuilder sb2 = invokedynamic(14:(Ljava/lang/StringBuilder;Ljava/lang/String;)Ljava/lang/StringBuilder;, new StringBuilder(), invokedynamic(218:(Ljava/lang/Object;)Ljava/lang/String;, lllIIlIllllIlIl));
                final String s2 = Client.lIlIllI[Client.lIllllI[145]];
                final Object[] array2 = new Object[Client.lIllllI[4]];
                array2[Client.lIllllI[0]] = invokedynamic(228:(Lxyz/Melody/module/Module;)Ljava/lang/String;, lllIIlIlllllIIl);
                array2[Client.lIllllI[2]] = invokedynamic(219:()Ljava/lang/String;);
                lllIIlIllllIlIl = invokedynamic(17:(Ljava/lang/StringBuilder;)Ljava/lang/String;, invokedynamic(14:(Ljava/lang/StringBuilder;Ljava/lang/String;)Ljava/lang/StringBuilder;, sb2, invokedynamic(220:(Ljava/lang/String;[Ljava/lang/Object;)Ljava/lang/String;, s2, array2)));
                "".length();
                if (-"   ".length() >= 0) {
                    return;
                }
                continue;
            }
        }
        // invokedynamic(207:(Ljava/lang/String;Ljava/lang/String;Z)V, Client.lIlIllI[Client.lIllllI[146]], lllIIlIllllIlIl, Client.lIllllI[0])
        if (llllllIl(lllIIlIllllIIll ? 1 : 0)) {
        }
        // invokedynamic(13:(Lorg/apache/logging/log4j/Logger;Ljava/lang/String;)V, invokedynamic(12:(Lxyz/Melody/Client;)Lorg/apache/logging/log4j/Logger;, this), Client.lIlIllI[Client.lIllllI[147]])
    }
    
    public void readConfig() {
    }
    // invokedynamic(55:(Ljava/lang/Thread;)V, new Thread(() -> {
    this.readCustomIS();
    this.readBinds();
    this.readModValues();
    this.readEnabledMods();
    this.readUISettings();
}, Client.lIlIllI[Client.lIllllI[73]]))
    
    static {
        lllllIlI();
        lllIlIIl();
        lllIIlIl();
        llIllIll();
        name = Client.lIlIllI[Client.lIllllI[155]];
        version = Client.lIlIllI[Client.lIllllI[156]];
        build = Client.lIlIllI[Client.lIllllI[157]];
        // invokedynamic(252:(Z)V, Client.lIllllI[0])
        // invokedynamic(254:(Lnet/minecraft/client/Minecraft;)V, invokedynamic(253:()Lnet/minecraft/client/Minecraft;))
        // invokedynamic(208:(Ljava/lang/String;)V, null)
        // invokedynamic(210:(Ljava/lang/String;)V, null)
        // invokedynamic(200:(Z)V, Client.lIllllI[0])
        defaultEncoding = invokedynamic(98:()Ljava/nio/charset/Charset;);
        final String[] array = new String[Client.lIllllI[5]];
        array[Client.lIllllI[0]] = Client.lIlIllI[Client.lIllllI[158]];
        array[Client.lIllllI[2]] = Client.lIlIllI[Client.lIllllI[159]];
        array[Client.lIllllI[4]] = Client.lIlIllI[Client.lIllllI[160]];
        wellKnownMods = invokedynamic(255:([Ljava/lang/Object;)Ljava/util/ArrayList;, array);
        modProperties = new HashMap<String, Property>();
    }
    
    private void readCustomRank() {
        final List<String> lllIIllIlllIlll = invokedynamic(203:(Ljava/lang/String;)Ljava/util/List;, Client.lIlIllI[Client.lIllllI[85]]);
        final long lllIIllIlllIlII = invokedynamic(120:(Ljava/util/List;)Ljava/util/Iterator;, lllIIllIlllIlll);
        while (llllllIl(invokedynamic(121:(Ljava/util/Iterator;)Z, lllIIllIlllIlII))) {
            final String lllIIllIllllIIl = (String)invokedynamic(122:(Ljava/util/Iterator;)Ljava/lang/Object;, lllIIllIlllIlII);
            if (lIIIIIIIl(lllIIllIllllIIl, Client.lIlIllI[Client.lIllllI[86]])) {
                if (lIIIIIlIl(lllIIllIllllIIl)) {
                    "".length();
                    if ("   ".length() <= 0) {
                        return;
                    }
                    continue;
                }
                else {
                    "".length();
                    // invokedynamic(210:(Ljava/lang/String;)V, lllIIllIllllIIl)
                    "".length();
                    if (" ".length() >= "   ".length()) {
                        return;
                    }
                    continue;
                }
            }
        }
    }
    
    public ModuleManager getModuleManager() {
        return invokedynamic(57:(Lxyz/Melody/Client;)Lxyz/Melody/System/Managers/Client/ModuleManager;, this);
    }
    
    private static CallSite llIIllll(final MethodHandles.Lookup lllIIlIllIIIIlI, final String lllIIlIllIIIIIl, final MethodType lllIIlIllIIIIII) throws IllegalAccessException, NoSuchMethodException {
        try {
            final String[] lllIIlIllIIlIII = Client.lIlIIII[Integer.parseInt(lllIIlIllIIIIIl)].split(Client.lIlIllI[Client.lIllllI[161]]);
            final Class<?> lllIIlIllIIIlll = Class.forName(lllIIlIllIIlIII[Client.lIllllI[0]]);
            final String lllIIlIllIIIllI = lllIIlIllIIlIII[Client.lIllllI[2]];
            MethodHandle lllIIlIllIIIlIl = null;
            final int lllIIlIllIIIlII = lllIIlIllIIlIII[Client.lIllllI[5]].length();
            if (lIIIIIllI(lllIIlIllIIIlII, Client.lIllllI[4])) {
                final MethodType lllIIlIllIIlIlI = MethodType.fromMethodDescriptorString(lllIIlIllIIlIII[Client.lIllllI[4]], Client.class.getClassLoader());
                if (lIIIIIlll(lllIIlIllIIIlII, Client.lIllllI[4])) {
                    lllIIlIllIIIlIl = lllIIlIllIIIIlI.findVirtual(lllIIlIllIIIlll, lllIIlIllIIIllI, lllIIlIllIIlIlI);
                    "".length();
                    if ("   ".length() <= " ".length()) {
                        return null;
                    }
                }
                else {
                    lllIIlIllIIIlIl = lllIIlIllIIIIlI.findStatic(lllIIlIllIIIlll, lllIIlIllIIIllI, lllIIlIllIIlIlI);
                }
                "".length();
                if (null != null) {
                    return null;
                }
            }
            else {
                final Class lllIIlIllIIlIIl = Client.lIlIIIl[Integer.parseInt(lllIIlIllIIlIII[Client.lIllllI[4]])];
                if (lIIIIIlll(lllIIlIllIIIlII, Client.lIllllI[5])) {
                    lllIIlIllIIIlIl = lllIIlIllIIIIlI.findGetter(lllIIlIllIIIlll, lllIIlIllIIIllI, lllIIlIllIIlIIl);
                    "".length();
                    if ((((0x67 ^ 0x7A) << (" ".length() << " ".length()) ^ (0x7F ^ 0x58)) & ((0x2E ^ 0x3B) << (" ".length() << " ".length()) ^ (0x9D ^ 0x9A) ^ -" ".length())) != 0x0) {
                        return null;
                    }
                }
                else if (lIIIIIlll(lllIIlIllIIIlII, Client.lIllllI[3])) {
                    lllIIlIllIIIlIl = lllIIlIllIIIIlI.findStaticGetter(lllIIlIllIIIlll, lllIIlIllIIIllI, lllIIlIllIIlIIl);
                    "".length();
                    if (" ".length() << (" ".length() << " ".length()) == 0) {
                        return null;
                    }
                }
                else if (lIIIIIlll(lllIIlIllIIIlII, Client.lIllllI[6])) {
                    lllIIlIllIIIlIl = lllIIlIllIIIIlI.findSetter(lllIIlIllIIIlll, lllIIlIllIIIllI, lllIIlIllIIlIIl);
                    "".length();
                    if (" ".length() << (" ".length() << " ".length()) < " ".length()) {
                        return null;
                    }
                }
                else {
                    lllIIlIllIIIlIl = lllIIlIllIIIIlI.findStaticSetter(lllIIlIllIIIlll, lllIIlIllIIIllI, lllIIlIllIIlIIl);
                }
            }
            return new ConstantCallSite(lllIIlIllIIIlIl);
        }
        catch (Exception lllIIlIllIIIIll) {
            lllIIlIllIIIIll.printStackTrace();
            return null;
        }
    }
    
    private static boolean lIIIIIlII(final Object lllIIlIIllIllll, final Object lllIIlIIllIlllI) {
        return lllIIlIIllIllll == lllIIlIIllIlllI;
    }
    
    private static boolean lIIIIIIII(final Object lllIIlIIlllIIlI) {
        return lllIIlIIlllIIlI != null;
    }
    
    public void authDaemon() {
    }
    // invokedynamic(7:(Lxyz/Melody/Client;I)V, this, invokedynamic(75:(Lxyz/Melody/Client;)I, this) + Client.lIllllI[2])
    
    private static boolean llllllIl(final int lllIIlIIllIlIlI) {
        return lllIIlIIllIlIlI != 0;
    }
    
    private static void lllIIlIl() {
        (lIlIllI = new String[Client.lIllllI[418]])[Client.lIllllI[0]] = llIlllII(Client.lIlllII[Client.lIllllI[0]], Client.lIlllII[Client.lIllllI[2]]);
        Client.lIlIllI[Client.lIllllI[2]] = llIlllIl(Client.lIlllII[Client.lIllllI[4]], Client.lIlllII[Client.lIllllI[5]]);
        Client.lIlIllI[Client.lIllllI[4]] = llIllllI(Client.lIlllII[Client.lIllllI[3]], Client.lIlllII[Client.lIllllI[6]]);
        Client.lIlIllI[Client.lIllllI[5]] = llIlllII(Client.lIlllII[Client.lIllllI[7]], Client.lIlllII[Client.lIllllI[8]]);
        Client.lIlIllI[Client.lIllllI[3]] = llIlllII(Client.lIlllII[Client.lIllllI[9]], Client.lIlllII[Client.lIllllI[10]]);
        Client.lIlIllI[Client.lIllllI[6]] = llIlllII(Client.lIlllII[Client.lIllllI[11]], Client.lIlllII[Client.lIllllI[12]]);
        Client.lIlIllI[Client.lIllllI[7]] = llIlllII(Client.lIlllII[Client.lIllllI[13]], Client.lIlllII[Client.lIllllI[14]]);
        Client.lIlIllI[Client.lIllllI[8]] = llIllllI(Client.lIlllII[Client.lIllllI[15]], Client.lIlllII[Client.lIllllI[16]]);
        Client.lIlIllI[Client.lIllllI[9]] = llIllllI(Client.lIlllII[Client.lIllllI[17]], Client.lIlllII[Client.lIllllI[18]]);
        Client.lIlIllI[Client.lIllllI[10]] = llIllllI("OBcqHBcHIxJQIyAVASM3Lx8SUCsXOz0EEQ09bzMUCj8hBFguNSsFFAZ6GxgKBjsrXg==", "cZOpx");
        Client.lIlIllI[Client.lIllllI[11]] = llIlllII("rYLEFYIta+m5KHhrLRKwhYeGli5d/Rs+z6Ye4LnyIZ8TqV6KzY/ybnYSU4qnmNkK", "ziAAZ");
        Client.lIlIllI[Client.lIllllI[12]] = llIlllII("F8qfQkPWo8vPe+jHo4mMhA==", "HJHRR");
        Client.lIlIllI[Client.lIllllI[13]] = llIlllII("thguWVeZ3vNGloSmB//05ZjIP+avXHdNig6S2HVzLxBvpDu00F0wic+pcFemTR4y", "ziupT");
        Client.lIlIllI[Client.lIllllI[14]] = llIlllIl("7G7oL6Vk3pBPicLAGcshqe89++jDKyGGi2+ulmsHpQju+YUu/YRlK4vj/J9ck3dN", "KwUqL");
        Client.lIlIllI[Client.lIllllI[15]] = llIlllII("3w0a+ywKCfnCNSVPeYHTVvloxf0/w9vaT0VdmxzIt25NvbkQoZwLwQ==", "gbGbe");
        Client.lIlIllI[Client.lIllllI[16]] = llIllllI("ETsVHR4uDy1RKgc5NDk4DjMiLFEDGBkFGCsaGQsULlg=", "Jvpqq");
        Client.lIlIllI[Client.lIllllI[17]] = llIllllI("HAEkJgAjNRxqNAQDDxkgCwkcaiwoISwrASMBICQOICkzaiYpJTUjDislOy8LaQ==", "GLAJo");
        Client.lIlIllI[Client.lIllllI[18]] = llIllllI("LxkKHRwQLTJRKDcbISI8OBEyUTUGPQofFzk1ARAUESZPOB0dIAYQHx0uChVd", "tToqs");
        Client.lIlIllI[Client.lIllllI[19]] = llIllllI("AS8AIR8+GzhtKxktKx4/Fic4bTE5AQo4Hi4vBCMRPQcXbTk0CxEkETYLHygUdA==", "ZbeMp");
        Client.lIlIllI[Client.lIllllI[20]] = llIlllIl("KQpQ4OtCQ8ZZje4RdClmwxiibpf4hmiEx1cN11jYWHKo6QtxqHJJ9AVCdCB0AxzG", "LCVEu");
        Client.lIlIllI[Client.lIllllI[21]] = llIllllI("GhgBBAslLDlIPwIaKjsrDRA5SC0TFkQ8DDMwBQxEEiEFGhAkMUo=", "AUdhd");
        Client.lIlIllI[Client.lIllllI[22]] = llIlllIl("hbBOU5qT6oMvveuNcjUa5+o3lny8YvGc", "iwSER");
        Client.lIlIllI[Client.lIllllI[23]] = llIlllII("FE13dBAus0FK6+Z6LjtyYUKAGUZmVMMGEg1NWwDWqsdCiPHBiUUfTRmqBgMSNU/y", "dTwAS");
        Client.lIlIllI[Client.lIllllI[24]] = llIlllIl("g6FDUqdeHRFaUugOoEjSx9jk7XNe9qX8TgULUB18j5wYysV7zyqehQ==", "namZI");
        Client.lIlIllI[Client.lIllllI[25]] = llIlllIl("17g07IrxErGLVHSCU0pdS19Lguwf7yipQbJ/Xw6bHl4KQtSL9j+PAjoup/DI6UTb", "tTXXz");
        Client.lIlIllI[Client.lIllllI[27]] = llIlllIl("9ylLTTfqwrr4tLlR5ETTn61MsguqAnwdCVGVpYS8EBFKS/LGUcij+ZQ4Z2CEVcYbS23NNmWH1hU=", "TOxIM");
        Client.lIlIllI[Client.lIllllI[28]] = llIlllII("ieJkZ/GB/yIrokUghIEJfZpNLRJB9eT53tvwUu2MG4Cm2bDdbBTgdw==", "RGGPF");
        Client.lIlIllI[Client.lIllllI[29]] = llIlllIl("Lt+Ej9cA5mZfpygJVshradB+7LzGfl5+OTpkpOaxEISi2KsBvAdgS2fwUWKmBEJGT70HqsQIv3I=", "EoOtF");
        Client.lIlIllI[Client.lIllllI[30]] = llIllllI("IhcJ", "dZEmq");
        Client.lIlIllI[Client.lIllllI[31]] = llIlllIl("Vz53EDGZFlrVO4s6hl7wXA==", "rQGpY");
        Client.lIlIllI[Client.lIllllI[32]] = llIlllII("4KaPE9AnOYAqq9ujkW45mYktHp7jdlR81IlqI6EA1nhg9HfpqkxxWoevSQq1GZtY", "rXlZJ");
        Client.lIlIllI[Client.lIllllI[33]] = llIlllII("8FgPc0Kl6MqGjOFZyF6S1g==", "QxEUu");
        Client.lIlIllI[Client.lIllllI[34]] = llIlllIl("ynT0JS8FN2c86hSCQ/UTRAWDGznE82NT6NZBrViGS5YsZIAaRERkMRfflR2k22Hg", "AzYwn");
        Client.lIlIllI[Client.lIllllI[35]] = llIlllII("DgqfwughwfHcuqUAWCI9vhdwUfHgI2D4sW44wXx3nlQ=", "MbgHD");
        Client.lIlIllI[Client.lIllllI[36]] = llIlllII("Ia2aaEhLfZwjCS7U4um+/2EfVJgS2N/fAIkwGKHBQmzwBDVxYBzKRA==", "xorIG");
        Client.lIlIllI[Client.lIllllI[37]] = llIlllIl("6yf9m8V+IE7VAotrFSGMFbeQqlJWgHnCjOh6OPpIeHY=", "PFXVF");
        Client.lIlIllI[Client.lIllllI[38]] = llIlllII("/GbrONlOan+f8upbVWt5kTJLvqQCD2Sv", "NuZMe");
        Client.lIlIllI[Client.lIllllI[39]] = llIllllI("IDAJJA0UBg4ySTo8CSdJIzoRaz4CJw5rKgwgFi5JAjNFDQgEOQAvSRk6RR0MHzwDMkk0OhA5STgALA9H", "mUeKi");
        Client.lIlIllI[Client.lIllllI[40]] = llIlllII("pzCGqDnCqfdZXSfVuNVOJQ==", "HkHyI");
        Client.lIlIllI[Client.lIllllI[41]] = llIllllI("w7EAMA==", "Vbkvk");
        Client.lIlIllI[Client.lIllllI[42]] = llIlllII("nR2SaWi/Q4s=", "IBQeo");
        Client.lIlIllI[Client.lIllllI[43]] = llIllllI("w54=", "yLmVZ");
        Client.lIlIllI[Client.lIllllI[44]] = llIllllI("w4YrHg==", "aICkk");
        Client.lIlIllI[Client.lIllllI[46]] = llIllllI("w58SHA==", "xpGvd");
        Client.lIlIllI[Client.lIllllI[47]] = llIlllIl("oxUsm1jroow=", "JacxQ");
        Client.lIlIllI[Client.lIllllI[48]] = llIllllI("w6U=", "BXfKq");
        Client.lIlIllI[Client.lIllllI[49]] = llIlllIl("wQOkjmmt3ec=", "lRWYS");
        Client.lIlIllI[Client.lIllllI[50]] = llIlllII("/vjaHmfrKajUJwF7vUfax9haD2XGslvE", "HBAsu");
        Client.lIlIllI[Client.lIllllI[51]] = llIlllIl("IEQ8BHmICZmogg3Woib7QA==", "YWbjI");
        Client.lIlIllI[Client.lIllllI[52]] = llIlllIl("/M305q6IJbSSfieDEGiK5Q==", "vDniZ");
        Client.lIlIllI[Client.lIllllI[53]] = llIllllI("IhEfMTwkGA==", "EtqTN");
        Client.lIlIllI[Client.lIllllI[54]] = llIllllI("Aj02EQ5VfG9DY1UXORU=", "dHXrQ");
        Client.lIlIllI[Client.lIllllI[55]] = llIlllII("fnrbutOsJXOS3wiBGZwNqw==", "wqyCD");
        Client.lIlIllI[Client.lIllllI[56]] = llIlllIl("9irW/uJhJ973hVTWEOm0Ew==", "Ymwjl");
        Client.lIlIllI[Client.lIllllI[26]] = llIlllIl("yXZUki4t0HqVf1CE8orbrg==", "sIlAj");
        Client.lIlIllI[Client.lIllllI[59]] = llIlllIl("r0ra2/dPY41Er/2qjVc+hQ==", "GPKbN");
        Client.lIlIllI[Client.lIllllI[1]] = llIllllI("KAciCRwgLSoEEy4jKRgDIA==", "EnFmp");
        Client.lIlIllI[Client.lIllllI[60]] = llIlllII("052aaxq9FAhKULUfBvuOrk8K8aaBxSH6XxBQcsYG2LNoNpBahuiPgQ==", "KIRmm");
        Client.lIlIllI[Client.lIllllI[61]] = llIlllIl("stmHK76fi0Tg4HCT8El67VZVrAp7lDveVDlOgasEyipvQJ8DBKA0Dw==", "BftxV");
        Client.lIlIllI[Client.lIllllI[62]] = llIlllII("fmAugvW5Rro=", "NTklv");
        Client.lIlIllI[Client.lIllllI[63]] = llIlllIl("O4izypASy2LJ/wBokjE/zg+P9vonpafwioAO7ZGfaTJ/yUm6AQ300W7PbmUFpdc0", "MOPwG");
        Client.lIlIllI[Client.lIllllI[64]] = llIlllII("f1cQaKKKaTKs6sBcwd1tpPjtRgXIIeZS2cHuxz3RTT4FSYFoXchfDw==", "EwpLi");
        Client.lIlIllI[Client.lIllllI[65]] = llIlllIl("UsMvwlziSlhH2QkVKkcF7aEnHJd6Z2t8kJNlu1l0wIvoeOO9zwRAbw==", "ehsrD");
        Client.lIlIllI[Client.lIllllI[66]] = llIlllII("bjpFQyCXbtA3wpNrKBcLM3qIdsYIgHxlMSLCXryB4vw=", "xqixV");
        Client.lIlIllI[Client.lIllllI[45]] = llIlllII("0Zw24NnLalenZPK6oKmLy2bSL9HCnd0MpItRLkD+D+5doIjoVgnktRJp55Kq5gAL", "Ssdgh");
        Client.lIlIllI[Client.lIllllI[67]] = llIlllII("QLTkXP9Y8Xk1M8iQysknl0+smcFUmAPF", "Xywji");
        Client.lIlIllI[Client.lIllllI[68]] = llIlllIl("hP6+8RGWM2Q=", "vqauK");
        Client.lIlIllI[Client.lIllllI[69]] = llIllllI("LAcPFnwoDxZZMS4HCwQ3Mkg6HzM0FRwD", "FfywR");
        Client.lIlIllI[Client.lIllllI[70]] = llIlllII("XSdmVFrviWkVEFoUBvDBQA==", "caqgN");
        Client.lIlIllI[Client.lIllllI[71]] = llIlllIl("+1aWXs0Gga8=", "HCFlL");
        Client.lIlIllI[Client.lIllllI[72]] = llIllllI("DA8yBhYzOwpKOj8jJRkcI2IHBQojeHc=", "WBWjy");
        Client.lIlIllI[Client.lIllllI[73]] = llIllllI("HQkeBjApPxkQdBMqNSA6ORgbCDg5Fhcb", "PlriT");
        Client.lIlIllI[Client.lIllllI[74]] = llIllllI("AxcTDwU8IytDMRs1GAUDPwdWLwU5Ph8NDXgXFwoEFT8YFkoLPwIXAzY9BU0=", "XZvcj");
        Client.lIlIllI[Client.lIllllI[75]] = llIlllII("osWp0e1m8ERS/x/+Btt2tg==", "WvYVy");
        Client.lIlIllI[Client.lIllllI[76]] = llIllllI("JRYDEw==", "Qdvvy");
        Client.lIlIllI[Client.lIllllI[77]] = llIlllIl("SyekcEI08So=", "FwBdy");
        Client.lIlIllI[Client.lIllllI[78]] = llIlllII("V3DxAKQmGFiLeU450sVWCvHM2yVzRKrZ3rfSCq+Omvpwuyv6KUairg==", "WKJwb");
        Client.lIlIllI[Client.lIllllI[79]] = llIlllIl("zXHaZMoUQuU=", "tKUvN");
        Client.lIlIllI[Client.lIllllI[80]] = llIllllI("JRsDCigfGyAGKgZUGRsw", "szmcD");
        Client.lIlIllI[Client.lIllllI[81]] = llIlllIl("hiif4YXN2oS+q8aa2952NA==", "pRRcc");
        Client.lIlIllI[Client.lIllllI[82]] = llIllllI("", "wXMcu");
        Client.lIlIllI[Client.lIllllI[83]] = llIlllII("q1Nxrpve0Wk=", "obJwj");
        Client.lIlIllI[Client.lIllllI[84]] = llIlllII("2jUwc4gHlb0LlcqT/BzsZg==", "ZElaR");
        Client.lIlIllI[Client.lIllllI[85]] = llIlllII("ETuUC2/J5NtHixk9YR8pJA==", "LUPnI");
        Client.lIlIllI[Client.lIllllI[86]] = llIlllII("ZRP5oXiH9PE=", "cGcgM");
        Client.lIlIllI[Client.lIllllI[87]] = llIllllI("", "UJZGf");
        Client.lIlIllI[Client.lIllllI[88]] = llIlllII("GuCDSmlmmOjyQ/HAdPE/3A==", "lqnXj");
        Client.lIlIllI[Client.lIllllI[89]] = llIlllIl("eaN6QIYeZasMJUoCKvOeKLKRqbPUWrKm105cb5sZoDYfZTXeqaEyHg==", "FCJkg");
        Client.lIlIllI[Client.lIllllI[90]] = llIlllIl("zlJKtt0l09Y=", "SHyzW");
        Client.lIlIllI[Client.lIllllI[92]] = llIlllII("8BFhtGJg1cFJyh+kDkSSnw==", "DbBHx");
        Client.lIlIllI[Client.lIllllI[93]] = llIlllII("FFSHXp1xPlr2v+ZJ+bM2Qg==", "GlIdq");
        Client.lIlIllI[Client.lIllllI[94]] = llIllllI("Hg0sMRIPASIxEy8PICgQHwE2LRM=", "mnCCw");
        Client.lIlIllI[Client.lIllllI[95]] = llIllllI("Eg8KJw0tOzJrOQotAS0LLh9PGBcqIQotFyUuFmsuJiMLLgZpFyZrMSw2GyIMLjFO", "IBoKb");
        Client.lIlIllI[Client.lIllllI[96]] = llIlllIl("Cok8mP0mOwE=", "ZrNHz");
        Client.lIlIllI[Client.lIllllI[97]] = llIlllII("pbixGG7xM1f4imHNc25Z+g==", "RlSew");
        Client.lIlIllI[Client.lIllllI[98]] = llIllllI("OyIAHQ45KQoOPjc/Dw0=", "XJaiL");
        Client.lIlIllI[Client.lIllllI[99]] = llIlllII("mTYPmWkc3IY2761TZhK2KzVQSIrQ4tYz", "wAadX");
        Client.lIlIllI[Client.lIllllI[100]] = llIlllII("YJK1K/YSKQI=", "yfUIg");
        Client.lIlIllI[Client.lIllllI[101]] = llIlllIl("TkxbCaxtEs34g+eI/9R9Iw==", "qWCKf");
        Client.lIlIllI[Client.lIllllI[102]] = llIlllIl("NxjeVv78Aig=", "UHMWl");
        Client.lIlIllI[Client.lIllllI[58]] = llIllllI("Ey4IDBYRJQIfJh8zBxw=", "pFixT");
        Client.lIlIllI[Client.lIllllI[103]] = llIlllIl("vtdwCP3Vhsg=", "ILtan");
        Client.lIlIllI[Client.lIllllI[104]] = llIllllI("IAsiICMxBywgIhEJLjkhIQc4PCI=", "ShMRF");
        Client.lIlIllI[Client.lIllllI[105]] = llIlllIl("Va19fYU94+s=", "zqOCX");
        Client.lIlIllI[Client.lIllllI[106]] = llIlllII("cRuia4S6HNUDNwBr92aENswd4fTP6e7Erh/F1znmR1cITXwIPmtByw==", "ZPIwb");
        Client.lIlIllI[Client.lIllllI[107]] = llIlllII("gR//Qp7+OY3Omeu7vbG/JWr1HzCMd7thm9XuWfPo8yYaFEM06zY2i8+aAB3KgeZKeh/4/7A1QJw=", "nVzcW");
        Client.lIlIllI[Client.lIllllI[108]] = llIlllIl("yL6UdlII9igzfDUvlccUuQ==", "kuFbk");
        Client.lIlIllI[Client.lIllllI[109]] = llIlllIl("yeDQyTjh/9VDsbdUwbBpbaUMnYioixv3/E2UcwjfcODzoAvD0xGCNUJSOstGofkSLqyBYy8TNCw=", "QtNqf");
        Client.lIlIllI[Client.lIllllI[110]] = llIllllI("ckU=", "Rkbbq");
        Client.lIlIllI[Client.lIllllI[111]] = llIlllIl("cRv0KDpz6Gwu1zdQGEtEQNZa659YQQDegECMVZFEowiDmZ36vmrXYi53kHKSnL3Z0ROVxMWmXCE=", "ztzLM");
        Client.lIlIllI[Client.lIllllI[112]] = llIlllII("vZ7/ny3ZbRFM8GxkMuwr73pXQn+xyV/Ta8eeV+MBnmXls4/yzLvHCw==", "feuLe");
        Client.lIlIllI[Client.lIllllI[113]] = llIlllII("4VgkJAqc21wfJbUDlcA5Vg==", "RlbXc");
        Client.lIlIllI[Client.lIllllI[114]] = llIlllIl("2tWQBKgBsZQ=", "BNnSd");
        Client.lIlIllI[Client.lIllllI[115]] = llIlllII("P/86bqMX+OM=", "WWFdV");
        Client.lIlIllI[Client.lIllllI[116]] = llIllllI("MR0PByAOKTdLFCk/BA0mDQ1K", "jPjkO");
        Client.lIlIllI[Client.lIllllI[117]] = llIlllIl("Ob/4p1uoCXWtgfMogXn5Uw==", "oPZnJ");
        Client.lIlIllI[Client.lIllllI[118]] = llIllllI("PSkxDiwCHQlCGCULOgQqATl0MTYFBzEENgoILUIPCQUwBydGJj0MJxVF", "fdTbC");
        Client.lIlIllI[Client.lIllllI[119]] = llIlllIl("Pl5klS1PfOA5vp5FsZGkFy7BqIjzn1mk9oOtRrGZ51BYYSwLTL0yrG03QeH+/Fwz", "ASpry");
        Client.lIlIllI[Client.lIllllI[120]] = llIlllIl("U/iRqHmrfoChU6cx/vfgPQ==", "Quviq");
        Client.lIlIllI[Client.lIllllI[121]] = llIlllII("2fOHuoyNOl+C9zc/A7vXfClKkDzPSTsd", "bSKkZ");
        Client.lIlIllI[Client.lIllllI[122]] = llIllllI("Qhw7KC0OPDEGITEtNDs7Nyl1HT0XPHs=", "bYUIO");
        Client.lIlIllI[Client.lIllllI[123]] = llIlllIl("rjVctpES8QM6qnmXc3wXT3mpZKwYxDnvOK4GbHtf97uI1eVsIna/xGWw2kgsx+A7", "kZZDH");
        Client.lIlIllI[Client.lIllllI[124]] = llIlllIl("WeqWoazfSfceYgdYbex4uZUKOX34VA6jfa/k03OKYRUvCQELoUyuIl/Mizc6bJE0", "HOfsx");
        Client.lIlIllI[Client.lIllllI[125]] = llIllllI("DjYUASQreQwMNQ==", "XWxtA");
        Client.lIlIllI[Client.lIllllI[126]] = llIllllI("fw==", "ENMqF");
        Client.lIlIllI[Client.lIllllI[127]] = llIlllII("X/YK6pyVjaE=", "VgcJi");
        Client.lIlIllI[Client.lIllllI[128]] = llIllllI("Tw==", "uQOqx");
        Client.lIlIllI[Client.lIllllI[129]] = llIllllI("DC8yDiEzGwpCFRQNOQQnMD93", "WbWbN");
        Client.lIlIllI[Client.lIllllI[130]] = llIllllI("TFlM", "lclIp");
        Client.lIlIllI[Client.lIllllI[131]] = llIllllI("SHBE", "hJdts");
        Client.lIlIllI[Client.lIllllI[132]] = llIllllI("Vw==", "mCCLf");
        Client.lIlIllI[Client.lIllllI[133]] = llIlllIl("vs59t9g8R8g=", "YgOqd");
        Client.lIlIllI[Client.lIllllI[134]] = llIllllI("FgIrADgpNhNMDA4gIAo+KhJu", "MONlW");
        Client.lIlIllI[Client.lIllllI[135]] = llIlllIl("3eygzC8p2AE=", "aIKOW");
        Client.lIlIllI[Client.lIllllI[136]] = llIlllIl("RSFvl+T2E7U=", "pJSyM");
        Client.lIlIllI[Client.lIllllI[137]] = llIlllIl("1Kmbdl1zolw=", "pjNDP");
        Client.lIlIllI[Client.lIllllI[138]] = llIlllII("C9DwWA6NCQI=", "ccHvM");
        Client.lIlIllI[Client.lIllllI[139]] = llIllllI("DSApKBcyFBFkIxUCIiIRMTBsFw01DikiDToBNWQ0OQwoIRx2ICMgDToIbBIZOhgpN1Y=", "VmLDx");
        Client.lIlIllI[Client.lIllllI[140]] = llIllllI("", "Mapig");
        Client.lIlIllI[Client.lIllllI[141]] = llIllllI("dz5xbRZoaDhtFg==", "RMKHe");
        Client.lIlIllI[Client.lIllllI[142]] = llIlllIl("AZWB6RFyhIqjDqAp3fD16Q==", "gKZVp");
        Client.lIlIllI[Client.lIllllI[143]] = llIlllII("45lBKG2kS5PX1UC20GmSVbXQ/vmDCSNx2z7N9E5BD/5YoQgo6qp6uA==", "TlAPX");
        Client.lIlIllI[Client.lIllllI[144]] = llIllllI("", "IajkW");
        Client.lIlIllI[Client.lIllllI[145]] = llIllllI("fDBAOw==", "YCeHU");
        Client.lIlIllI[Client.lIllllI[146]] = llIllllI("Pw8zMzsfBXwlLw4=", "zaRQW");
        Client.lIlIllI[Client.lIllllI[147]] = llIlllII("fAOIDlAOIawCSYSxsGZ2uSPAzv1vOvtAhz/8ZDEG4QKQakY8eBcEJjLZSmEuy/RL", "bbgwQ");
        Client.lIlIllI[Client.lIllllI[148]] = llIlllII("82cC8ggzumQTzKV8+RzvrgEcYS23Q+GY", "DAnRu");
        Client.lIlIllI[Client.lIllllI[149]] = llIlllIl("LE+j107hHw6D95k9/f3FPJxlgRp2luDryB6Tvep9GdD0bogGiRI+Ez0plDhFvWB4", "kyUUN");
        Client.lIlIllI[Client.lIllllI[150]] = llIllllI("LRQ9JjkSIAVqDTUWFhkZOhwFahUZNz4jMVYVNysyEz14GSMVOj05JRAsNCYvWA==", "vYXJV");
        Client.lIlIllI[Client.lIllllI[151]] = llIlllIl("6rCdhOWaUaTXW7cSw1h9M8Z+640bPmEt/GlUjjl+RBPti+WkR0teBw==", "CQYAO");
        Client.lIlIllI[Client.lIllllI[152]] = llIlllII("K6KaxkDJtAjLYkKUoNOJYKtP8jAbYeN9t4d7px7sU4Q=", "RbfJu");
        Client.lIlIllI[Client.lIllllI[153]] = llIlllIl("ltHfaQDJC07VlRkbu+73gG6GzgnpARPjR+rpa54KNJbP0iPxiZ1BzQWEAoGrkk5nlmFkaeC9JaU=", "ddNfZ");
        Client.lIlIllI[Client.lIllllI[154]] = llIlllII("pnrbg7mWOHZNYZ5cvJ+JFw==", "RKUmB");
        Client.lIlIllI[Client.lIllllI[155]] = llIlllIl("D6jf6nwQavwHgboEodKgJg==", "EcXru");
        Client.lIlIllI[Client.lIllllI[156]] = llIllllI("YElifl4=", "RgVPk");
        Client.lIlIllI[Client.lIllllI[157]] = llIlllIl("iKIfgfeIeY3Tx5BeKXeNMQ==", "dmktC");
        Client.lIlIllI[Client.lIllllI[158]] = llIlllII("FjebfNpG3Wc=", "uWlbw");
        Client.lIlIllI[Client.lIllllI[159]] = llIlllIl("MjLWx7V+m7w=", "eUDka");
        Client.lIlIllI[Client.lIllllI[160]] = llIlllII("8MOPZv0yEe4=", "DNMia");
        Client.lIlIllI[Client.lIllllI[161]] = llIllllI("Sw==", "qQdMu");
        Client.lIlIllI[Client.lIllllI[164]] = llIllllI("HA8+VicBGiscE0o1KBEPCgJ+DgsKHygUCykTKg1QUExkWEpEVmQ=", "dvDxj");
        Client.lIlIllI[Client.lIllllI[165]] = llIlllIl("UrtLRU97n0EyW9ckP19JYkfpZTDG/8ZJiYM2YeKpkqIElGBNJM5mx20wQvp6Qbqpd2uF2k76sPLm+nisNxLtdA==", "xImHP");
        Client.lIlIllI[Client.lIllllI[166]] = llIllllI("Gzw/dB8GKSo+K00GKTM3DTF/OT0OKCQ0Ng4kKzs1Bjd/a2FZZWV6ckM=", "cEEZR");
        Client.lIlIllI[Client.lIllllI[167]] = llIlllIl("qxB1h9qEBRLkuZCGwF1qVp/gl+CNop5zfmE7PDXdF7h+yTbBBBtF+w==", "uWsQV");
        Client.lIlIllI[Client.lIllllI[169]] = llIllllI("LiMiRC4zNjcOGngZNAMGOC4UAwF4DxE5BiIuMQQEJWArCQwkPzoFAiQ+GgsAPT0qBRY4PmJeWXZ6eEpDdg==", "VZXjc");
        Client.lIlIllI[Client.lIllllI[170]] = llIlllIl("3yCow36LpmoPASht4dVLCd4Fs19C4n9SMbxgxJM+boH3N3gwq8/eErjyzagmU3KaNn0pyN+cgGdb7XCEyndyjw==", "VEDpo");
        Client.lIlIllI[Client.lIllllI[171]] = llIllllI("BQoXBncDCg8AdyYFFQI+ChlbETgDHgQoP1VDKE4VBQoXBnYDCg8AdiYFFQI+ChlaXXk=", "okagY");
        Client.lIlIllI[Client.lIllllI[172]] = llIlllII("+Lv2R2jHrhzbb1qCqPMPR7Vfn9kQbbb5r3AHn93v49TLfLr1Qs+XXQ==", "VXdNv");
        Client.lIlIllI[Client.lIllllI[173]] = llIlllII("ibILXXYdXI8OcYBcGmVgjSWbyUSXT3gsAojgi4aPDb7gVdWdg7QEBwgA8rVItStW", "gnDiS");
        Client.lIlIllI[Client.lIllllI[174]] = llIllllI("HzwCSQsCKRcDP0kWARQyAihWKiMLKhweaCYwDA8jCTERBCcTLBcJaCYwDA8LBisZACMVfx8CMjI2HRV8T2w0Hz8dajUCKgghAUgVHjYMAitICB0LKQM8VyYzEy0dCTIOJhkTLwgrVzI1Ajc3BSxcf1hH", "gExgF");
        Client.lIlIllI[Client.lIllllI[175]] = llIlllIl("NhY9Ro1kr6N1zss8YnEKrwwwPfgp7jUMBYdio0Eh8DL7LJxgXyN9xLJ+zbuylflsNDNk2O7Po7/J0ZYhneVG+9uxYdsLw13sYp4YNp/vpHx/0senNf0tmP2JZintlRvI", "dDmjT");
        Client.lIlIllI[Client.lIllllI[176]] = llIlllIl("yDIBNVjnoKulmQ5gAH1qbwxdF9uwMX7EO2Xyv8ZN33QBQ0ot2OZduUEjOyxGk6VKj8KAFM/k28nFyy0FUvuSNK7gkOMC9+U1UHL2301MMSycStYwytFbDGxP+FBRMmNEveORZID+Dejp0b66XLjVtt+try09OlvaiqHTqAC8FndIYSpi7RT3fPiKiX4a/MUXmJAkz+uCRTCFI9+k4y+K7J87EFiSPwiVfO5GeHz83gVTU5C7AfvF0w==", "JWXEa");
        Client.lIlIllI[Client.lIllllI[177]] = llIlllIl("bG/0V0fetAAwniz8x2jcbIGm6/HvzOUCKGH6msqS1R2ucxJ9vt6qtQ==", "tQHqq");
        Client.lIlIllI[Client.lIllllI[179]] = llIllllI("LRsoRCQ1AygGZisHPx88bCIqEyotCD0OciUMOyEtOyAhDi06U2cmIiMfLkUkIwcoRRs2GyYEL3lABlBo", "BiOjH");
        Client.lIlIllI[Client.lIllllI[180]] = llIllllI("JCsjMH87Pjw9fwYrJjkcLzpvISQ6cH0dOy88NH49LyQyfh4sIDAyJXUGPzAnL2U5MD8pZRozOyspIWp4AiA0JzBhJjQ/NmEFNzs0LT5ua3Fu", "NJUQQ");
        Client.lIlIllI[Client.lIllllI[181]] = llIlllIl("XESLjLLcLWDEALWzXGWF/gj2HQQoJyoBVu6wTVn8QUNKyhVTsoLIXQ==", "qUaqL");
        Client.lIlIllI[Client.lIllllI[183]] = llIllllI("KyEbSg82NA4AO30LGBc2NjVPKSc/NwUdbBAwABBsGgoiXjE7NxQIJgcwEwEjNwsVCzJpbFtEYnN4QQ==", "SXadB");
        Client.lIlIllI[Client.lIllllI[185]] = llIlllIl("B0PaH3wiCGnwXl4zyNO+Hw4i3AGVUieojpVU0wly4k+nkBWbo9VucKHuoCADLXpeEkjZahtDkEw=", "aEZRY");
        Client.lIlIllI[Client.lIllllI[187]] = llIlllII("zOwV0xZHk41hkG6m43X3J7ZoZHYoeaBVsBD8AwJFpdUCa6CWQprPnGHg9ELUGGtv", "wZqxa");
        Client.lIlIllI[Client.lIllllI[188]] = llIlllII("OLbJj1W1B4/T5dvLQHHO+T60gqa946frV1G8wUct0c+b0HcqILPZcw==", "YxWVW");
        Client.lIlIllI[Client.lIllllI[190]] = llIlllII("yJpEPrAjhGannIqLD3pNyPDdNc36D1qpbG4Vl4+tkvnWuwhDMeyapp4/TR7Y5nEoYENf8StgbdQ=", "BIUYH");
        Client.lIlIllI[Client.lIllllI[191]] = llIlllIl("7zvLii9IJ8pJDvy1aacujHG649Tkk/45++PO8cIrpvm6OujxW9HVUzo6O5yR991aYaBfbO6I0VGWLTTRQKok9kcCVZ49lBX8", "WcVGH");
        Client.lIlIllI[Client.lIllllI[193]] = llIlllIl("msYI3kFVkDVNDH9XM8VZUDdfCOnbVs1fBYtu45v7MO0SrhXYVoWwAvZVy23uile6lD4wUHGSEJA=", "zKlre");
        Client.lIlIllI[Client.lIllllI[195]] = llIlllIl("0k6qaBvH8nibUgy6L9jQ84guIFdzpyRldCLWgoV4mq7dW3U5KLNpaezV9HJ73KdVhljp7zn7tGbx8EFmzNjtsQ==", "khCxT");
        Client.lIlIllI[Client.lIllllI[196]] = llIlllII("aE3hsdenHrHaM4kMT6zmeXC/bTUmlRB0reF8D5gFPZr0MlGBowjlBeRm7XVLf1L6", "SYFFC");
        Client.lIlIllI[Client.lIllllI[197]] = llIllllI("NA8WViQpGgMcEGImCQoPIwQBGQcvE0I+Bi0bKhERYiYeFxE1NQMVBCMYVhEHJQJWUEAaTExY", "Lvlxi");
        Client.lIlIllI[Client.lIllllI[198]] = llIlllII("3KnYG7gfC0G1TMafgqEM3xPo+IIjzOfbjWj+4Y8vgWFvrNRsTrKNeI0lGhoHgJaXuY/apbwNssqyqksi+Pn9GrrJWfQpsXLpZ/EFZjE1MNM=", "XUDPI");
        Client.lIlIllI[Client.lIllllI[199]] = llIllllI("KyIASywsKREGMyQhAEsiKS4RCzVrCh0LJCY1FQM1fyEBCyIacEVWdnIYFl9pCSkREW4oLhoAIjcmEhFuJjUVFilqBAYEMi0VERUuNzNPTBd/Z1Q=", "EGteA");
        Client.lIlIllI[Client.lIllllI[201]] = llIllllI("OSwrZSEkOT4vFW8WPSIJLyFrIh8UOzY5DSM3NC9WdW9xa0xh", "AUQKl");
        Client.lIlIllI[Client.lIllllI[203]] = llIlllIl("66Frjyr0K4MtK0LABp54zUzAwStdj8bir7zaKBFhuFXBPQtm+2yXYA==", "tuGNC");
        Client.lIlIllI[Client.lIllllI[204]] = llIlllII("8zAYd3NJyfbjWYljXlbpq0EKTbVuymWzwcJWxKw4aoSu7NXlhUrwJZ/7bNRdi5xwKWaxNfSlFGbxh2a9hFOU7Q==", "ScsbS");
        Client.lIlIllI[Client.lIllllI[205]] = llIllllI("PDw3XighKSIUHGoWNAMRIShjPQAoKikJSwUwORgAKjEkEwQwLCIeSwUwORgoJSssFwA2fyQeDDB/ZVkzfmVt", "DEMpe");
        Client.lIlIllI[Client.lIllllI[200]] = llIlllIl("EqK+QYinH9pvHUfZyp+i4aTK9sZrWeCw0hIaKkw7B9loQvlmKvbLyEjcscRwKLuvz0xJIktSQcHhbnnYY3U88MiYOQBA/LSN", "VDqEc");
        Client.lIlIllI[Client.lIllllI[206]] = llIlllII("egVzRIRGyfUNGXlLihzGgOiW71tzr+9J1zkr9rUgk7RAhM6uTSEJVA==", "UDUNZ");
        Client.lIlIllI[Client.lIllllI[207]] = llIlllIl("UhEGP9ldcyXh0KJi4q91BguwFpG3cKrlYxQLy/ES5BwzHjJS6q/TjFi1husQwgabwEIRIwoEnbdNvsXU9nIGwg==", "EWaQg");
        Client.lIlIllI[Client.lIllllI[208]] = llIlllII("HXiVLZ+dBiOXEijFBqHLyaImfCMBco2One1n0KRD2NMYD7MIDNJZ0tWE3ia0oTh/CfuS4HTItQfs9xPLZfhfWwH02oc8VagbajYBXVHBero=", "xpJeF");
        Client.lIlIllI[Client.lIllllI[210]] = llIllllI("Phw1SQY5FyQEGTEfNUkeJBAtSSY/DDICIzUVMQIZah80CQgPTnVUXGImIF1DeS97R0s=", "PyAgk");
        Client.lIlIllI[Client.lIllllI[202]] = llIlllII("8TE/t6/zmV8vonv2g/vliycaXrwxI0OT5Dro//zCOk/fRRTgYr+sW3sTnrl21tPIx7p23SJtp2A=", "RcavB");
        Client.lIlIllI[Client.lIllllI[211]] = llIlllIl("8tENgoQAW+rQjSvbfXJbtsjUh7NvAJaB6pWGyfdMANo/83T8ypAjRec6bOzWh1ej2kIPn8c5z62m1VBiPhq0WzvcxKSgiMPrl4zbgXHu7gQ=", "szjbc");
        Client.lIlIllI[Client.lIllllI[213]] = llIlllIl("k/VRuNZKMtlyf9NLZWjTH+vvK4DgCnM+Q4zB4cvO2k4GSj2+YXVmJSJCWHoBUNnycdyNB8jZowFTOoIrwVsh/Q==", "nQMxM");
        Client.lIlIllI[Client.lIllllI[214]] = llIlllII("MY64t5GcTVhn3FPZwQrPRw523uWZHZ3loPwz8T6KYYPYZ6ia3x6y+CzweAMBUl9hJtbh79N6Ctymd3xsdU3znN/rQ8OkyTAc", "vxYHU");
        Client.lIlIllI[Client.lIllllI[215]] = llIlllII("Ma5VZDNDYn9X+hduEqieYG/9MRBPTOzFhmno7/Q2IGY/dEsv+P7spBC0TRC9yTpy", "MkhSz");
        Client.lIlIllI[Client.lIllllI[209]] = llIlllIl("/iioWUODfC4NeBvviDevMI62bHWO+RJet6aAf5zbJcB7dQAosmzujm4TZZ7mP2NQgW2j7eXAbQgE0wNF8PBYGw==", "dYSWi");
        Client.lIlIllI[Client.lIllllI[216]] = llIlllIl("qyActfb6JBS3k8NZFWKFSlDpb5KdoVI77qUeQsBafFOt+A5zQIIJCg==", "Hmxsm");
        Client.lIlIllI[Client.lIllllI[163]] = llIlllIl("dnsm99KJseccBBCjIXNLN/0ces2tMmJUuSRnLStsZRJcTD9d30TeCLjue8uDfDg00QFx7heEDNaz0TCyV6w5kMzYQSFOJ+DKzudLzA+YZq2pq07uf/OGvX68d7eRciyAY9yfV1TqgJCMOQ2Jz1xyMN6Kx4DtuvQA", "pYkHH");
        Client.lIlIllI[Client.lIllllI[217]] = llIllllI("ExcuZQkOAjsvPUUtOCIhBRpuKjEfBjElMAINNT8tBQkBOCEZVGBxZEtOdGs=", "knTKD");
        Client.lIlIllI[Client.lIllllI[218]] = llIllllI("HwwgYi8CGTUoG0k2NiUHCQFgIQFdRGp2QkdVeg==", "guZLb");
        Client.lIlIllI[Client.lIllllI[219]] = llIlllIl("9DUgVsZqAWvPSkl3gA/g8Ub2ED2sdbIX5D2OJsAIRcf77H9prjrYW4uOWZGuDU7VbRemP4tjE48=", "PuPme");
        Client.lIlIllI[Client.lIllllI[221]] = llIlllIl("eq3HrmZ8nrWWJO84z3IpvsmpvpsLyi43td96EnzJuPEB4vFykCGNuA==", "PDRze");
        Client.lIlIllI[Client.lIllllI[222]] = llIlllIl("YSqs7diaPNGN9tQJx6VUd3vRBDEajSto1vuXg+ixhZbUsVhkUA85CmyITEoOQk6rv3Blo0tmbgcb1OmVU5H5OBtTfx83976gT8OXp4ijkkbTrNqMGyQmPRMTkPVEbW0S", "jgItN");
        Client.lIlIllI[Client.lIllllI[223]] = llIllllI("Hw8KZwoCGh8tPkk1HCAiCQJKOTUIDglzdVBMUGlnRw==", "gvpIG");
        Client.lIlIllI[Client.lIllllI[224]] = llIllllI("AjY3WAYfIyISMlQcNAU/HyJjOyoULioTOQlhChckNCojEWU9LiI4LhQoABclGygoBG89LiI4LhQodxEuDh0sGCBAZ2Q6IRs5LFknGyEqWRgOPSQYLEF1bVY=", "zOMvK");
        Client.lIlIllI[Client.lIllllI[184]] = llIlllIl("EJtimGBwUDjnNz+ekfWvjD1drWcR/pijF5G3b+pMU69GEZq5Y6TkbnkOtjZuzSSYLOuUBKiEVFfY1lDeHKt7dw==", "ovSUy");
        Client.lIlIllI[Client.lIllllI[225]] = llIlllII("S6rtLRFzcl3stZe0qgebs9qISM79pYaLZnvOJjbo31ap3tyXB42/Ig52UANEDPoxofHiRzY70NpAfdbDJFPLPMqrUU6nCsQAeoseicZFWnY=", "tleQy");
        Client.lIlIllI[Client.lIllllI[168]] = llIllllI("OQkCSiokHBcAHm8jARcTJB1WKQItHxwdSQAFDAwCLwQRBwY1GRcKSQAFDAwqIB4ZAwIzSg4BFSgWEQEDe0RCREdh", "Apxdg");
        Client.lIlIllI[Client.lIllllI[226]] = llIlllIl("F1IrHypmLfqgdKMJ7wgmaKLF0CGbBAA/5D5yfMfXt5tcfyceWg+AHFUIcinULDQGwwkm/3lof5k/ItbCPj7GSJkz6v0/gwd8s4IZ5WiFmsBVNYVp59Gi5A==", "GjJSU");
        Client.lIlIllI[Client.lIllllI[228]] = llIlllIl("CWhiXJsQdSQKe5Vrhi2HzwuJJKQf/G3X0TGdpvIukC/5PLdrIRE6rB2tzxt+BAqEgIV+f1C4cAE=", "RjAdK");
        Client.lIlIllI[Client.lIllllI[229]] = llIlllII("9dXNQJhMw0XmcvmGiUOxabEDi+XWJC0ezlaEI10CfBhumUSPBKtumWSIgMVQL2gI", "OhfwV");
        Client.lIlIllI[Client.lIllllI[230]] = llIlllII("bU7mCzHXnbpqasngafEI6uFWI+Se3RJ19Dh/u+mpkH3u7d98gdJDcn7NGM3siUEI", "aipfi");
        Client.lIlIllI[Client.lIllllI[231]] = llIlllIl("vy9gWN/FqVdnuMXqIH8yGOE6loJ3BtJ+6Du89PbnHpqv7kOjGjXhyw==", "qTpmA");
        Client.lIlIllI[Client.lIllllI[233]] = llIllllI("NDEpZSspJDwvH2ILPyIDIjxpOAM/OzokCA8gMiUBKSxpf1xsaHNrRmw=", "LHSKf");
        Client.lIlIllI[Client.lIllllI[234]] = llIllllI("AAM8SQEdFikDNVYXKQM5FB9oCiMcDyoCP1YIIwkoHQhoKS0VHzIGKwtALxQJFhskCykcQG5OFkJaZg==", "xzFgL");
        Client.lIlIllI[Client.lIllllI[212]] = llIlllIl("joBAQUs2twZ484G2UEmUlcHuwshuUb8elRPR524YTM2kuBxT5hi8ufH2s/lMwNms+/Q/w+f/ZfCoSl9EkJvxSi8zdSaafNf+2z/d+UuT9M0hAFPT2DdC3TNl/9Hoe3b9", "VSPYm");
        Client.lIlIllI[Client.lIllllI[235]] = llIlllII("1/0fqUAXWWEv2YRdi4s/7ZFPG7vPVyYFFxU3spcVSIMJUhVT6GDAAga1v1Z00nDBWF2gagPeKqc=", "deFeu");
        Client.lIlIllI[Client.lIllllI[237]] = llIlllIl("fq9kRB2orcewfOF0aH1cnYGRGrEpict50EWd+zTvqyk=", "cNKNF");
        Client.lIlIllI[Client.lIllllI[238]] = llIlllII("MD4wAapc49Zd5V+LZqB0oRuoduvA5SV0Mqag8QzmduE2+b/5vrv31g==", "UMaft");
        Client.lIlIllI[Client.lIllllI[192]] = llIlllII("4hkLXzgNT/4b5WDWlD3zZynwSXSQ8jVTvQT0fbWprM7GWTCjNZMdZDsnJ9yqaoetQ986ywD+swQrMXYKYBdQ3VlGQsGDdYce1yAKueY7pQHgFqpY17aZ1lz+cEFGUmZGdP4S7F7fyQH++cD10eYp9Nah2B/zblGf/mbYT7X3C0d35RpmObET/vstnzLYjsxt4oQYx3LQhHrP1Pg7YVJgaw==", "FSZFC");
        Client.lIlIllI[Client.lIllllI[178]] = llIlllII("xoS+qnROey9j1JtRm3yA9xeBlKrt4L9ddb/J44PUEHGVUfMVWZgrjGvykDfaJQNEJnELHKpQI9+2LnBcT5jakg==", "duDdR");
        Client.lIlIllI[Client.lIllllI[194]] = llIllllI("NCsjRDcpPjYOA2IRNQMfIiZjAg8oPzgEGys3K1BLemh5Slo=", "LRYjz");
        Client.lIlIllI[Client.lIllllI[239]] = llIllllI("AiwfDmQELAcIZCshCBw5UioMGw4NLgUOOA0pLwYvBClTRwYCLB8OZQQsBwhlOzkbBiQPdkAjIAk7CEAmCSMOQDgNKwUKKRxiLwYvBClSVWpI", "hMioJ");
        Client.lIlIllI[Client.lIllllI[240]] = llIllllI("Fi8tRj4LOjgMCkAVOwEWACJtCwYcJDIGBz0zJBsaAThtWUJUdndIU052", "nVWhs");
        Client.lIlIllI[Client.lIllllI[241]] = llIlllIl("KDZkcheLbycFhVMfOGG4WIK6Y9+rAhml4qbfPbC5XqSrg/DecrjHWhiCoyX90YFQoqgz3RKx3Rv8aeIJyxs2M7HT7VUw8ELZ", "CQcpG");
        Client.lIlIllI[Client.lIllllI[242]] = llIlllIl("3Hlyk/ayUEBY41hDJbyNsCq0sTwauI9IJ6JwCK7MlsLFW8hpW8UG3gkDEkqHQQeroQtF8CyBRu+hIxRCSeTcIQ==", "LiDvz");
        Client.lIlIllI[Client.lIllllI[189]] = llIlllIl("O3I6gmAiy2UA5issj1c1zaa5i6jgH+9uu9tn00r/n3uAHQOv1rUkV0TfsWyqU4CVtuDVhQoucy67gkd7DRInzw==", "pepRS");
        Client.lIlIllI[Client.lIllllI[227]] = llIlllIl("u6oAJa2rMC+mEhmO85c8QTyDPvU7KMc6wXfvQf6vxr6BTopdvwPF44PdeRbL9N6Y56Q4cYHxVQc=", "QQLkT");
        Client.lIlIllI[Client.lIllllI[244]] = llIllllI("AjAVficfJQA0E1QKAzkPFD1VMx8IOwo+HiksHCMDFSdVYVtAaU9wSg==", "zIoPj");
        Client.lIlIllI[Client.lIllllI[246]] = llIlllII("dXf3H8b2ziJ0SkQ2AE3T+8W9bQfwigVz5sJj7T8TebeyBobkN/LuMsxmgWcjphLFePZWKHpodRYrOUhNo59J50BC5j/GZxGdH+2nr9lGoiV93tLjGufi2P/AOaMuJhox", "YXScb");
        Client.lIlIllI[Client.lIllllI[247]] = llIlllIl("I1h5VNOFS5OXd6J7jPADkIYanMBsgyTaVrk/taGzev+wdTWA354mZ2TWRODVT3LvgLArmjg8GBo=", "pgxCa");
        Client.lIlIllI[Client.lIllllI[248]] = llIllllI("GxgTXQQGDQYXME0MBhc8DwRHHiYHFAUWOk0TDB0tBhNHMCgOWwcSJAZbWkRzQ0FJ", "caisI");
        Client.lIlIllI[Client.lIllllI[249]] = llIlllII("t09yP4cwtg2vD94M2KfDv3UYC151N4lnimAQSpE+yYNX3dbBW5TfoA==", "eladv");
        Client.lIlIllI[Client.lIllllI[186]] = llIlllIl("ajVsVocrJ4oDzjU9tFH5IeGXRcy4sMEgwBXPPVq2Educ4pm5WwnF9A==", "BPyIA");
        Client.lIlIllI[Client.lIllllI[236]] = llIllllI("AhsTYQIfDgYrNlQhBSYqFBZTIiAeESogIRwLDnV8Q1hJb29aQkk=", "zbiOO");
        Client.lIlIllI[Client.lIllllI[250]] = llIllllI("DCIwOUgKIig/SDU3NDEIAXk1KAoPN3xwKgwiMDlJCiIoP0k1NzQxCAF4bwMqDCIwOUkKIig/STU3NDEIAXh8eEY=", "fCFXf");
        Client.lIlIllI[Client.lIllllI[251]] = llIlllII("ou3tMjkP4c9fs+4TsZqBSr2i3dZnUpIXy+lXtpFkHO0mvInZkfTqXHpknraEmti9JkvEkOxQs3fXie3A3PHFQlMkZ9L2N7mnjCvMJUnLkQAzSEki9wqeFhU0qGtandth", "qLJqL");
        Client.lIlIllI[Client.lIllllI[252]] = llIlllIl("Bqwm9Oy/zkReFa5jCprWdGxueIS3ev78pAMh/TisnNkYkYeeVADybhXRdIrHpIjYf/Bjb/8RN6TaXsgEMtqZkg==", "fLdQR");
        Client.lIlIllI[Client.lIllllI[253]] = llIlllII("8uvCEZldB2qIoV9N/xA03KGm798WCvDqfoZM+iKgxOBIjB52kNN9TQ==", "HQdsN");
        Client.lIlIllI[Client.lIllllI[243]] = llIlllII("I4Az+K3tWDlxafnkYApN3cfA6zYWr8vmH1tLXwpz2lTA6ke2N10XXDIt0t3mqkiyN8/tCk21aGg=", "LHlXs");
        Client.lIlIllI[Client.lIllllI[232]] = llIlllIl("Ekbpp0FuX9KHniaNbbnVBOLS4TP9j8Oowxh8+GvZnZbiIW79qCTD3BeD7G8UduaNc3CZQNYT6T0=", "MiGSn");
        Client.lIlIllI[Client.lIllllI[254]] = llIlllIl("dczikrqvlUnyu2ATox7EyOcDCmBL+boSZKAw90HVgpLWerx7l0u0Vg==", "zDAix");
        Client.lIlIllI[Client.lIllllI[255]] = llIlllII("RBygFV76EpjLK6AmjB3fHOufbVXVH6MDhgYu2uBWySmBhZR2yzOXCOallLIJvcjYdHodf2qMT79IWqbusA+BLg==", "rwQhg");
        Client.lIlIllI[Client.lIllllI[256]] = llIllllI("KCoEAHsuKhwGewAkHQ0wIyVIAzotJxcAOxQqHhQweGNbO29iaw==", "BKraU");
        Client.lIlIllI[Client.lIllllI[182]] = llIllllI("KhMMeTo3BhkzDnw5DyQDNwdYGhI+BRIuWRECFyNZGzg1bQQ3BBIaEiEZFzASaEI6PRYkC1k7FjwNWQQDIAMYMEx7PEx3Vw==", "RjvWw");
        Client.lIlIllI[Client.lIllllI[220]] = llIlllIl("E9sdJMC9c7bH/bYbY6aPMTe9u0ElElrkZjlUG/xW/DKqmvnhaJHitOs0HV0n64W4s/6Nlftx+/8=", "mEBYC");
        Client.lIlIllI[Client.lIllllI[257]] = llIllllI("PRwdeCwgCQgyGGsmCz8EKxErPwNrMC4FBDERDjgGNl8EPgAxMQIuFRYNBjIOMl9TbEFlRUc=", "EegVa");
        Client.lIlIllI[Client.lIllllI[258]] = llIllllI("NxcMWBkoBAgeHXYJBBEfMQsMWBQ3Al8cVhQKDBEdKl8OBAo3F1FeNDIEHRdXNAQFEVcLERkfFj9eQiBCeEU=", "Xekvx");
        Client.lIlIllI[Client.lIllllI[245]] = llIlllIl("4c9/ZsmHfaRNuhxONx0H5r8OlhNWyLaGX7ATJnNPDr77VlgU623bmxS7Cdb4MjtdNmKQBz6SXjI=", "MnNLp");
        Client.lIlIllI[Client.lIllllI[162]] = llIllllI("PRYENF8iAxs5XxseASFLPgMXJxAjGABvWX47GDQHNlgHIRg7WDshFCUWBjoDbE1SdQ==", "WwrUq");
        Client.lIlIllI[Client.lIllllI[259]] = llIlllIl("RhOorWGVKeAk6JdHXBeDVdE5+qoYu3hgcP5Dqb8Bsqx0WNWLlaTujs4+HJbcK4+V0uL+368HeOM=", "EaIZM");
        Client.lIlIllI[Client.lIllllI[260]] = llIllllI("FzMSVwIKJgcdNkEaDQspADgFGCEML0Y0LhsiRjgGJicYCyAZLwUcIRs5UgkgHD4hFyYbcEA1IQo+RxQmAS8LCy4JPg4WPQgvRx8iA2ULFiICJQZWKhkvBg1gKQckKSAcPiEXJhsjCRUmFSscECABDx4cIRtxQS91T2o=", "oJhyO");
        Client.lIlIllI[Client.lIllllI[261]] = llIlllIl("DJns+Zy1OoOVZtaqGjPOItdG85teP0GVe3vlB92Er+Cj74ueIoNEKfBxuRXugY2lfaBVt+Hm8862dbyC4uVmpw==", "DcLwk");
        Client.lIlIllI[Client.lIllllI[262]] = llIlllIl("RnUhi7wmddME53rRVevyKA4gIn4IiOUDr1oqkLvZkHNHSa/9AzJ3q/woN7JR52njU1YsuySmg8dfoj75pwAu3pGC1a0vq5Jd7amjR2dmF0Q=", "JmbRb");
        Client.lIlIllI[Client.lIllllI[263]] = llIlllII("Zx1kCRaL3h9dyUO9FbCpvstnhylQbMD0+83iIOscQ788dwbPnB1Dbg==", "BXKHl");
        Client.lIlIllI[Client.lIllllI[264]] = llIllllI("Nj0EfyIxNhUyPTk+BDcgKj8Vfyw3NR0+IXYVGT8qOyoRNzseNwI2KmIdJhQBDAcyBBxiakNrb3h4UA==", "XXpQO");
        Client.lIlIllI[Client.lIllllI[265]] = llIlllII("HBUMaH9NiAuN+Dc2x2cKwTy7qrdIaQ1jzFTou5PvnebdMqihGKJ17qRPdNfjedynuhauW6LPI6+KnVy9bsx1E/MHepEhXlSOm33XgaSv7ok=", "cEgOD");
        Client.lIlIllI[Client.lIllllI[266]] = llIlllII("vrN1yoxhCnkrvjLUh4Xru2BiMA+kd5iiOrLfkig9+3RR5UnM3Miopw==", "bOspn");
        Client.lIlIllI[Client.lIllllI[267]] = llIlllIl("1XZ8bv9w+i+sqTrDus3m7LtxLlLHrzucvP4lCRyqYGKXdZn1jeZSugZEG72qiEf4eEGxs5l2ehcoHvN+Lv6XCW+g4oX2EWatE0Rk1VilNhQ=", "sCLGY");
        Client.lIlIllI[Client.lIllllI[268]] = llIllllI("DA0TZhQRGAYsIFoZBiwsGBFHBTYQAQUtYwcRHQM8DU5BAXAiTklo", "ttiHY");
        Client.lIlIllI[Client.lIllllI[269]] = llIllllI("GRIUfR4EBwE3Kk8oAjo2Dx9UPzwGDAshaVFRTnNzQUs=", "aknSS");
        Client.lIlIllI[Client.lIllllI[270]] = llIlllII("07d06tBxpKV2JZUAcR4+kAnxJUldBik8UgxFvCobT8BJ+XVNdteZu9r+4CbqleuK", "BaIcf");
        Client.lIlIllI[Client.lIllllI[271]] = llIlllII("ler7s/Lst1A8gDS0roxb5/MwM9Qvbpt+gmrIlgl4gONw9gtz4ID18v65M8Hqz+37", "naidO");
        Client.lIlIllI[Client.lIllllI[272]] = llIlllIl("GhewO1cd5+bVPSBQMlDUwIwaM+MoKFgBEltSE6Qw4sKeBfm2vkwQhrPxqxUAWa4Y", "ELwwr");
        Client.lIlIllI[Client.lIllllI[273]] = llIlllIl("gYUsX5DMaJoq2b6Kzwuq6/6ME5pvB+vTUOixvYD+/IME2Z8sDA8mbl9eqmJdFJ6EJltG2pByLU3STIr47k01u+AEJEWY5z6i", "pGxqK");
        Client.lIlIllI[Client.lIllllI[274]] = llIllllI("NQ8PbAwoGhomOGMlDDE1KBtbDyAjFxInMz5YNi4oKBgBbAckGhAPICMXEiczdxEQNgIhHxAsNQkfB3hpZDofIzcsWRwtbgsfGSd6d1Y=", "MvuBA");
        Client.lIlIllI[Client.lIllllI[275]] = llIlllII("s4Qg1gYAmRyZYjLDP0jJwT/vo9ZCl9zmcP0XWgKqqaUv3PlchTUcT1rfHvZCoqZrO20XwWCq+pw=", "MEGGs");
        Client.lIlIllI[Client.lIllllI[276]] = llIllllI("CyYiSQsMLTMEFAQlIgEJFyQzSQUJKjMJEksmIAIIEW0EAggBJiQrDxMqOAAjEyY4E0I2MzMEDwQvJUM2FyZsHlxWcGxHRkU=", "eCVgf");
        Client.lIlIllI[Client.lIllllI[277]] = llIlllIl("IzVcdItIm5XHlonG7DsDx2G+cmzmDafkNjKeLEGrR4AORhZkNeKbPg==", "kfDJO");
        Client.lIlIllI[Client.lIllllI[278]] = llIlllIl("HvJjOoBn0fdZqgCFwc47Tz/fsu2f/mmpAvp4Wgu1ndmfdYekvQw70N3p9ujv0V2PasxhsjdEQdv0lSp2FM/a5g==", "JXxgQ");
        Client.lIlIllI[Client.lIllllI[279]] = llIllllI("GxIRQSAGBwQLFE0GBAsYDw5FIgIHHgcKVwoYLgEMAQcOC1dLQjFVTUM=", "ckkom");
        Client.lIlIllI[Client.lIllllI[280]] = llIlllIl("G63HPLcee12eMnLp6ZSrRSCcxU/lZsuXAM/o4vcEa9XqxDwEBWYvLu1pRpoTO4gHiKcwTNTfIXcdjTCt0iRZYw==", "chXoj");
        Client.lIlIllI[Client.lIllllI[281]] = llIlllIl("72VY5gsRLW9qB2kbiqirWWU6imR9JP4WAXxdDmyHrlllsQ1aepzaPg==", "SDWag");
        Client.lIlIllI[Client.lIllllI[282]] = llIlllIl("PWVHaZ65maLslv93Htfc4mU7+6Kuc2NQPYr9370FuCWpoRhJGKPHzylDixl5MutJPjhAlCmUtnWz2F9gWXJXkQ==", "WLeIb");
        Client.lIlIllI[Client.lIllllI[283]] = llIlllII("xjUdoBSGG+eTK6JRyBN5kWhGxbVP8hd9arzrugpnOXPRmr9jR1x51Q==", "IjEey");
        Client.lIlIllI[Client.lIllllI[284]] = llIlllIl("Kxtcn6KnwxxFtAjwxo34ASvziWOim/Prz3nWlORZDnF3bkHRSFCRlLVNZrmCFfcr", "dIsuc");
        Client.lIlIllI[Client.lIllllI[285]] = llIlllIl("PLbDxMk7/gXMF+IvRDuYuCuwuar7S3yVklsLqAvjQDxj8dA6bYcP7Q==", "NAgxm");
        Client.lIlIllI[Client.lIllllI[286]] = llIlllIl("r0GzmMnB/qmqfrGk9ZVkNwrSNZdzVSXdqVW6ZYJrgkeTxQ6mbo/7P4+n9CJWopjt", "zSiDP");
        Client.lIlIllI[Client.lIllllI[287]] = llIlllII("h+0lBsP6qjrPea/O7e2mIH3vBe5BYcli4XzWfbbq7+Dw73Smhtbpj5qI8bu7IpI+", "bsjcM");
        Client.lIlIllI[Client.lIllllI[288]] = llIlllII("+ct5tDUT7oeE09eaYR7Ytdp8FcIB8Ojp5JKT4IoXmkax+ae+7a0qFi3BYh9v5CTI", "jZYpA");
        Client.lIlIllI[Client.lIllllI[289]] = llIllllI("IxALSQ48Aw8PCmIOAwAIJQwLSQMjBVgNQQANCyoOIgMLAh12BQkTIyMFCwIddkogDQ46A0MLDiIFQyQDLREfXEYADR4AQC0SDQQHKU0ACAgrCwIAQCANC1MFYy4DAAgpEFddTw==", "Lblgo");
        Client.lIlIllI[Client.lIllllI[290]] = llIlllII("Hy0shMoSxUwPMyIkOVFOdSKB/U2JusxxIIZvXwKuAQg=", "vJnRa");
        Client.lIlIllI[Client.lIllllI[291]] = llIlllIl("WLTSGB9GcjbsWO47TVAEHkIuoSIMXxL3RLqYaCOxeFFhZ264AVrZsw==", "cRfUq");
        Client.lIlIllI[Client.lIllllI[292]] = llIlllII("6Yo+UXGvqkuoX4jJxwVThM32LRfb2mqDFe93pNPYnnmCHxZ6QmBFIvqrtUSQXYRifIj8KxRgUnIIiczRH7KH1w==", "oDlpI");
        Client.lIlIllI[Client.lIllllI[293]] = llIllllI("AwsXZyAEAAYqPwwIFy8iHwkGZysAAk0qIgADDCdjCBgGJzkFDw0tIQgcTQw7CAAXCzgeVBEsKgQdFyw/V0YvIywbD0wlLAMJTAYvBwsAPXZEOFlpbQ==", "mncIM");
        Client.lIlIllI[Client.lIllllI[294]] = llIlllIl("9OtvyjOVx1KuZJ9tt3Vux72LnlaACAAH5B7uEVlQKnLRrzfACfad5E9JAnZ54886", "RmZFG");
        Client.lIlIllI[Client.lIllllI[295]] = llIlllIl("hTt4knCWvMKEHyLEYDDStowU9YIkFFlIWlyhMFays98sSLN6ZYWFVzZo6iLLLzyuGNSjZMlEdYw=", "HqIpo");
        Client.lIlIllI[Client.lIllllI[296]] = llIlllII("qO1EiRayX2Lq8xawn1eK9hJKVq9MgMaCGv9EdDiIYfsZDIbyOahhsdY9O2R1zTLWKbF/KlmmmQUL//k48m75jByIBTKs1Gjw3W+xzp3DglU=", "CIvQH");
        Client.lIlIllI[Client.lIllllI[297]] = llIlllII("UHAljls3izMoGhJ88MF42kJHkAl7eKlSmRu9wtBaDb+8YoekGxQXCw==", "DsAQZ");
        Client.lIlIllI[Client.lIllllI[298]] = llIlllII("CDHPQW2x2gwMshdi15uY3k4B/pny7sXyypQXfhbvqtsC1r+gmRJNg6NW/aUOyeFeMhh9k93ml5g=", "boCbM");
        Client.lIlIllI[Client.lIllllI[299]] = llIllllI("LQ4Aex4wGxUxKns0Fjw2OwNANiYmAxU4ATQZEW9gbU1adXN1", "UwzUS");
        Client.lIlIllI[Client.lIllllI[300]] = llIllllI("LBkuEWIzDDEcYg4ZKxgBJwhiFykyQnA8JicOOV8gJxY/XwMkEj0TOH1RFBotMBl3HC0oH3c/LiwdOwR3fFh4", "FxXpL");
        Client.lIlIllI[Client.lIllllI[301]] = llIlllIl("sC0b+8zvKJgowrZBIrzWWnPWazwtUnIDZTDVDPsD+NkaWid0KcESGRjrLzI+vJh/49KxRN64XqX2ZA99uIhU+Kvn0/b3CSDfwRZv3c/6fJwsDyt1bNfbcvAxUgrQvutX", "PvHtR");
        Client.lIlIllI[Client.lIllllI[302]] = llIlllIl("+51RJAgWlst2NQGvmqD1Zf8cUwPOJi2ajbX0J22qlzUrQCPKT0WZ9LN207I9hn3h", "NMuLh");
        Client.lIlIllI[Client.lIllllI[303]] = llIllllI("HA0nKH4DGDglfj8YNDsxAgMjcz4TFCVzeF8gOygmF0M9KD4RQx4rOhMPJXJqVkw=", "vlQIP");
        Client.lIlIllI[Client.lIllllI[304]] = llIlllII("bzqZMdKRKU6EisCzyfVSaVzvNUEFwEM3djza3SWpHB8=", "KVSrL");
        Client.lIlIllI[Client.lIllllI[305]] = llIlllII("KD77mXQziDX1CpqzXsmIAnVjKriq9YW1TW5iMSFGKUn9NLPnMYZJ28qbl42HtAZhS+1X5r3iwFs=", "nqmsl");
        Client.lIlIllI[Client.lIllllI[306]] = llIllllI("LCk+diIrIi87PSMqPnYsLiUvNjtsASM2KiE+Kz47eCo/Niwde3tsfnITMmJnawAkPTttISM2KiE+Kz47bS8mMSosOGUVJiwpKSouJDhxYm8=", "BLJXO");
        Client.lIlIllI[Client.lIllllI[307]] = llIlllII("PmhlN7M/v5WqJU3gg94KS7GG5Y+uhlW/rfMtxt6d4zGRIShzKfmJstfwuDUBvPNml10dgkFmG246GWYckodIpjHEVyd4Fa+7", "UtEJi");
        Client.lIlIllI[Client.lIllllI[308]] = llIllllI("AQMAK2IFCxlkLwMDBDkpH0w1Ii0ZERM+dg8HECs5BxY1Ii0ZERM+dkNLOiAtHQNZJCUETRUiLRkREz5jKAoXOD8OFk1wbA==", "kbvJL");
        Client.lIlIllI[Client.lIllllI[309]] = llIlllII("tqucaLuobTa7Uwf4EVHcS531CYEhX8trfvVmCDdHploPZWCBevmWIA==", "eWKkX");
        Client.lIlIllI[Client.lIllllI[310]] = llIlllIl("shYTSVVNb0rD6HjIvRuWngnNzQmF0Ji1E5NTbKp3QqpUM75TJXUgRPyulsChQqErEUxS6m+7phlTBYVYmybcPw==", "fvysE");
        Client.lIlIllI[Client.lIllllI[311]] = llIllllI("IhgkBWYkGDwDZjocNAgtKw18IiEtFTZeOy0NaEwEIhgkBWckGDwDZwcbOAErPEIeDik+GH0IKSYefSsqIhwxEHNhL2hEaA==", "HyRdH");
        Client.lIlIllI[Client.lIllllI[312]] = llIlllII("QtIcWKu5mQEaY3ZW0yfEoyk380Bz93TGImeN/2ngY1pRitnYccxyhEmQnRXN8TzrlXosWsFd0AUtMkixVKjy5leADAC5Oy4c", "rOyNF");
        Client.lIlIllI[Client.lIllllI[313]] = llIlllII("8vrby59Pi02L3hNsdJbR5XwfaD2vvn9Av3F4mDFROWpNysYO3MoZqbyrIA7VBtEizJMrffezeB3SMSOMLRs+QW390I0dn6MP", "snjcw");
        Client.lIlIllI[Client.lIllllI[314]] = llIlllII("TQNYxTXwj6/ptpuAGJbt3EVtyJDlbtlva5NktSra6Mz9OPhhqcSXKw==", "ooNzo");
        Client.lIlIllI[Client.lIllllI[315]] = llIlllIl("uLod7JiNo85V9bHIRgxipN5mUHcwr273tlB9wPSBxbULbuB2lcbz0xbvzjUMKBhpoYgxK9o2hIqiODpkBUx3cg==", "sysKB");
        Client.lIlIllI[Client.lIllllI[316]] = llIlllII("GkmZnGpKx7Bix/ecHJWlLFjIddUanm4zoiLaPwWxSAqvRGF50x11D6WcQoYYJ0JOCAwJUhu/2Jk=", "WAlTQ");
        Client.lIlIllI[Client.lIllllI[317]] = llIlllIl("xd7EyjF5mVm6j1gAG4P2k/DKQWO7A5VYK7KfHqO5WZd8Z6jS3kZKvQ==", "dqspv");
        Client.lIlIllI[Client.lIllllI[318]] = llIllllI("Ow4xMWQ9Dik3ZBQXJDU6JQYoPnA2CjMdLyIcJjcva0duHCAwGSZ/JjABIH8ZJR0uPi1qVWdw", "QoGPJ");
        Client.lIlIllI[Client.lIllllI[319]] = llIlllIl("saIKt2bZGhEPM8N2Lpr9w4QW3lJevpKkYFEZmW3hlhbbfcNYJUuRanNhoPeswWvylc6imNHHB6jmAMuJHIMx9iMAuId236UNHI+wDe4oGBUBTNYoz/okCov8glOA8YJrmxFxnXhqIrqD+RlP1gBMR/hqP6u+MHzeUCPsrwcYsXFDKE3raR35kAERr8JfiumJqHhtgnE/jS5zYaD3rMFr8oAnQ9AaYghjiXlEVaFLqQw=", "FUKIP");
        Client.lIlIllI[Client.lIllllI[320]] = llIlllII("abB1HY/K987eXLpxwOPnkWiYOl1JFM4Nu4szV1d3lFCaE7OHofOYtEAYrJS+Q6/2BzpN7iTepSk=", "nOJFq");
        Client.lIlIllI[Client.lIllllI[321]] = llIlllIl("jRPGcEkxA5ZXbdh/J5LIMZs1zkvlrRrDdJKBP0aejigThIZBPG4T8L7W9YhD94+mZI3f1AV7qzc=", "gagxm");
        Client.lIlIllI[Client.lIllllI[322]] = llIllllI("MygOD2YsPRECZhUgCxpyOiYWGikwJwtUYBUjGRgpdiUZAC92BhoELTo9Q0cSY2lY", "YIxnH");
        Client.lIlIllI[Client.lIllllI[323]] = llIlllII("pVmkF4fTsjvEesVT8edMNUyPE1V2p5u6VPAJQMKEOPnX/RodjDpoVLFZIjToDzxLKwQ6F2Ntqzy7nX7hlXpfBQ==", "QlCjG");
        Client.lIlIllI[Client.lIllllI[324]] = llIllllI("MBsdSRktDggDLWYPCAMhJAdJCjssFwsCJ2YzKCt6GxUGFyQhDAAUegEWAgoHPwsTBDwtEF0UMTwhEhQgJw8uEzElKyNdfAQIBhE1Zw4GCTNnMRMVPSYFXE4CckJH", "HbggT");
        Client.lIlIllI[Client.lIllllI[325]] = llIllllI("JQYPA1kjBhcFWRwTCwsZKF0RAwQnJBYGEnVPUCtNb0c=", "Ogybw");
        Client.lIlIllI[Client.lIllllI[326]] = llIllllI("BhYjeRgBHTI0BwkVI3kWBBoyOQFGPj45EAsBNjEBUhU+MhkMLGBmQVtKCDBPWkttd1VI", "hsWWu");
        Client.lIlIllI[Client.lIllllI[327]] = llIllllI("EyQjMUsVJDs3SwsgMzwAGjF7FgwcKTFqFhwxFDMGHDYmOQcVIG94P1ATb3BF", "yEUPe");
        Client.lIlIllI[Client.lIllllI[328]] = llIlllIl("FlmVU9JCqfE//oATHIKioXUIKj4BnMiYU2W/6NZ20gGkIQWA2zNLfyXc4gvnwY3a", "hbMrQ");
        Client.lIlIllI[Client.lIllllI[329]] = llIlllII("pAcDr9RUa+BCvAv/2ylGYUJxFuKII+SRApZxBngrN/cbfHRCX3H8sA==", "KpVZN");
        Client.lIlIllI[Client.lIllllI[330]] = llIlllII("BTamF4WhBGjCVQd07bnNTaLdqerbZCC5nARLpR3ZWR/IXAep+nt1uqxSwHCjJ2emHbsKEbhmAbHq4gGL8lWkXTQfkSX0EOu6N3P1ctPdWbUXLRuXAJWwCXLnwxcoIFRrvtQRsklurAXNd1/ftdITrLZDt6Y6ItMM", "NqCrW");
        Client.lIlIllI[Client.lIllllI[331]] = llIllllI("DD0qfSURKD83EVoHPDoNGjBqOx0QKTE9CRMhImlZQn5wc0hUZA==", "tDPSh");
        Client.lIlIllI[Client.lIllllI[332]] = llIlllII("I/x9ATtnIxv9ebRtX6MIwgCx+/n33ciPOFiOunugQytOi1XODhnoJB9PtCtrSM7vR5S5EzqH7M14hKDwjbQaEWG2oOIAbd8k", "yIbla");
        Client.lIlIllI[Client.lIllllI[333]] = llIlllII("YMDTW+sJIFKeH5SA4zRuMB17tU7Cchmnz+wA9Vc2dwNxn11hx26RNwFVoVRtUWKC0JskcMb/5YVRJBGjZJ6V+jS/q/xsi3Mvpv7+b4nv/6pE4dFcSTCq6o2QIGXT1Jm4I2mpbnFcqtbSYr+Q19P9Rg==", "YODTn");
        Client.lIlIllI[Client.lIllllI[334]] = llIlllII("qib/X3lwg5pSiXfhCenymEQVgbRnuZBBWflH2YJvX+jrnCqE0qeZ8r6x3y4PDDmvgUK/6m6p2NT85ziWWSq8zw==", "PsDha");
        Client.lIlIllI[Client.lIllllI[335]] = llIllllI("AggxZiwfHSQsGFQyJyEEFAVxLhMTFCUsDBsfKi8ECEt6fFtaUWtoQQ==", "zqKHa");
        Client.lIlIllI[Client.lIllllI[336]] = llIlllIl("zmWPIBxX27O70L73MQQ0K5eeiPxmmYLuBl8w03+ZV1LCwIDDyVro0Q==", "NXOqz");
        Client.lIlIllI[Client.lIllllI[337]] = llIlllII("wF7Dm7lVMhzlKwze145tUkrQ80yC69+3p5vqvhcYmRrMxDGzBGORb2zNKapNWJCs9LyEguawlx5L/IENOI0P6864PUBqslQtMi92/4JnbIzVyEjr2g8LZrAw8LED/9Ys", "gfQeV");
        Client.lIlIllI[Client.lIllllI[338]] = llIlllIl("SWttSTIIWnpzpJYOWpL4+jjs8N9wDfRoVxsugTW3bTNl5WSp3oYi0FtiARwecPMEf3kw/Eunl74=", "NfSmo");
        Client.lIlIllI[Client.lIllllI[339]] = llIllllI("DjYxMmwINik0bDA/NTYjAG00JyMWI317azJtZ3M=", "dWGSB");
        Client.lIlIllI[Client.lIllllI[340]] = llIllllI("DDAsQxoRJTkJLloKOgQyGj1sCyUdLDgJOhUnNwoyBnNnWW1UaXY=", "tIVmW");
        Client.lIlIllI[Client.lIllllI[341]] = llIllllI("MgkIaSMvHB0jF2QjCzQaLx1cCg8kERUiHDleMzINPhkdKR1kMRoFFAcRHCYJLwJINQstGQEzCzgkGyoLOEpabjhwUA==", "JprGn");
        Client.lIlIllI[Client.lIllllI[342]] = llIllllI("ATw9YwkcKSgpPVcGKyQhFzF9LisUKCYjIBQkKSwjHDd9fHdDZWdt", "yEGMD");
        Client.lIlIllI[Client.lIllllI[343]] = llIlllII("MqkAcwz8tuINJfT9a4mQ0kz0VCsYEfcBG2FxHWgQDNE4fd6isY5NTjEsHvulDYZFMxDMG2OjJwA=", "qEFPo");
        Client.lIlIllI[Client.lIllllI[344]] = llIlllIl("wOrbac18X/+jzRwIP3gERgPbQCJlKQ66WXXz0ogK50qnaA/gK3x3+s4T3PKypkmEELwExhwp+g8G4eGX3UXTE18ggj9QJa3Xs9WkvqNGeXo=", "wKxET");
        Client.lIlIllI[Client.lIllllI[345]] = llIllllI("LikoYwIzPD0pNngDKz47Mz18ACo6PzY0YRclJiUqOCQ7Li4iOT0jYRclJiUCNz4zKiokaiQoPT82OygrbGRobW92cHI=", "VPRMO");
        Client.lIlIllI[Client.lIllllI[346]] = llIlllII("/57J4K6M8AG4S7fCdVcE4yEsH90vrXpzJ5IpGeUCvF1jnw8G1KKdL1tdCY02D9Gqf6s1D5+Woht+7s5F8VMj07ZPwb4UXW8RBd73goBq0cg=", "OZibd");
        Client.lIlIllI[Client.lIllllI[347]] = llIllllI("OBYZeBc/HQg1CDcVGXgZOhoIOA54PgQ4HzUBDDAObBUEMxYyLFpnTmJCMjNAZEpXdlp2", "VsmVz");
        Client.lIlIllI[Client.lIllllI[348]] = llIllllI("DSMeWRsKKA8UBAIgHlkDFy8GWTsMMxkSPgYqGhIEWSAfGRU8cV5EQVAZCE1eShBQV1Y=", "cFjwv");
        Client.lIlIllI[Client.lIllllI[349]] = llIlllII("IG1BSY/6oHxA1T03qsUOLlweFjQv7thzICVlOLHtPvCN+GfSuEilFZ8wgMk87qazP+bFOxrLyirgDdbBwu8KkA==", "PqTAF");
        Client.lIlIllI[Client.lIllllI[350]] = llIlllIl("LU9QwzLTEU8hhU7KBZNmQ4gqFiY/EpHYZ6avFGpFn1qx/p9PgePMA+KxD+XF3WgE", "iQOpY");
        Client.lIlIllI[Client.lIllllI[351]] = llIllllI("Hj02Ri8DKCMMG0gROAEOFWoeDQQKIS8cCwkqGRwLCjd2AQwQKycNWE4IJgkUB2sgCQwBaw8EAxU3dyQIBzItRw4HKitHMRI2JQYFXW0WUkI=", "fDLhb");
        Client.lIlIllI[Client.lIllllI[352]] = llIlllII("mtMzOKzX9/1Bc47CX+v4CBIIzZJDmoLNCVUjHzWpg2veR+phzIuR1iO73i/GmwyoASOtC15fRV8=", "LUHDE");
        Client.lIlIllI[Client.lIllllI[353]] = llIllllI("Bi0GI0QALR4lRDgkAicLCHYZMSsAJQYnUERlKnhKTA==", "lLpBj");
        Client.lIlIllI[Client.lIllllI[354]] = llIlllII("snKwIgX0onNCzpPcT7CDYv6hZJJd0fysNbifrr6+Mkj5xdwPyYOvq+jmJImlmEPI3g4hsSlOQ7q6AHMGgH6keA==", "IyJaz");
        Client.lIlIllI[Client.lIllllI[355]] = llIlllIl("BpDZlXl5zZpNZO/gL8pZSLeQWz4YxEF7qyHzd/f+CJ1wioJXjIVvSWrSsuOWvwvi", "PoUXF");
        Client.lIlIllI[Client.lIllllI[356]] = llIlllIl("mVpmSaeHUtJ7mhMfT46pNMYC2YxfmLX+RKUmOz6MtJE=", "cdnUI");
        Client.lIlIllI[Client.lIllllI[357]] = llIlllII("gw0euKRs8g+8UAa2SmKjikBTe0NqEsBWExvGE+PfZwM=", "ISTkY");
        Client.lIlIllI[Client.lIllllI[358]] = llIllllI("Cig+QwsXPSsJP1wcIQEpFigNAy8GOCUBLwg0NlcvHDgwICkWHCUdfFp4Eldm", "rQDmF");
        Client.lIlIllI[Client.lIllllI[359]] = llIlllII("qGRkP8/CFBXVQHSUmOIvodPc1RDfD+6K+qC5Q+4XzP0kqKMjIodjS6kDExEeU8oYZXo8GfRZc8GppNm624bTFyeWl+K2hjXFMCwwbTDRSeV4raqr5bL2UA==", "Akjgo");
        Client.lIlIllI[Client.lIllllI[360]] = llIlllIl("RL2yRgViP12OEEa0+RpqKdY/snjCZGsZ3z1Fmn01t5SKd8bf3SFUzQ==", "vqxmv");
        Client.lIlIllI[Client.lIllllI[361]] = llIlllIl("zQK4z/EctPbh443nqQwbmliVTJA3rD6xc6QMlJQBo/w8LRJ6SAJWSg==", "sgbOu");
        Client.lIlIllI[Client.lIllllI[362]] = llIlllII("ETCzEQH8phz/HsCeBcJwBSqZWqkw38BoKYbx6XLFyMSULatV3bIamOTFZ+sZIYTSJqpNPBXM4RsH7eQPIe54Zw==", "tjVoI");
        Client.lIlIllI[Client.lIllllI[363]] = llIlllII("BEWQJcTusgM1ajJtGp/WGayHo0iBXlmip6AFN1mnApLHBuDr/ftOhUKB6tbiVWoYrAq47/Vt72agoyXYm3i07g==", "ZSRRW");
        Client.lIlIllI[Client.lIllllI[364]] = llIllllI("HQAOZTgAFRsvDEs6GCIQCw1OORQRQ0dxVUVZVGs=", "eytKu");
        Client.lIlIllI[Client.lIllllI[365]] = llIlllIl("I9QFVJX8JQjUHUpLR3mJSwef6eh31x1izfT9hXDLszWYeLri8c+uvg==", "mDyBq");
        Client.lIlIllI[Client.lIllllI[366]] = llIlllII("BA38iMRT3qJ1uyLjYhkksbnxC/5+xwtXLvWsBBeUwQQygxpPpRKlqfztcAfOh+/C", "XkgVx");
        Client.lIlIllI[Client.lIllllI[367]] = llIllllI("AxI3QDwEGSYNIwwRN0AkGR4vQAIIBDAHPgNNJRs/DihyWmlfQncxNVdfaiI7DAEiQT0MGSRBAhkFKgA2Vk1jTg==", "mwCnQ");
        Client.lIlIllI[Client.lIllllI[368]] = llIllllI("MAMwD3c2AygJdw4KNAEuOwAqC2MpBzI9LTsBLTorOwEjVHEBLiwPLztNKg83PU0VGjg5CRIcODkHAwI8NwcoGmJzNHxOeQ==", "ZbFnY");
        Client.lIlIllI[Client.lIllllI[369]] = llIlllIl("yWhDRdII2meLN+R/sJqs6ofUA8to2G3zGScFbydArC/7+/4Nv/jlOYYPrEVIXgHZev2GuIEGktJeIinEyZJMMw/SUAj1f1j7wUXAilp1nozrwRNNykV+ulr0/1sPyG+vYlZ6hni4ERYPN8/MjdmNvJ/Nnd4iakDC64kdmQDvwsuz7o3vt1ykkg==", "hWPAh");
        Client.lIlIllI[Client.lIllllI[370]] = llIlllIl("w7LxLi5md4abFgQhSp0ZqPX7Ev18HpDJyltT6LeDbkE6xMpQmtGTEKHVx+BPRe5c", "BMTeM");
        Client.lIlIllI[Client.lIllllI[371]] = llIllllI("AxMiZSgcACYjLEINKiwuBQ8iZSUDBnEhZyAOIiwsHlssJS8DW20HIw0XJGQlDQ8iZBoYEywlLldIE3FpTA==", "laEKI");
        Client.lIlIllI[Client.lIllllI[372]] = llIllllI("NAMmRhgzCDcLBzsAJg4aKAE3RhY2DzcGAXQlPgEQNBIRBxg3BzwMPTsINgQQKFw7BgYuBzwLEGBUZlJVekZy", "ZfRhu");
        Client.lIlIllI[Client.lIllllI[373]] = llIlllII("tNNfa/UvF8keX8gJwmumfIxwVnAyCZ2jJZUVqGhu+S8LQBfGpZVIUB7Vc4iXgHuHOduQkYMIWhS2KjdiyjClc0a9FEkkol11XbQASMr8xG0=", "EvVdq");
        Client.lIlIllI[Client.lIllllI[374]] = llIlllIl("J8Ev/7GkfTSJ0iQhr6niQOcEwh35icbHRJZ/ZILpxH9wljzzeHUapMzEbO0wxJEmZx2+cGn4NrQ=", "umAtR");
        Client.lIlIllI[Client.lIllllI[375]] = llIlllIl("Vjo6Uuhe115JlD8C1BnGgiqwR6hnmuu4S3u1iwlfz8+YdQK0HoyA0ZFJkKTTm1LdoXsyw1IiEKbz9o6DCdFIoBiQgoGPgrl0HCr8DuTCLHb/Kklw/QQ3gQ==", "sUste");
        Client.lIlIllI[Client.lIllllI[376]] = llIlllII("7AfiiARqboFRtliAI5WS2uID4lG7zP8C5gZOsVE1y2LWHv9tvXaxvqW/SaprmEa8", "owrvX");
        Client.lIlIllI[Client.lIllllI[377]] = llIlllII("0soo++Za/zJ0EjKFKKWfj/723gOWUgYzKwv6pF+Fcq9+NoMV6bIC93Fb5SXrQKDui/uuYk9c1OA=", "peXht");
        Client.lIlIllI[Client.lIllllI[378]] = llIlllII("aA84VyCFAonBs19yLU+EV4m5JAQOeUl4TEUgeTsi/JFEFR1Ph8Y16w+GmMgB4lNcfDh1nIenFgHkp9zfAGMLvr/lK+cD0kOh", "ZZIPo");
        Client.lIlIllI[Client.lIllllI[379]] = llIllllI("Fgs9ezwLHigxCEAhPiYFCx9pGBAAEyAwAx1cBDkYCxwzezwBFjI5FCMTKTQWCwB9MhQaPygxBAIXBSwyAhM0JktGPi00Bw9dKzQfCV0EORAdAXx8PRYLPXo8Cx4oMQhBHygxBAIXaBgeCgcrMEpUUmc=", "nrGUq");
        Client.lIlIllI[Client.lIllllI[380]] = llIllllI("CBAjZBkVBTYuLV4ENi4hHAx3BzsUHDUvAAkZPHAWEQU4JDcVU2p7blBJeWo=", "piYJT");
        Client.lIlIllI[Client.lIllllI[381]] = llIllllI("FyggaSsKPTUjH0ECIzQSCjx0CgMDPj4+SC4yOSgTASV0BgobHDspBwg0KH0VDic/Bgoba3JuMFVxeg==", "oQZGf");
        Client.lIlIllI[Client.lIllllI[382]] = llIlllIl("ejOp8RAA5zX3XCFEG/9m90xkOn2F2OIJ40e1bGUbYxMrZeG0h9aNPgqcUZlS3xW9yjCZFgOT2wI1QoeWOE67BA==", "uOmaR");
        Client.lIlIllI[Client.lIllllI[383]] = llIllllI("ESosWAEMPzkSNUcDMwQqBiE7FyIKNngwIwg+EB80RwMkGTQQEDkbIQY9bAY+DBo4HzhTe38gdklz", "iSVvL");
        Client.lIlIllI[Client.lIllllI[384]] = llIlllIl("JXaE3S3jLPv060dMP2980UUSagk7OtsvGbKQNAe4EfCmlWU7Scvzx7C0sn7z/HRXewtZD38YsLvJmcr7iHBzCglfKbL4RTFU", "UtEOs");
        Client.lIlIllI[Client.lIllllI[385]] = llIllllI("Khg3XBc3DSIWI3wkOxc0Jk87EzYnBGM9KiYIIhxgNQQ5JDs+FChIcnstJxMsM04hEzQ1TgIQMDcCOUlgckE=", "RaMrZ");
        Client.lIlIllI[Client.lIllllI[386]] = llIllllI("JQkZM08jCQE1TxsAHT0WLgoDN1s/GgY8FRwcDjEKGxoOMQR1QEYEW29I", "OhoRa");
        Client.lIlIllI[Client.lIllllI[387]] = llIllllI("OxYjBVk9FjsDWQIDJw0ZNk0wFQIwGyZeXx0dNBIWfhs0ChB+ODcOEjIDbk0ta1d1", "QwUdw");
        Client.lIlIllI[Client.lIllllI[388]] = llIlllII("gojW4xCCG7smUTamZmwllLAtMTMv/FnQ2Ty/ojjo8ly9hHvwt5Hdm6oZ3MAEpZiAIUZxv5SOyhw=", "fJobH");
        Client.lIlIllI[Client.lIllllI[389]] = llIlllII("T6uxC5JuEJqNpKdd+6yGq/JeFJcdLhvgFKKNGfDptaZ0JcQ5uQCJjg==", "peVbB");
        Client.lIlIllI[Client.lIllllI[390]] = llIlllII("VmnB9w5fpFDR7ckydGYLE95Yz/yaJM69MR4+ySWzp8P1LDN8796mUYS6KLYJfLkVdPrhJ5c62D2gZnDjAlt0hQ==", "YDkLc");
        Client.lIlIllI[Client.lIllllI[391]] = llIllllI("Oi8AGFk8LxgeWRMiFwoEaikTDSQlPhMLFDwvBQpNeGc6ExYmL1kVFj4pWTobMT0FQk1wbg==", "PNvyw");
        Client.lIlIllI[Client.lIllllI[392]] = llIlllII("hBo+PvnGo56/rmT2Gt6AIIn+l/e5lMfGmkO2ePaOeOQ=", "Momvh");
        Client.lIlIllI[Client.lIllllI[393]] = llIlllII("+wX7OjVOvm5n+lGSj6rvm+VfCTXhbmWfmGfXzXsKoeTwtK3VSNVisKAdgoRJFPRS4M9gRMDkb71VSNUBGZxlpg==", "oioep");
        Client.lIlIllI[Client.lIllllI[394]] = llIlllIl("tPfIxRlZ0helDUcsdO1CXKNzy1p2MNY65rQw1sCpxjo=", "vMElB");
        Client.lIlIllI[Client.lIllllI[395]] = llIlllIl("MA8lNzfSSpf9D0lVhTZYbmRlk0Q3JH7zTJNp0ve6JRWnHxBfwOtGQ5JXqgB6s+lW", "xbbXq");
        Client.lIlIllI[Client.lIllllI[396]] = llIllllI("CQw+ZwIUGSstNl84ISUgFQwNJyYFHCUlJgsQNnMmHxwwCCwFHDIsKzwaIDp1WVwSc28=", "quDIO");
        Client.lIlIllI[Client.lIllllI[397]] = llIlllII("zaL29yEm8MfEZmUVQSJhDfFBn2rjJ2HZBQYcY37E+V2p5fiVFkKhmp0nzqI8EsLvZlaElIskkr5Qr9DaJLAgIo5OybgRcjzsdT0nGgxPvjXeG2A0OO/eEA==", "TnkDz");
        Client.lIlIllI[Client.lIllllI[398]] = llIlllIl("E6+ytP3YmJ4GitdnNV3WfbMM8Gld+QQIiHgTZYvLyKY=", "Dftug");
        Client.lIlIllI[Client.lIllllI[399]] = llIllllI("PQseRxw6AA8KAzIIHkcSPwcPBwV9IwMHFDAcCw8FaQgDDB03MV1YRWRaNRBLZ1tQSVFz", "Snjiq");
        Client.lIlIllI[Client.lIllllI[400]] = llIlllII("sBthg4vkrbH76veAqHJ9vwgTmTwKe0FInljEwxHsiy4FVuZgMUXmYJMElnYA83Noi/FP1JBC3sEzXnBrCdWZ1b99M2cMvIhu3TG5LqWlLinNMIIKstVCrg==", "rbAeS");
        Client.lIlIllI[Client.lIllllI[401]] = llIlllIl("oWMhO3v4fDDPxh3wHtiXwfOv6Llpbsw/I3f/zYqZdw4quxkKYLZQU0CyHXlsAbgOyiSa/R+XCxA=", "tnupG");
        Client.lIlIllI[Client.lIllllI[402]] = llIllllI("CxsbaSoWDg4jHl0xGDQTFg9PCgIfDQU+STAKADNJOjAifQ4BASUmAh4ND31VQVhBZ0dTQg==", "sbaGg");
        Client.lIlIllI[Client.lIllllI[403]] = llIlllIl("y0ClRp6afZm0wx9/XhRC/K5I1EBe/4Vg2rdvV2RGCkwp6iFgyXoAp954g8SRo2ZQvyI45iEkN7lIGxyKILVumg7nxvs7C8GueswzPng4KT0=", "ucGjS");
        Client.lIlIllI[Client.lIllllI[404]] = llIlllIl("xjdRA84E42lCwxb0W0CSuYmdMr0idwVWSQHsn9UgTJXSKj5FGJn9SQ==", "jAynk");
        Client.lIlIllI[Client.lIllllI[405]] = llIlllII("XfNDAKP29aNePZXbBDRRpYeSvEB7CojHUeU4JqDNAuO6Dr+mfAy8Ow==", "VoWAG");
        Client.lIlIllI[Client.lIllllI[406]] = llIlllII("iI9n5YlagCm1nOsR9lR3mB10gAuBy9v/CNIkhMq2+RbvDLJye34HOoORLdXInZux", "bsnUy");
        Client.lIlIllI[Client.lIllllI[407]] = llIlllIl("i9aj6SYQ5FXuE2JQFfbuvgxjK7tEaqzK63nwK2HoiHYqHNAl70phtQ==", "sDctR");
        Client.lIlIllI[Client.lIllllI[408]] = llIlllII("SPj4UEp7RmxkLERmgZ0HvscYXOV8ght418+85qbXf0+USPzr0rZL8h4PyYoORmFF65yBmkIw9WLSElfYDSYTeA==", "zRrKk");
        Client.lIlIllI[Client.lIllllI[409]] = llIlllII("ogEu5ZitGvbic19sT7I5UI28ieMsBhCKbhDdURZRAmuviWgGEh1c/A==", "AVJbE");
        Client.lIlIllI[Client.lIllllI[410]] = llIlllIl("rfQaI5hLl36X9zryE5XXmBF1CUbY5hW+Tn4TiVjkSiLX8VwrNsZcbHryNnebN31zm0GD1BWEida8sCm5FXt7ww==", "AporJ");
        Client.lIlIllI[Client.lIllllI[411]] = llIlllIl("N0+JI3xt9bSyb7ETuxAQaOM6+1EQSOiuxI72EJaIf0qLB19N7wjpBF1KaO5o58nT", "LUvLI");
        Client.lIlIllI[Client.lIllllI[412]] = llIlllII("BS+IZEPICPLDXAKxS/1VH3WqdmXiocMzvE8VOQKBHaNsh9yxfZDAv5XjK4ny/az1ev0zo5qfopBI95qyxyysvg==", "uJQTH");
        Client.lIlIllI[Client.lIllllI[413]] = llIlllIl("rZ0X0TQTeTCFUwouxWXVT4Ca16yJ9NhjkmSqMwY2pURi4yiZC3HaoQ==", "VsbbC");
        Client.lIlIllI[Client.lIllllI[414]] = llIllllI("Nx8UfB8qCgE2K2ElAjs3IRJUPT4rKwEnISouCz4iKhRUZmZ1Rk5ycg==", "OfnRR");
        Client.lIlIllI[Client.lIllllI[415]] = llIlllII("L8Fbqa5ntB5EPzfgqvSFePpvDngvRvVIwanVdjtIe2cRUfo6P+33fVmb9oerNB14", "XUWJg");
        Client.lIlIllI[Client.lIllllI[416]] = llIlllIl("uGse3VqI76Pg7olDTKNB3kQN/QvNXFms+x8LgtmkAY/U73Jsa/hhkNBDnN1iZFHsrPPbnykPp8dZoEplWco8A/OxpHQkzCjewCVP/axKzLg=", "qiLLX");
        Client.lIlIllI[Client.lIllllI[417]] = llIlllIl("J5c2tcMbXgs1/RYD8w9IhecMxh31o+lYzuIaHvkqze/29M7yvmKoNQ==", "GzLJh");
        Client.lIlllII = null;
    }
    
    private static String llIllllI(String lllIIlIlIIllIIl, final String lllIIlIlIIllIII) {
        lllIIlIlIIllIIl = new String(Base64.getDecoder().decode(lllIIlIlIIllIIl.getBytes(StandardCharsets.UTF_8)), StandardCharsets.UTF_8);
        final StringBuilder lllIIlIlIIlllII = new StringBuilder();
        final char[] lllIIlIlIIllIll = lllIIlIlIIllIII.toCharArray();
        int lllIIlIlIIllIlI = Client.lIllllI[0];
        final long lllIIlIlIIlIlII = (Object)lllIIlIlIIllIIl.toCharArray();
        final boolean lllIIlIlIIlIIll = lllIIlIlIIlIlII.length != 0;
        short lllIIlIlIIlIIlI = (short)Client.lIllllI[0];
        while (llllllII(lllIIlIlIIlIIlI, lllIIlIlIIlIIll ? 1 : 0)) {
            final char lllIIlIlIIlllll = lllIIlIlIIlIlII[lllIIlIlIIlIIlI];
            lllIIlIlIIlllII.append((char)(lllIIlIlIIlllll ^ lllIIlIlIIllIll[lllIIlIlIIllIlI % lllIIlIlIIllIll.length]));
            "".length();
            ++lllIIlIlIIllIlI;
            ++lllIIlIlIIlIIlI;
            "".length();
            if (" ".length() << (" ".length() << " ".length()) <= 0) {
                return null;
            }
        }
        return String.valueOf(lllIIlIlIIlllII);
    }
    
    @Mod.EventHandler
    public void init(final FMLInitializationEvent lllIlIIIIIllIlI) {
        // invokedynamic(13:(Lorg/apache/logging/log4j/Logger;Ljava/lang/String;)V, invokedynamic(12:(Lxyz/Melody/Client;)Lorg/apache/logging/log4j/Logger;, this), Client.lIlIllI[Client.lIllllI[37]])
        // invokedynamic(100:(I)V, Client.lIllllI[2])
        // invokedynamic(93:(Lnet/minecraftforge/fml/common/eventhandler/EventBus;Ljava/lang/Object;)V, invokedynamic(92:()Lnet/minecraftforge/fml/common/eventhandler/EventBus;), invokedynamic(104:()Lxyz/Melody/Performance/FoamFix/ProxyCommon;))
        this.initFMLFeature();
    }
    // invokedynamic(106:(Lxyz/Melody/Performance/FoamFix/ProxyCommon;)V, invokedynamic(104:()Lxyz/Melody/Performance/FoamFix/ProxyCommon;))
    
    public static void preCharset() {
        try {
            final Charset lllIIlllIlIIlll = invokedynamic(98:()Ljava/nio/charset/Charset;);
            // invokedynamic(13:(Lorg/apache/logging/log4j/Logger;Ljava/lang/String;)V, invokedynamic(1:(Ljava/lang/Class;)Lorg/apache/logging/log4j/Logger;, Client.class), invokedynamic(17:(Ljava/lang/StringBuilder;)Ljava/lang/String;, invokedynamic(16:(Ljava/lang/StringBuilder;Ljava/lang/Object;)Ljava/lang/StringBuilder;, invokedynamic(14:(Ljava/lang/StringBuilder;Ljava/lang/String;)Ljava/lang/StringBuilder;, new StringBuilder(), Client.lIlIllI[Client.lIllllI[67]]), invokedynamic(98:()Ljava/nio/charset/Charset;))))
            if (lIIIIIIIl((Object)lllIIlllIlIIlll, invokedynamic(186:(Ljava/lang/String;)Ljava/nio/charset/Charset;, Client.lIlIllI[Client.lIllllI[68]]))) {
                final Class<?> lllIIlllIlIlIIl = invokedynamic(187:(Ljava/lang/String;)Ljava/lang/Class;, Client.lIlIllI[Client.lIllllI[69]]);
                final Field lllIIlllIlIlIII = invokedynamic(188:(Ljava/lang/Class;Ljava/lang/String;)Ljava/lang/reflect/Field;, lllIIlllIlIlIIl, Client.lIlIllI[Client.lIllllI[70]]);
            }
            // invokedynamic(189:(Ljava/lang/reflect/Field;Z)V, lllIIlllIlIlIII, Client.lIllllI[2])
            // invokedynamic(190:(Ljava/lang/reflect/Field;Ljava/lang/Object;Ljava/lang/Object;)V, lllIIlllIlIlIII, lllIIlllIlIIlll, invokedynamic(186:(Ljava/lang/String;)Ljava/nio/charset/Charset;, Client.lIlIllI[Client.lIllllI[71]]))
            // invokedynamic(13:(Lorg/apache/logging/log4j/Logger;Ljava/lang/String;)V, invokedynamic(1:(Ljava/lang/Class;)Lorg/apache/logging/log4j/Logger;, Client.class), invokedynamic(17:(Ljava/lang/StringBuilder;)Ljava/lang/String;, invokedynamic(16:(Ljava/lang/StringBuilder;Ljava/lang/Object;)Ljava/lang/StringBuilder;, invokedynamic(14:(Ljava/lang/StringBuilder;Ljava/lang/String;)Ljava/lang/StringBuilder;, new StringBuilder(), Client.lIlIllI[Client.lIllllI[72]]), invokedynamic(98:()Ljava/nio/charset/Charset;))))
            "".length();
            if (" ".length() > " ".length() << (" ".length() << " ".length())) {
                return;
            }
        }
        catch (Exception lllIIlllIlIIllI) {
        }
        // invokedynamic(146:(Ljava/lang/Exception;)V, lllIIlllIlIIllI)
    }
    
    private void readEnabledMods() {
        // invokedynamic(13:(Lorg/apache/logging/log4j/Logger;Ljava/lang/String;)V, invokedynamic(12:(Lxyz/Melody/Client;)Lorg/apache/logging/log4j/Logger;, this), Client.lIlIllI[Client.lIllllI[119]])
        final List<String> lllIIllIIlIIIIl = invokedynamic(203:(Ljava/lang/String;)Ljava/util/List;, Client.lIlIllI[Client.lIllllI[120]]);
        final Exception lllIIllIIIllllI = invokedynamic(120:(Ljava/util/List;)Ljava/util/Iterator;, lllIIllIIlIIIIl);
        while (llllllIl(invokedynamic(121:(Ljava/util/Iterator;)Z, lllIIllIIIllllI))) {
            final String lllIIllIIlIIIll = (String)invokedynamic(122:(Ljava/util/Iterator;)Ljava/lang/Object;, lllIIllIIIllllI);
            final Module lllIIllIIlIIlII = invokedynamic(225:(Ljava/lang/String;)Lxyz/Melody/module/Module;, lllIIllIIlIIIll);
            if (lIIIIIlIl(lllIIllIIlIIlII)) {
                "".length();
                if (" ".length() << " ".length() == 0) {
                    return;
                }
                continue;
            }
            else {
                // invokedynamic(229:(Lxyz/Melody/module/Module;Z)V, lllIIllIIlIIlII, Client.lIllllI[2])
                // invokedynamic(13:(Lorg/apache/logging/log4j/Logger;Ljava/lang/String;)V, invokedynamic(12:(Lxyz/Melody/Client;)Lorg/apache/logging/log4j/Logger;, this), invokedynamic(17:(Ljava/lang/StringBuilder;)Ljava/lang/String;, invokedynamic(14:(Ljava/lang/StringBuilder;Ljava/lang/String;)Ljava/lang/StringBuilder;, invokedynamic(14:(Ljava/lang/StringBuilder;Ljava/lang/String;)Ljava/lang/StringBuilder;, invokedynamic(14:(Ljava/lang/StringBuilder;Ljava/lang/String;)Ljava/lang/StringBuilder;, new StringBuilder(), Client.lIlIllI[Client.lIllllI[121]]), invokedynamic(228:(Lxyz/Melody/module/Module;)Ljava/lang/String;, lllIIllIIlIIlII)), Client.lIlIllI[Client.lIllllI[122]])))
                "".length();
                if (-(166 + 78 - 52 + 7 ^ (0xF2 ^ 0x93) << " ".length()) >= 0) {
                    return;
                }
                continue;
            }
        }
    }
    // invokedynamic(13:(Lorg/apache/logging/log4j/Logger;Ljava/lang/String;)V, invokedynamic(12:(Lxyz/Melody/Client;)Lorg/apache/logging/log4j/Logger;, this), Client.lIlIllI[Client.lIllllI[123]])
    
    private void initModHider() {
        final File lllIIllllIIlIII = new File(invokedynamic(158:()Ljava/io/File;), Client.lIlIllI[Client.lIllllI[52]]);
        // invokedynamic(159:(Lnet/minecraftforge/common/config/Configuration;)V, new Configuration(lllIIllllIIlIII))
        // invokedynamic(161:(Lnet/minecraftforge/common/config/Configuration;)V, invokedynamic(160:()Lnet/minecraftforge/common/config/Configuration;))
        final char lllIIllllIIIllI = invokedynamic(120:(Ljava/util/List;)Ljava/util/Iterator;, invokedynamic(163:(Lnet/minecraftforge/fml/common/Loader;)Ljava/util/List;, invokedynamic(162:()Lnet/minecraftforge/fml/common/Loader;)));
        while (llllllIl(invokedynamic(121:(Ljava/util/Iterator;)Z, lllIIllllIIIllI))) {
            final ModContainer lllIIllllIIlIlI = (ModContainer)invokedynamic(122:(Ljava/util/Iterator;)Ljava/lang/Object;, lllIIllllIIIllI);
            // invokedynamic(170:(Ljava/util/HashMap;Ljava/lang/Object;Ljava/lang/Object;)Ljava/lang/Object;, invokedynamic(164:()Ljava/util/HashMap;), invokedynamic(165:(Lnet/minecraftforge/fml/common/ModContainer;)Ljava/lang/String;, lllIIllllIIlIlI), invokedynamic(169:(Lnet/minecraftforge/common/config/Configuration;Ljava/lang/String;Ljava/lang/String;ZLjava/lang/String;)Lnet/minecraftforge/common/config/Property;, invokedynamic(160:()Lnet/minecraftforge/common/config/Configuration;), Client.lIlIllI[Client.lIllllI[53]], invokedynamic(166:(Lnet/minecraftforge/fml/common/ModContainer;)Ljava/lang/String;, lllIIllllIIlIlI), invokedynamic(168:(Ljava/util/List;Ljava/lang/Object;)Z, invokedynamic(167:()Ljava/util/List;), invokedynamic(165:(Lnet/minecraftforge/fml/common/ModContainer;)Ljava/lang/String;, lllIIllllIIlIlI)), invokedynamic(165:(Lnet/minecraftforge/fml/common/ModContainer;)Ljava/lang/String;, lllIIllllIIlIlI)))
            "".length();
            "".length();
            if (" ".length() << (" ".length() << " ".length()) <= (((0x10 ^ 0x9) << (" ".length() << " ".length()) ^ (0x6D ^ 0x4)) << " ".length() & ((0x2E ^ 0x47 ^ (0x7A ^ 0x63) << (" ".length() << " ".length())) << " ".length() ^ -" ".length()))) {
                return;
            }
        }
    }
    
    private void readCustomIS() {
        // invokedynamic(13:(Lorg/apache/logging/log4j/Logger;Ljava/lang/String;)V, invokedynamic(12:(Lxyz/Melody/Client;)Lorg/apache/logging/log4j/Logger;, this), Client.lIlIllI[Client.lIllllI[107]])
        final List<String> lllIIllIlIIIIll = invokedynamic(203:(Ljava/lang/String;)Ljava/util/List;, Client.lIlIllI[Client.lIllllI[108]]);
        final byte lllIIllIlIIIIII = invokedynamic(120:(Ljava/util/List;)Ljava/util/Iterator;, lllIIllIlIIIIll);
        while (llllllIl(invokedynamic(121:(Ljava/util/Iterator;)Z, lllIIllIlIIIIII))) {
            final String lllIIllIlIIIlIl = (String)invokedynamic(122:(Ljava/util/Iterator;)Ljava/lang/Object;, lllIIllIlIIIIII);
            final ItemSwitcher lllIIllIlIIIllI = (ItemSwitcher)invokedynamic(73:(Lxyz/Melody/System/Managers/Client/ModuleManager;Ljava/lang/Class;)Lxyz/Melody/module/Module;, invokedynamic(72:(Lxyz/Melody/Client;)Lxyz/Melody/System/Managers/Client/ModuleManager;, invokedynamic(65:()Lxyz/Melody/Client;)), ItemSwitcher.class);
            // invokedynamic(223:(Lxyz/Melody/module/modules/QOL/Swappings/ItemSwitcher;Ljava/lang/String;)V, lllIIllIlIIIllI, lllIIllIlIIIlIl)
            // invokedynamic(13:(Lorg/apache/logging/log4j/Logger;Ljava/lang/String;)V, invokedynamic(12:(Lxyz/Melody/Client;)Lorg/apache/logging/log4j/Logger;, this), invokedynamic(17:(Ljava/lang/StringBuilder;)Ljava/lang/String;, invokedynamic(14:(Ljava/lang/StringBuilder;Ljava/lang/String;)Ljava/lang/StringBuilder;, invokedynamic(14:(Ljava/lang/StringBuilder;Ljava/lang/String;)Ljava/lang/StringBuilder;, invokedynamic(14:(Ljava/lang/StringBuilder;Ljava/lang/String;)Ljava/lang/StringBuilder;, new StringBuilder(), Client.lIlIllI[Client.lIllllI[109]]), lllIIllIlIIIlIl), Client.lIlIllI[Client.lIllllI[110]])))
            "".length();
            if (null != null) {
                return;
            }
        }
    }
    // invokedynamic(13:(Lorg/apache/logging/log4j/Logger;Ljava/lang/String;)V, invokedynamic(12:(Lxyz/Melody/Client;)Lorg/apache/logging/log4j/Logger;, this), Client.lIlIllI[Client.lIllllI[111]])
    
    public static void middleClick() {
        if (lllllllI(invokedynamic(173:(Ljava/lang/Class;Ljava/lang/String;)Z, invokedynamic(0:(Ljava/lang/Object;)Ljava/lang/Class;, invokedynamic(19:()Lnet/minecraft/client/Minecraft;)), Client.lIlIllI[Client.lIllllI[59]]))) {
            // invokedynamic(173:(Ljava/lang/Class;Ljava/lang/String;)Z, invokedynamic(0:(Ljava/lang/Object;)Ljava/lang/Class;, invokedynamic(19:()Lnet/minecraft/client/Minecraft;)), Client.lIlIllI[Client.lIllllI[1]])
            "".length();
        }
    }
    
    public void saveMenuMode() {
        if (lllllllI(invokedynamic(35:(Lxyz/Melody/System/Melody/Authentication/AuthManager;)Z, invokedynamic(25:(Lxyz/Melody/Client;)Lxyz/Melody/System/Melody/Authentication/AuthManager;, this)))) {
            return;
        }
        "".length();
        final String lllIIlllIIlIIIl = invokedynamic(206:(Z)Ljava/lang/String;, invokedynamic(205:()Z));
    }
    // invokedynamic(207:(Ljava/lang/String;Ljava/lang/String;Z)V, Client.lIlIllI[Client.lIllllI[80]], lllIIlllIIlIIIl, Client.lIllllI[0])
    
    private static boolean lIIIIIlll(final int lllIIlIlIIIIIIl, final int lllIIlIlIIIIIII) {
        return lllIIlIlIIIIIIl == lllIIlIlIIIIIII;
    }
    
    @Mod.EventHandler
    public void postInit(final FMLPostInitializationEvent lllIlIIIIIlIIll) {
        // invokedynamic(100:(I)V, Client.lIllllI[4])
        // invokedynamic(107:(Lxyz/Melody/Performance/FoamFix/ProxyCommon;)V, invokedynamic(104:()Lxyz/Melody/Performance/FoamFix/ProxyCommon;))
        // invokedynamic(109:(Lxyz/Melody/Performance/Math/AIImprovements;Lnet/minecraftforge/fml/common/event/FMLPostInitializationEvent;)V, invokedynamic(108:(Lxyz/Melody/Client;)Lxyz/Melody/Performance/Math/AIImprovements;, this), lllIlIIIIIlIIll)
        // invokedynamic(110:(Lxyz/Melody/Client;)Lxyz/Melody/MelodyInitializer;, this)
        "".length();
        // invokedynamic(111:()V)
        // invokedynamic(110:(Lxyz/Melody/Client;)Lxyz/Melody/MelodyInitializer;, this)
        "".length();
        // invokedynamic(112:()V)
        // invokedynamic(110:(Lxyz/Melody/Client;)Lxyz/Melody/MelodyInitializer;, this)
        "".length();
        // invokedynamic(113:()V)
        // invokedynamic(110:(Lxyz/Melody/Client;)Lxyz/Melody/MelodyInitializer;, this)
        "".length();
    }
    // invokedynamic(114:()V)
    // invokedynamic(13:(Lorg/apache/logging/log4j/Logger;Ljava/lang/String;)V, invokedynamic(12:(Lxyz/Melody/Client;)Lorg/apache/logging/log4j/Logger;, this), Client.lIlIllI[Client.lIllllI[38]])
    
    public static void drawTitle(final String lllIIlllIllllll, final EnumChatFormatting lllIIlllIlllllI) {
    }
    // invokedynamic(175:(Lnet/minecraft/client/gui/GuiIngame;Ljava/lang/String;Ljava/lang/String;III)V, invokedynamic(174:(Lnet/minecraft/client/Minecraft;)Lnet/minecraft/client/gui/GuiIngame;, invokedynamic(19:()Lnet/minecraft/client/Minecraft;)), invokedynamic(17:(Ljava/lang/StringBuilder;)Ljava/lang/String;, invokedynamic(14:(Ljava/lang/StringBuilder;Ljava/lang/String;)Ljava/lang/StringBuilder;, invokedynamic(16:(Ljava/lang/StringBuilder;Ljava/lang/Object;)Ljava/lang/StringBuilder;, new StringBuilder(), lllIIlllIlllllI), lllIIlllIllllll)), null, Client.lIllllI[0], Client.lIllllI[57], Client.lIllllI[58])
    
    @Mod.EventHandler
    public void preInit(final FMLPreInitializationEvent lllIlIIIIIlllIl) {
    }
    // invokedynamic(13:(Lorg/apache/logging/log4j/Logger;Ljava/lang/String;)V, invokedynamic(12:(Lxyz/Melody/Client;)Lorg/apache/logging/log4j/Logger;, this), Client.lIlIllI[Client.lIllllI[35]])
    // invokedynamic(13:(Lorg/apache/logging/log4j/Logger;Ljava/lang/String;)V, invokedynamic(12:(Lxyz/Melody/Client;)Lorg/apache/logging/log4j/Logger;, this), invokedynamic(17:(Ljava/lang/StringBuilder;)Ljava/lang/String;, invokedynamic(16:(Ljava/lang/StringBuilder;Ljava/lang/Object;)Ljava/lang/StringBuilder;, invokedynamic(14:(Ljava/lang/StringBuilder;Ljava/lang/String;)Ljava/lang/StringBuilder;, new StringBuilder(), Client.lIlIllI[Client.lIllllI[36]]), invokedynamic(98:()Ljava/nio/charset/Charset;))))
    // invokedynamic(99:(Lxyz/Melody/Performance/FoamFix/api/IFoamFixHelper;)V, new FoamFixHelper())
    // invokedynamic(100:(I)V, Client.lIllllI[0])
    // invokedynamic(103:(Lxyz/Melody/Performance/FoamFix/shared/FoamFixConfig;Ljava/io/File;Z)V, invokedynamic(101:()Lxyz/Melody/Performance/FoamFix/shared/FoamFixConfig;), invokedynamic(102:(Lnet/minecraftforge/fml/common/event/FMLPreInitializationEvent;)Ljava/io/File;, lllIlIIIIIlllIl), Client.lIllllI[0])
    // invokedynamic(105:(Lxyz/Melody/Performance/FoamFix/ProxyCommon;)V, invokedynamic(104:()Lxyz/Melody/Performance/FoamFix/ProxyCommon;))
    
    private void readMenuMode() {
        // invokedynamic(13:(Lorg/apache/logging/log4j/Logger;Ljava/lang/String;)V, invokedynamic(12:(Lxyz/Melody/Client;)Lorg/apache/logging/log4j/Logger;, this), Client.lIlIllI[Client.lIllllI[74]])
        final List<String> lllIIlllIIllIIl = invokedynamic(203:(Ljava/lang/String;)Ljava/util/List;, Client.lIlIllI[Client.lIllllI[75]]);
        final byte lllIIlllIIlIllI = invokedynamic(120:(Ljava/util/List;)Ljava/util/Iterator;, lllIIlllIIllIIl);
        while (llllllIl(invokedynamic(121:(Ljava/util/Iterator;)Z, lllIIlllIIlIllI))) {
            final String lllIIlllIIllIll = (String)invokedynamic(122:(Ljava/util/Iterator;)Ljava/lang/Object;, lllIIlllIIlIllI);
            if (llllllIl(invokedynamic(79:(Ljava/lang/String;Ljava/lang/Object;)Z, lllIIlllIIllIll, Client.lIlIllI[Client.lIllllI[76]]))) {
                "".length();
            }
            // invokedynamic(204:(Z)V, Client.lIllllI[2])
            if (llllllIl(invokedynamic(79:(Ljava/lang/String;Ljava/lang/Object;)Z, lllIIlllIIllIll, Client.lIlIllI[Client.lIllllI[77]]))) {
                "".length();
            }
            // invokedynamic(204:(Z)V, Client.lIllllI[0])
            "".length();
            if (-" ".length() != -" ".length()) {
                return;
            }
        }
        final Logger logger = invokedynamic(12:(Lxyz/Melody/Client;)Lorg/apache/logging/log4j/Logger;, this);
        final StringBuilder sb = invokedynamic(14:(Ljava/lang/StringBuilder;Ljava/lang/String;)Ljava/lang/StringBuilder;, new StringBuilder(), Client.lIlIllI[Client.lIllllI[78]]);
        "".length();
    }
    // invokedynamic(13:(Lorg/apache/logging/log4j/Logger;Ljava/lang/String;)V, logger, invokedynamic(17:(Ljava/lang/StringBuilder;)Ljava/lang/String;, invokedynamic(14:(Ljava/lang/StringBuilder;Ljava/lang/String;)Ljava/lang/StringBuilder;, invokedynamic(36:(Ljava/lang/StringBuilder;Z)Ljava/lang/StringBuilder;, sb, invokedynamic(205:()Z)), Client.lIlIllI[Client.lIllllI[79]])))
    
    public static boolean isWhitelisted(final String lllIIllllIIIIll) {
        return invokedynamic(172:(Lnet/minecraftforge/common/config/Property;)Z, (Property)invokedynamic(171:(Ljava/util/HashMap;Ljava/lang/Object;)Ljava/lang/Object;, invokedynamic(164:()Ljava/util/HashMap;), lllIIllllIIIIll));
    }
    
    public static void rightClick() {
        if (lllllllI(invokedynamic(173:(Ljava/lang/Class;Ljava/lang/String;)Z, invokedynamic(0:(Ljava/lang/Object;)Ljava/lang/Class;, invokedynamic(19:()Lnet/minecraft/client/Minecraft;)), Client.lIlIllI[Client.lIllllI[54]]))) {
            // invokedynamic(173:(Ljava/lang/Class;Ljava/lang/String;)Z, invokedynamic(0:(Ljava/lang/Object;)Ljava/lang/Class;, invokedynamic(19:()Lnet/minecraft/client/Minecraft;)), Client.lIlIllI[Client.lIllllI[55]])
            "".length();
        }
    }
    
    private static boolean lIIIIIIIl(final Object lllIIlIIlllIlIl, final Object lllIIlIIlllIlII) {
        return lllIIlIIlllIlIl != lllIIlIIlllIlII;
    }
    
    private static boolean lIIIIIllI(final int lllIIlIIllllIIl, final int lllIIlIIllllIII) {
        return lllIIlIIllllIIl <= lllIIlIIllllIII;
    }
    
    public void log(final String lllIIlIlllIlIII) {
    }
    // invokedynamic(13:(Lorg/apache/logging/log4j/Logger;Ljava/lang/String;)V, invokedynamic(12:(Lxyz/Melody/Client;)Lorg/apache/logging/log4j/Logger;, this), invokedynamic(17:(Ljava/lang/StringBuilder;)Ljava/lang/String;, invokedynamic(14:(Ljava/lang/StringBuilder;Ljava/lang/String;)Ljava/lang/StringBuilder;, invokedynamic(14:(Ljava/lang/StringBuilder;Ljava/lang/String;)Ljava/lang/StringBuilder;, new StringBuilder(), Client.lIlIllI[Client.lIllllI[148]]), lllIIlIlllIlIII)))
    
    private void readCustomName() {
        final List<String> lllIIlllIIIlIII = invokedynamic(203:(Ljava/lang/String;)Ljava/util/List;, Client.lIlIllI[Client.lIllllI[81]]);
        final double lllIIlllIIIIlIl = invokedynamic(120:(Ljava/util/List;)Ljava/util/Iterator;, lllIIlllIIIlIII);
        while (llllllIl(invokedynamic(121:(Ljava/util/Iterator;)Z, lllIIlllIIIIlIl))) {
            final String lllIIlllIIIlIlI = (String)invokedynamic(122:(Ljava/util/Iterator;)Ljava/lang/Object;, lllIIlllIIIIlIl);
            if (lIIIIIIIl(lllIIlllIIIlIlI, Client.lIlIllI[Client.lIllllI[82]])) {
                if (lIIIIIlIl(lllIIlllIIIlIlI)) {
                    "".length();
                    if (" ".length() << " ".length() != " ".length() << " ".length()) {
                        return;
                    }
                    continue;
                }
                else {
                    "".length();
                    // invokedynamic(208:(Ljava/lang/String;)V, lllIIlllIIIlIlI)
                    "".length();
                    if (-(116 + 85 - 60 + 54 ^ 84 + 123 - 120 + 112) >= 0) {
                        return;
                    }
                    continue;
                }
            }
        }
    }
    
    public AltManager getAccountManager() {
        return invokedynamic(50:(Lxyz/Melody/Client;)Lxyz/Melody/System/Melody/Account/AltManager;, this);
    }
    
    private static void lllllIlI() {
        (lIllllI = new int[419])[0] = (((0xCA ^ 0xC3) << (" ".length() << " ".length()) ^ (0x5F ^ 0x64)) & ((0xBC ^ 0xAF) << (" ".length() << " ".length()) ^ (0xF4 ^ 0xA7) ^ -" ".length()));
        Client.lIllllI[1] = ((0x6D ^ 0x60) << " ".length() ^ (0xBD ^ 0xA0)) << "   ".length();
        Client.lIllllI[2] = " ".length();
        Client.lIllllI[3] = " ".length() << (" ".length() << " ".length());
        Client.lIllllI[4] = " ".length() << " ".length();
        Client.lIllllI[5] = "   ".length();
        Client.lIllllI[6] = ((0x59 ^ 0x78) << " ".length() ^ (0x11 ^ 0x56));
        Client.lIllllI[7] = "   ".length() << " ".length();
        Client.lIllllI[8] = ((0x16 ^ 0x5D) << " ".length() ^ 73 + 61 - 57 + 68);
        Client.lIllllI[9] = " ".length() << "   ".length();
        Client.lIllllI[10] = ((0x83 ^ 0x9A) << " ".length() ^ (0xC ^ 0x37));
        Client.lIllllI[11] = (0xD4 ^ 0xB5 ^ (0x3A ^ 0x23) << (" ".length() << " ".length())) << " ".length();
        Client.lIllllI[12] = (0x5 ^ 0xE);
        Client.lIllllI[13] = "   ".length() << (" ".length() << " ".length());
        Client.lIllllI[14] = ((0x6 ^ 0x45) << " ".length() ^ 81 + 58 - 123 + 123);
        Client.lIllllI[15] = (0xAC ^ 0x8F ^ (0x3 ^ 0xA) << (" ".length() << " ".length())) << " ".length();
        Client.lIllllI[16] = (0x6F ^ 0x60);
        Client.lIllllI[17] = " ".length() << (" ".length() << (" ".length() << " ".length()));
        Client.lIllllI[18] = (63 + 173 - 164 + 141 ^ (0x17 ^ 0x26) << (" ".length() << " ".length()));
        Client.lIllllI[19] = (0x3B ^ 0x56 ^ (0x4E ^ 0x57) << (" ".length() << " ".length())) << " ".length();
        Client.lIllllI[20] = (0x17 ^ 0x4);
        Client.lIllllI[21] = (0x2C ^ 0x29) << (" ".length() << " ".length());
        Client.lIllllI[22] = (0x22 ^ 0x37);
        Client.lIllllI[23] = ((0x3B ^ 0x32) << "   ".length() ^ (0x52 ^ 0x11)) << " ".length();
        Client.lIllllI[24] = (0x53 ^ 0x3A ^ (0xFF ^ 0xC0) << " ".length());
        Client.lIllllI[25] = "   ".length() << "   ".length();
        Client.lIllllI[26] = (0x84 ^ 0x9F) << " ".length();
        Client.lIllllI[27] = (39 + 42 - 22 + 106 ^ (0x65 ^ 0x4A) << (" ".length() << " ".length()));
        Client.lIllllI[28] = (0x50 ^ 0x5D) << " ".length();
        Client.lIllllI[29] = (0xB0 ^ 0xAB);
        Client.lIllllI[30] = (0x94 ^ 0x93) << (" ".length() << " ".length());
        Client.lIllllI[31] = (110 + 86 - 74 + 29 ^ (0xEF ^ 0xAA) << " ".length());
        Client.lIllllI[32] = (0x45 ^ 0x4A) << " ".length();
        Client.lIllllI[33] = (0x29 ^ 0x36);
        Client.lIllllI[34] = " ".length() << (0x5B ^ 0x5E);
        Client.lIllllI[35] = (0x1A ^ 0x3B ^ ((0x18 ^ 0x55) & ~(0xFF ^ 0xB2)));
        Client.lIllllI[36] = (0x5E ^ 0x4F) << " ".length();
        Client.lIllllI[37] = (0x7F ^ 0x5C);
        Client.lIllllI[38] = (0xB3 ^ 0x92 ^ (0xBF ^ 0xBA) << "   ".length()) << (" ".length() << " ".length());
        Client.lIllllI[39] = (0x61 ^ 0x44);
        Client.lIllllI[40] = ((0x1F ^ 0x2A) << " ".length() ^ (0xE2 ^ 0x9B)) << " ".length();
        Client.lIllllI[41] = ((0x2F ^ 0x28) << (0x2B ^ 0x2E) ^ 172 + 109 - 127 + 45);
        Client.lIllllI[42] = (0x90 ^ 0x95) << "   ".length();
        Client.lIllllI[43] = (0x7D ^ 0x1E ^ (0x4B ^ 0x6E) << " ".length());
        Client.lIllllI[44] = (0x14 ^ 0x1) << " ".length();
        Client.lIllllI[45] = " ".length() << ("   ".length() << " ".length());
        Client.lIllllI[46] = ((0xB1 ^ 0xBE) << "   ".length() ^ (0x53 ^ 0x0));
        Client.lIllllI[47] = (0xCE ^ 0xC5) << (" ".length() << " ".length());
        Client.lIllllI[48] = (0x9D ^ 0xB0);
        Client.lIllllI[49] = ((0x5B ^ 0x70) << (" ".length() << " ".length()) ^ 76 + 62 - 126 + 175) << " ".length();
        Client.lIllllI[50] = (0x8C ^ 0xA3);
        Client.lIllllI[51] = "   ".length() << (" ".length() << (" ".length() << " ".length()));
        Client.lIllllI[52] = ((0x4C ^ 0x53) << (" ".length() << " ".length()) ^ (0xEF ^ 0xA2));
        Client.lIllllI[53] = (0x63 ^ 0x7A) << " ".length();
        Client.lIllllI[54] = ((0x5B ^ 0x74) << (" ".length() << " ".length()) ^ 29 + 134 - 161 + 141);
        Client.lIllllI[55] = ((0x70 ^ 0x7F) << " ".length() ^ (0xA9 ^ 0xBA)) << (" ".length() << " ".length());
        Client.lIllllI[56] = (0x4F ^ 0x3E ^ (0x15 ^ 0x4) << (" ".length() << " ".length()));
        Client.lIllllI[57] = ((0x8E ^ 0x87) << "   ".length() ^ (0xB3 ^ 0x86)) << (" ".length() << (" ".length() << " ".length()));
        Client.lIllllI[58] = (0xAA ^ 0xB3) << (" ".length() << " ".length());
        Client.lIllllI[59] = ((0x0 ^ 0x2D) << " ".length() ^ (0xFB ^ 0x96));
        Client.lIllllI[60] = (0xFC ^ 0xC3 ^ "   ".length() << " ".length());
        Client.lIllllI[61] = (0xBD ^ 0xA0) << " ".length();
        Client.lIllllI[62] = (0xBD ^ 0x86);
        Client.lIllllI[63] = (0x6 ^ 0x9) << (" ".length() << " ".length());
        Client.lIllllI[64] = (0x3 ^ 0x3E);
        Client.lIllllI[65] = ((0x39 ^ 0x28) << (" ".length() << " ".length()) ^ (0xCE ^ 0x95)) << " ".length();
        Client.lIllllI[66] = (0x22 ^ 0xB ^ (0xE ^ 0x5) << " ".length());
        Client.lIllllI[67] = (0x17 ^ 0x56);
        Client.lIllllI[68] = (0xA2 ^ 0x83) << " ".length();
        Client.lIllllI[69] = (0x41 ^ 0x20 ^ (0xD ^ 0x1C) << " ".length());
        Client.lIllllI[70] = (0x79 ^ 0x50 ^ (0x8D ^ 0x8A) << "   ".length()) << (" ".length() << " ".length());
        Client.lIllllI[71] = (28 + 79 - 55 + 79 ^ (0xC ^ 0x6F) << " ".length());
        Client.lIllllI[72] = (0x5 ^ 0x58 ^ (0xFE ^ 0xC1) << " ".length()) << " ".length();
        Client.lIllllI[73] = (0x69 ^ 0x24 ^ (0x52 ^ 0x57) << " ".length());
        Client.lIllllI[74] = (0x34 ^ 0x3D) << "   ".length();
        Client.lIllllI[75] = (0xF ^ 0x4E ^ " ".length() << "   ".length());
        Client.lIllllI[76] = ((0x1 ^ 0x1A) << (" ".length() << " ".length()) ^ (0x47 ^ 0xE)) << " ".length();
        Client.lIllllI[77] = (0x53 ^ 0x18);
        Client.lIllllI[78] = (0x26 ^ 0x35) << (" ".length() << " ".length());
        Client.lIllllI[79] = (0x40 ^ 0xD);
        Client.lIllllI[80] = (0x70 ^ 0x57) << " ".length();
        Client.lIllllI[81] = (0x9A ^ 0x81 ^ (0xA9 ^ 0xBC) << (" ".length() << " ".length()));
        Client.lIllllI[82] = (0x66 ^ 0x63) << (" ".length() << (" ".length() << " ".length()));
        Client.lIllllI[83] = (0xDC ^ 0x8D);
        Client.lIllllI[84] = (107 + 132 - 227 + 129 ^ (0x1C ^ 0x35) << (" ".length() << " ".length())) << " ".length();
        Client.lIllllI[85] = (0xFD ^ 0xAE);
        Client.lIllllI[86] = ((0x75 ^ 0x68) << (" ".length() << " ".length()) ^ (0xEF ^ 0x8E)) << (" ".length() << " ".length());
        Client.lIllllI[87] = ((0x7F ^ 0x68) << (" ".length() << " ".length()) ^ (0x7A ^ 0x73));
        Client.lIllllI[88] = (0x76 ^ 0x5D) << " ".length();
        Client.lIllllI[89] = (0xDF ^ 0x88);
        Client.lIllllI[90] = (11 + 94 - 56 + 94 ^ (0x7D ^ 0x5C) << (" ".length() << " ".length())) << "   ".length();
        Client.lIllllI[91] = -" ".length();
        Client.lIllllI[92] = (0x1 ^ 0x58);
        Client.lIllllI[93] = (0x8D ^ 0xA0) << " ".length();
        Client.lIllllI[94] = (112 + 79 - 11 + 47 ^ (0x57 ^ 0x40) << "   ".length());
        Client.lIllllI[95] = (0xA7 ^ 0xB0) << (" ".length() << " ".length());
        Client.lIllllI[96] = (0x13 ^ 0x4E);
        Client.lIllllI[97] = ("   ".length() << (" ".length() << " ".length()) ^ (0x7B ^ 0x58)) << " ".length();
        Client.lIllllI[98] = (0xE6 ^ 0xAB ^ (0x98 ^ 0x91) << " ".length());
        Client.lIllllI[99] = "   ".length() << (0x45 ^ 0x40);
        Client.lIllllI[100] = (0xDF ^ 0xBE);
        Client.lIllllI[101] = (0x17 ^ 0x26) << " ".length();
        Client.lIllllI[102] = ((0x27 ^ 0x18) << " ".length() ^ (0x4E ^ 0x53));
        Client.lIllllI[103] = (0x6D ^ 0x8);
        Client.lIllllI[104] = (0x15 ^ 0x26) << " ".length();
        Client.lIllllI[105] = (0x44 ^ 0x23);
        Client.lIllllI[106] = (0x67 ^ 0x6A) << "   ".length();
        Client.lIllllI[107] = (0x1D ^ 0x74);
        Client.lIllllI[108] = ((0x18 ^ 0x35) << (" ".length() << " ".length()) ^ 121 + 37 - 98 + 69) << " ".length();
        Client.lIllllI[109] = (0xEC ^ 0x87);
        Client.lIllllI[110] = ((0x92 ^ 0x87) << (" ".length() << " ".length()) ^ (0xF9 ^ 0xB6)) << (" ".length() << " ".length());
        Client.lIllllI[111] = (0x11 ^ 0x7C);
        Client.lIllllI[112] = (0x35 ^ 0x2) << " ".length();
        Client.lIllllI[113] = ((0x7C ^ 0x45) << " ".length() ^ (0x41 ^ 0x5C));
        Client.lIllllI[114] = (0xC4 ^ 0xC3) << (" ".length() << (" ".length() << " ".length()));
        Client.lIllllI[115] = (181 + 202 - 181 + 39 ^ " ".length() << (0x28 ^ 0x2F));
        Client.lIllllI[116] = (0x6F ^ 0x72 ^ (0xCC ^ 0xC5) << (" ".length() << " ".length())) << " ".length();
        Client.lIllllI[117] = (0x47 ^ 0x34);
        Client.lIllllI[118] = (0xB8 ^ 0xA5) << (" ".length() << " ".length());
        Client.lIllllI[119] = (0xE2 ^ 0x97);
        Client.lIllllI[120] = (0x3 ^ 0x38) << " ".length();
        Client.lIllllI[121] = (0xD1 ^ 0x98 ^ (0x23 ^ 0x3C) << " ".length());
        Client.lIllllI[122] = ((0xA3 ^ 0xBA) << " ".length() ^ (0x3C ^ 0x1)) << "   ".length();
        Client.lIllllI[123] = (0x3A ^ 0x4D ^ (0x70 ^ 0x77) << " ".length());
        Client.lIllllI[124] = (0x17 ^ 0x2A) << " ".length();
        Client.lIllllI[125] = (0x60 ^ 0x1B);
        Client.lIllllI[126] = (" ".length() << (" ".length() << " ".length()) ^ (0xAB ^ 0xB0)) << (" ".length() << " ".length());
        Client.lIllllI[127] = ((0x9F ^ 0x96) << "   ".length() ^ (0x7 ^ 0x32));
        Client.lIllllI[128] = (0x35 ^ 0x24 ^ (0xBB ^ 0xAC) << " ".length()) << " ".length();
        Client.lIllllI[129] = 27 + 107 - 120 + 113;
        Client.lIllllI[130] = " ".length() << ((0xDA ^ 0x91) << " ".length() ^ 116 + 25 - 43 + 47);
        Client.lIllllI[131] = (0x30 ^ 0x5D) + (0x2F ^ 0x3C) - ((0x5C ^ 0x51) << "   ".length()) + (0x41 ^ 0x28);
        Client.lIllllI[132] = ((0x21 ^ 0x3E) << " ".length() ^ 23 + 87 - 18 + 35) << " ".length();
        Client.lIllllI[133] = 100 + 4 - 75 + 102;
        Client.lIllllI[134] = ((0x4C ^ 0x4B) << "   ".length() ^ (0x6C ^ 0x75)) << (" ".length() << " ".length());
        Client.lIllllI[135] = 69 + 78 - 120 + 106;
        Client.lIllllI[136] = (0x33 ^ 0x70) << " ".length();
        Client.lIllllI[137] = (0x30 ^ 0x57) + ((0x9A ^ 0x8B) << " ".length()) - (0xDD ^ 0x9E) + (0x79 ^ 0x38);
        Client.lIllllI[138] = (0xBC ^ 0xAD) << "   ".length();
        Client.lIllllI[139] = (0xB5 ^ 0xAC) + ((0xB7 ^ 0xA0) << (" ".length() << " ".length())) - -(0xA4 ^ 0xAC) + ("   ".length() << (" ".length() << " ".length()));
        Client.lIllllI[140] = ((0x34 ^ 0x5D) << " ".length() ^ 53 + 114 - 141 + 125) << " ".length();
        Client.lIllllI[141] = (0xD7 ^ 0xB0) + (48 + 18 - 59 + 122) - (0xED ^ 0x82) + ((0x74 ^ 0x7D) << " ".length());
        Client.lIllllI[142] = (0x97 ^ 0xB4) << (" ".length() << " ".length());
        Client.lIllllI[143] = 53 + 68 - 99 + 119;
        Client.lIllllI[144] = (0x3 ^ 0x44) << " ".length();
        Client.lIllllI[145] = ((0x83 ^ 0x94) << (" ".length() << " ".length())) + (0xE0 ^ 0x91) - ((0x62 ^ 0x5F) << " ".length()) + ((0xAF ^ 0xA0) << (" ".length() << " ".length()));
        Client.lIllllI[146] = (0x3D ^ 0x34) << (" ".length() << (" ".length() << " ".length()));
        Client.lIllllI[147] = (0x78 ^ 0x1D) + ((0x18 ^ 0x31) << " ".length()) - ("   ".length() << (" ".length() << (" ".length() << " ".length()))) + ((0xD ^ 0x8) << " ".length());
        Client.lIllllI[148] = (0x3D ^ 0x74) << " ".length();
        Client.lIllllI[149] = (0xBD ^ 0x9E) + (0xB0 ^ 0xB9) - -(0x11 ^ 0x5B) + (0x0 ^ 0x1D);
        Client.lIllllI[150] = ((0xAA ^ 0xB5) << " ".length() ^ (0x30 ^ 0x2B)) << (" ".length() << " ".length());
        Client.lIllllI[151] = 117 + 44 - 92 + 80;
        Client.lIllllI[152] = (0x6D ^ 0x4A ^ (0x5C ^ 0x47) << (" ".length() << " ".length())) << " ".length();
        Client.lIllllI[153] = (0xF3 ^ 0x9C) + ((0x2F ^ 0x3C) << (" ".length() << " ".length())) - (0x1B ^ 0x66) + (0x7F ^ 0x26);
        Client.lIllllI[154] = (94 + 94 - 32 + 21 ^ (0x73 ^ 0x22) << " ".length()) << "   ".length();
        Client.lIllllI[155] = ((0x38 ^ 0x27) << " ".length()) + (0x17 ^ 0xE) - ((0x67 ^ 0x6E) << " ".length()) + ((0x3B ^ 0x2E) << (" ".length() << " ".length()));
        Client.lIllllI[156] = (0xCD ^ 0x9A ^ (0x30 ^ 0x3D) << " ".length()) << " ".length();
        Client.lIllllI[157] = 113 + 61 - 49 + 30;
        Client.lIllllI[158] = ((0x23 ^ 0x36) << (" ".length() << " ".length()) ^ (0x6B ^ 0x18)) << (" ".length() << " ".length());
        Client.lIllllI[159] = (" ".length() << " ".length()) + ((0xBB ^ 0xB6) << "   ".length()) - (0x44 ^ 0x11) + ((0xD7 ^ 0xC6) << "   ".length());
        Client.lIllllI[160] = (0x69 ^ 0x26) << " ".length();
        Client.lIllllI[161] = 108 + 149 - 243 + 145;
        Client.lIllllI[162] = " ".length() << (" ".length() << "   ".length());
        Client.lIllllI[163] = (164 + 159 - 235 + 95 ^ (0x80 ^ 0xA1) << (" ".length() << " ".length())) << (" ".length() << " ".length());
        Client.lIllllI[164] = (0x85 ^ 0xBE ^ (0x61 ^ 0x7E) << " ".length()) << (0x44 ^ 0x1B ^ (0xEC ^ 0xC1) << " ".length());
        Client.lIllllI[165] = 140 + 3 + 1 + 17;
        Client.lIllllI[166] = ((0x6E ^ 0x5F) << " ".length() ^ (0x45 ^ 0x76)) << " ".length();
        Client.lIllllI[167] = ((0xA7 ^ 0xB2) << (" ".length() << " ".length())) + (0x53 ^ 0x2) - ((0xC9 ^ 0x98) << " ".length()) + ((0xB6 ^ 0xB3) << (0xA4 ^ 0xA1));
        Client.lIllllI[168] = (0xC2 ^ 0xBF ^ (0x2 ^ 0x9) << " ".length()) << " ".length();
        Client.lIllllI[169] = (0xAF ^ 0x86) << (" ".length() << " ".length());
        Client.lIllllI[170] = (0x61 ^ 0x8) + ((0x7 ^ 0x26) << (" ".length() << " ".length())) - ((0x75 ^ 0x66) << (" ".length() << " ".length())) + (" ".length() << (" ".length() << " ".length()));
        Client.lIllllI[171] = (0xEF ^ 0xBC) << " ".length();
        Client.lIllllI[172] = (0xBD ^ 0xB0) + (0x27 ^ 0x20) - -(0x13 ^ 0x28) + ((0x81 ^ 0x8A) << "   ".length());
        Client.lIllllI[173] = (0x2D ^ 0x38) << "   ".length();
        Client.lIllllI[174] = 95 + 83 - 120 + 111;
        Client.lIllllI[175] = (0x41 ^ 0x14) << " ".length();
        Client.lIllllI[176] = (" ".length() << (" ".length() << (" ".length() << " ".length()))) + (0x5B ^ 0x44) - -(0xD9 ^ 0xA1) + (" ".length() << (" ".length() << " ".length()));
        Client.lIllllI[177] = (0x27 ^ 0xC) << (" ".length() << " ".length());
        Client.lIllllI[178] = 106 + 93 - 60 + 88;
        Client.lIllllI[179] = ((0x4E ^ 0x49) << " ".length()) + (0x71 ^ 0x12) - -(0x69 ^ 0x4E) + (0x9D ^ 0x88);
        Client.lIllllI[180] = (0xD ^ 0x0 ^ (0x63 ^ 0x4E) << " ".length()) << " ".length();
        Client.lIllllI[181] = 50 + 76 - 106 + 155;
        Client.lIllllI[182] = 129 + 250 - 362 + 234;
        Client.lIllllI[183] = (0x6A ^ 0x29 ^ (0x14 ^ 0x1D) << "   ".length()) << (" ".length() << (" ".length() << " ".length()));
        Client.lIllllI[184] = (0x63 ^ 0x56) << (" ".length() << " ".length());
        Client.lIllllI[185] = (0x72 ^ 0x3F) + (72 + 29 + 22 + 32) - ((0x69 ^ 0x3C) << " ".length()) + (0x3A ^ 0x49);
        Client.lIllllI[186] = ((0x25 ^ 0x6) << " ".length() ^ (0x33 ^ 0x7A)) << (" ".length() << (" ".length() << " ".length()));
        Client.lIllllI[187] = (0x7A ^ 0x23) << " ".length();
        Client.lIllllI[188] = 130 + 129 - 193 + 113;
        Client.lIllllI[189] = 38 + 193 - 57 + 59;
        Client.lIllllI[190] = ((0x2C ^ 0x25) << (" ".length() << (" ".length() << " ".length())) ^ 31 + 138 + 17 + 3) << (" ".length() << " ".length());
        Client.lIllllI[191] = 129 + 27 - 80 + 57 + ((0x4C ^ 0x43) << (" ".length() << " ".length())) - ((0x3F ^ 0x2) << " ".length()) + ((0x37 ^ 0x0) << " ".length());
        Client.lIllllI[192] = (" ".length() << " ".length() ^ (0xF ^ 0x7C)) << " ".length();
        Client.lIllllI[193] = (0xFC ^ 0xA7) << " ".length();
        Client.lIllllI[194] = (0x42 ^ 0x7B) << (" ".length() << " ".length());
        Client.lIllllI[195] = (0xD6 ^ 0xC3) + (20 + 91 - 8 + 38) - -(0x59 ^ 0x54) + (" ".length() << "   ".length());
        Client.lIllllI[196] = (0x5C ^ 0x4B) << "   ".length();
        Client.lIllllI[197] = ((0x3D ^ 0x3A) << "   ".length()) + (53 + 87 - 27 + 40) - (0xA ^ 0x77) + (0xC6 ^ 0xA3);
        Client.lIllllI[198] = (0x65 ^ 0x38) << " ".length();
        Client.lIllllI[199] = (0xFD ^ 0xAC) + ((0x62 ^ 0x4D) << " ".length()) - (0xC8 ^ 0xBD) + (103 + 59 - 97 + 64);
        Client.lIllllI[200] = "   ".length() << ("   ".length() << " ".length());
        Client.lIllllI[201] = ("   ".length() << (" ".length() << " ".length()) ^ (0x88 ^ 0xAB)) << (" ".length() << " ".length());
        Client.lIllllI[202] = 2 + 181 - 140 + 154;
        Client.lIllllI[203] = 56 + 176 - 151 + 108;
        Client.lIllllI[204] = ((0x54 ^ 0x21) << " ".length() ^ 164 + 49 - 212 + 180) << " ".length();
        Client.lIllllI[205] = 158 + 23 - 60 + 70;
        Client.lIllllI[206] = (0x34 ^ 0x59) + (0x7A ^ 0x53) - (88 + 101 - 92 + 36) + ((0x44 ^ 0x4F) << (" ".length() << (" ".length() << " ".length())));
        Client.lIllllI[207] = (0x24 ^ 0x45) << " ".length();
        Client.lIllllI[208] = (0x53 ^ 0x4E) + ((0x30 ^ 0x2B) << " ".length()) - -(0xC ^ 0x2F) + (0xC ^ 0x41);
        Client.lIllllI[209] = ((0x84 ^ 0x9B) << (" ".length() << " ".length()) ^ (0x23 ^ 0x3A)) << " ".length();
        Client.lIllllI[210] = ((0x1D ^ 0x18) << (" ".length() << " ".length()) ^ (0x55 ^ 0x70)) << (" ".length() << " ".length());
        Client.lIllllI[211] = ("   ".length() << "   ".length() ^ (0x58 ^ 0x23)) << " ".length();
        Client.lIllllI[212] = (0xD1 ^ 0xBE) << " ".length();
        Client.lIllllI[213] = 182 + 153 - 185 + 49;
        Client.lIllllI[214] = (0x11 ^ 0x8) << "   ".length();
        Client.lIllllI[215] = (0xBE ^ 0xB1) + ((0x7C ^ 0x59) << (" ".length() << " ".length())) - -(0x43 ^ 0x5B) + ((0xAA ^ 0xAD) << " ".length());
        Client.lIllllI[216] = 82 + 57 + 1 + 63;
        Client.lIllllI[217] = 1 + 49 - 29 + 184;
        Client.lIllllI[218] = (0x28 ^ 0x4F) << " ".length();
        Client.lIllllI[219] = 97 + 183 - 87 + 14;
        Client.lIllllI[220] = ((0x35 ^ 0x38) << " ".length() ^ (0x34 ^ 0x11)) << (" ".length() << " ".length());
        Client.lIllllI[221] = ((0xE0 ^ 0xA1) << " ".length() ^ 37 + 96 - 89 + 99) << (" ".length() << (" ".length() << " ".length()));
        Client.lIllllI[222] = 198 + 178 - 274 + 107;
        Client.lIllllI[223] = ((0x5 ^ 0x14) << (" ".length() << " ".length()) ^ (0xA8 ^ 0x85)) << " ".length();
        Client.lIllllI[224] = 80 + 178 - 65 + 18;
        Client.lIllllI[225] = 114 + 25 + 34 + 40;
        Client.lIllllI[226] = 161 + 147 - 120 + 27;
        Client.lIllllI[227] = (0xE3 ^ 0xB6 ^ " ".length() << (0xC5 ^ 0xC0)) << " ".length();
        Client.lIllllI[228] = (" ".length() ^ (0x57 ^ 0x5A) << " ".length()) << "   ".length();
        Client.lIllllI[229] = (0x53 ^ 0x6) + ((0x46 ^ 0x67) << (" ".length() << " ".length())) - (69 + 80 + 41 + 21) + (145 + 186 - 330 + 210);
        Client.lIllllI[230] = (0xE4 ^ 0x89) << " ".length();
        Client.lIllllI[231] = ((0x9B ^ 0xB6) << (" ".length() << " ".length())) + (127 + 29 - 71 + 94) - ((0xDE ^ 0x91) << (" ".length() << " ".length())) + ((0x4B ^ 0x40) << (" ".length() << (" ".length() << " ".length())));
        Client.lIllllI[232] = 224 + 72 - 126 + 77;
        Client.lIllllI[233] = (6 + 170 - 27 + 40 ^ (0xF7 ^ 0xB2) << " ".length()) << (" ".length() << " ".length());
        Client.lIllllI[234] = 47 + 209 - 207 + 172;
        Client.lIllllI[235] = ((0x10 ^ 0x1) << "   ".length()) + ((0x5C ^ 0x1B) << " ".length()) - (0xF8 ^ 0xA7) + ((0x18 ^ 0x1D) << "   ".length());
        Client.lIllllI[236] = ("   ".length() << (" ".length() << (" ".length() << " ".length()))) + ((0x33 ^ 0x7C) << " ".length()) - -(0xA9 ^ 0xA5) + (0x33 ^ 0x24);
        Client.lIllllI[237] = (0x44 ^ 0x43) << (0x8 ^ 0xD);
        Client.lIllllI[238] = (0xDA ^ 0x97) + ((0xA2 ^ 0xC7) << " ".length()) - (0x3A ^ 0x6B) + (0xF ^ 0x14);
        Client.lIllllI[239] = 161 + 124 - 73 + 17;
        Client.lIllllI[240] = (0x6A ^ 0x29 ^ "   ".length() << (" ".length() << (" ".length() << " ".length()))) << " ".length();
        Client.lIllllI[241] = 143 + 196 - 263 + 155;
        Client.lIllllI[242] = ((0x9B ^ 0xA8) << " ".length() ^ (0xE2 ^ 0x99)) << "   ".length();
        Client.lIllllI[243] = (0x77 ^ 0xC) << " ".length();
        Client.lIllllI[244] = ((0x23 ^ 0x28) << "   ".length()) + (12 + 180 - 161 + 178) - ((0xFA ^ 0xA3) << " ".length()) + ((0x11 ^ 0xC) << (" ".length() << " ".length()));
        Client.lIllllI[245] = (0x22 ^ 0x19) + ((0x2B ^ 0x22) << "   ".length()) - (0x1D ^ 0x3E) + (63 + 82 + 7 + 7);
        Client.lIllllI[246] = (140 + 199 - 335 + 247 ^ "   ".length() << ("   ".length() << " ".length())) << (" ".length() << " ".length());
        Client.lIllllI[247] = 119 + 162 - 136 + 92;
        Client.lIllllI[248] = (0x6A ^ 0x2F ^ (0x34 ^ 0x2D) << " ".length()) << " ".length();
        Client.lIllllI[249] = 204 + 89 - 168 + 114;
        Client.lIllllI[250] = ((0x31 ^ 0x58) << " ".length() ^ 74 + 55 - 6 + 48) << " ".length();
        Client.lIllllI[251] = 1 + 47 + 70 + 125;
        Client.lIllllI[252] = (0x21 ^ 0x1C) << (" ".length() << " ".length());
        Client.lIllllI[253] = 116 + 66 - 74 + 77 + (" ".length() << " ".length()) - ((0x67 ^ 0x46) << " ".length()) + ((0x33 ^ 0x2C) << (" ".length() << " ".length()));
        Client.lIllllI[254] = (" ".length() ^ (0x4B ^ 0x44) << " ".length()) << "   ".length();
        Client.lIllllI[255] = 105 + 33 + 47 + 64;
        Client.lIllllI[256] = (0x3E ^ 0x43) << " ".length();
        Client.lIllllI[257] = 55 + 61 - 37 + 54 + (15 + 84 - 79 + 215) - ((0x7D ^ 0x68) << "   ".length()) + (0xB7 ^ 0x82);
        Client.lIllllI[258] = ((0x4A ^ 0x57) << (" ".length() << " ".length())) + (" ".length() << (" ".length() << " ".length())) - (0x1 ^ 0x34) + ((0x54 ^ 0x5B) << (" ".length() << " ".length())) << " ".length();
        Client.lIllllI[259] = 94 + 56 - 111 + 218;
        Client.lIllllI[260] = (0x5C ^ 0x3D) + ((0x45 ^ 0x48) << (" ".length() << " ".length())) - ((0x49 ^ 0x5E) << " ".length()) + ((0x1E ^ 0x13) << " ".length()) << " ".length();
        Client.lIllllI[261] = 31 + 9 + 138 + 81;
        Client.lIllllI[262] = (0x57 ^ 0x4 ^ (0x62 ^ 0x6B) << " ".length()) << (" ".length() << " ".length());
        Client.lIllllI[263] = 255 + 68 - 151 + 89;
        Client.lIllllI[264] = 96 + 117 - 118 + 36 << " ".length();
        Client.lIllllI[265] = 247 + 15 - 238 + 239;
        Client.lIllllI[266] = ("   ".length() << (" ".length() << " ".length()) ^ (0x9B ^ 0xB6)) << "   ".length();
        Client.lIllllI[267] = 251 + 119 - 204 + 99;
        Client.lIllllI[268] = (0x15 ^ 0x22) + (0x6B ^ 0x1E) - (0x2B ^ 0x4C) + (" ".length() << ("   ".length() << " ".length())) << " ".length();
        Client.lIllllI[269] = ((0x18 ^ 0x17) << (" ".length() << (" ".length() << " ".length()))) + ((0xED ^ 0x90) << " ".length()) - (200 + 76 + 38 + 47) + ((0xF ^ 0x4A) << " ".length());
        Client.lIllllI[270] = (0x34 ^ 0x77) << (" ".length() << " ".length());
        Client.lIllllI[271] = 139 + 165 - 257 + 222;
        Client.lIllllI[272] = 59 + 0 - 53 + 129 << " ".length();
        Client.lIllllI[273] = 71 + 105 - 71 + 166;
        Client.lIllllI[274] = (0xC ^ 0x1D) << (" ".length() << (" ".length() << " ".length()));
        Client.lIllllI[275] = 218 + 236 - 400 + 219;
        Client.lIllllI[276] = 111 + 135 - 155 + 46 << " ".length();
        Client.lIllllI[277] = 230 + 187 - 191 + 49;
        Client.lIllllI[278] = (0x6A ^ 0x2F) << (" ".length() << " ".length());
        Client.lIllllI[279] = ((0xAA ^ 0xB5) << "   ".length()) + ((0x57 ^ 0x2) << " ".length()) - (245 + 227 - 457 + 232) + ((0x48 ^ 0x7D) << " ".length());
        Client.lIllllI[280] = 105 + 31 - 71 + 74 << " ".length();
        Client.lIllllI[281] = 206 + 73 - 40 + 40;
        Client.lIllllI[282] = (0x82 ^ 0xA1) << "   ".length();
        Client.lIllllI[283] = (" ".length() << "   ".length()) + (79 + 100 - 32 + 20) - (0x5E ^ 0x17) + (52 + 47 + 80 + 0);
        Client.lIllllI[284] = (0x9A ^ 0xAF) + ((0x76 ^ 0x4F) << " ".length()) - ((0x78 ^ 0x2B) << " ".length()) + ((0xE0 ^ 0xC3) << (" ".length() << " ".length())) << " ".length();
        Client.lIllllI[285] = 214 + 252 - 412 + 229;
        Client.lIllllI[286] = (0x80 ^ 0xC7) << (" ".length() << " ".length());
        Client.lIllllI[287] = ((0x4E ^ 0x4B) << (0xC6 ^ 0xC3)) + ((0xAC ^ 0xBB) << " ".length()) - (66 + 135 - 79 + 21) + ((0xF8 ^ 0x97) << " ".length());
        Client.lIllllI[288] = (0x5C ^ 0x1B) + (0x7E ^ 0x5B) - ((0x66 ^ 0x71) << (" ".length() << " ".length())) + (64 + 57 - 27 + 33) << " ".length();
        Client.lIllllI[289] = (0xA ^ 0x1B) + (124 + 163 - 198 + 120) - (143 + 41 - 119 + 112) + ((0xFF ^ 0x88) << " ".length());
        Client.lIllllI[290] = (0x9F ^ 0x98 ^ (0x71 ^ 0x76) << " ".length()) << (114 + 60 - 167 + 128 ^ (0xE4 ^ 0xA5) << " ".length());
        Client.lIllllI[291] = 31 + 56 - 47 + 249;
        Client.lIllllI[292] = (0x6 ^ 0x71) + (0xC0 ^ 0x97) - (102 + 130 - 174 + 105) + ((0x68 ^ 0x5B) << " ".length()) << " ".length();
        Client.lIllllI[293] = 290 + 204 - 414 + 211;
        Client.lIllllI[294] = (0xDD ^ 0x94) << (" ".length() << " ".length());
        Client.lIllllI[295] = ((0x0 ^ 0x25) << (" ".length() << " ".length())) + (208 + 107 - 210 + 114) - (34 + 5 + 151 + 23) + (119 + 0 - 106 + 126);
        Client.lIllllI[296] = (0x91 ^ 0x9A) + (0x3C ^ 0x5F) - ((0x2C ^ 0xD) << " ".length()) + (0x1F ^ 0x78) << " ".length();
        Client.lIllllI[297] = 54 + 144 + 56 + 41;
        Client.lIllllI[298] = (0x32 ^ 0x17) << "   ".length();
        Client.lIllllI[299] = 289 + 268 - 414 + 154;
        Client.lIllllI[300] = 66 + 91 - 31 + 23 << " ".length();
        Client.lIllllI[301] = ((0x4B ^ 0x22) << " ".length()) + (" ".length() << "   ".length()) - ((0x28 ^ 0x7D) << " ".length()) + (87 + 230 - 211 + 145);
        Client.lIllllI[302] = (64 + 70 - 40 + 33 << " ".length() ^ 124 + 55 - 8 + 10) << (" ".length() << " ".length());
        Client.lIllllI[303] = ((0xA3 ^ 0xBC) << (" ".length() << " ".length())) + ((0x68 ^ 0x67) << "   ".length()) - (" ".length() << "   ".length()) + (0xC7 ^ 0x86);
        Client.lIllllI[304] = (0x6F ^ 0x44) + ((0x2A ^ 0x9) << " ".length()) - ((0x3B ^ 0x30) << (" ".length() << " ".length())) + ((0x28 ^ 0x1) << " ".length()) << " ".length();
        Client.lIllllI[305] = ((0x52 ^ 0x71) << " ".length()) + ((0xB4 ^ 0x93) << (" ".length() << " ".length())) - (17 + 77 + 64 + 57) + ((0x59 ^ 0x10) << (" ".length() << " ".length()));
        Client.lIllllI[306] = (("   ".length() << "   ".length() & ~("   ".length() << "   ".length())) ^ (0x33 ^ 0x20)) << (" ".length() << (" ".length() << " ".length()));
        Client.lIllllI[307] = ((0x74 ^ 0x47) << (" ".length() << " ".length())) + ((0xF7 ^ 0xB0) << (" ".length() << " ".length())) - (86 + 293 - 127 + 61) + ((0xE6 ^ 0xA7) << " ".length());
        Client.lIllllI[308] = 30 + 27 + 60 + 36 << " ".length();
        Client.lIllllI[309] = 170 + 127 - 257 + 267;
        Client.lIllllI[310] = (0x31 ^ 0x7C) << (" ".length() << " ".length());
        Client.lIllllI[311] = 103 + 43 + 88 + 75;
        Client.lIllllI[312] = (0x7D ^ 0x4A) + ((0x1D ^ 0xA) << (" ".length() << " ".length())) - (" ".length() << " ".length()) + ((0x8B ^ 0x8E) << " ".length()) << " ".length();
        Client.lIllllI[313] = 220 + 87 - 150 + 154;
        Client.lIllllI[314] = (28 + 75 - 82 + 118 ^ (0x4 ^ 0x2F) << (" ".length() << " ".length())) << "   ".length();
        Client.lIllllI[315] = 76 + 214 - 223 + 182 + ((0x14 ^ 0xB) << " ".length()) - (0x3 ^ 0x3C) + (0x32 ^ 0x73);
        Client.lIllllI[316] = (0x1 ^ 0x48) + ((0xB0 ^ 0x93) << (" ".length() << " ".length())) - (0x6F ^ 0x8) + (0xAD ^ 0x82) << " ".length();
        Client.lIllllI[317] = 120 + 252 - 362 + 305;
        Client.lIllllI[318] = (0x3A ^ 0x5D ^ (0xD ^ 0x8) << "   ".length()) << (" ".length() << " ".length());
        Client.lIllllI[319] = ((0xAA ^ 0xA1) << (" ".length() << (" ".length() << " ".length()))) + (0xB ^ 0x48) - -(0x63 ^ 0x50) + (0xB0 ^ 0xA7);
        Client.lIllllI[320] = 60 + 156 - 119 + 62 << " ".length();
        Client.lIllllI[321] = 34 + 199 - 225 + 311;
        Client.lIllllI[322] = (0xE ^ 0xB) << ("   ".length() << " ".length());
        Client.lIllllI[323] = 202 + 42 - 190 + 193 + (0x7F ^ 0x3C) - ((0xF ^ 0x1E) << (" ".length() << (" ".length() << " ".length()))) + (215 + 273 - 323 + 114);
        Client.lIllllI[324] = 106 + 2 - 45 + 84 + ((0xCD ^ 0xC6) << (" ".length() << " ".length())) - (0xDB ^ 0x8A) + (0x87 ^ 0xB4) << " ".length();
        Client.lIllllI[325] = 100 + 21 + 107 + 95;
        Client.lIllllI[326] = ((0xC3 ^ 0xC4) << "   ".length() ^ (0xF2 ^ 0x9B)) << (" ".length() << " ".length());
        Client.lIllllI[327] = 238 + 1 - 204 + 284 + (73 + 92 + 72 + 82) - (82 + 66 - 88 + 379) + ((0x34 ^ 0xB) << " ".length());
        Client.lIllllI[328] = 141 + 131 - 164 + 55 << " ".length();
        Client.lIllllI[329] = 18 + 174 + 27 + 108;
        Client.lIllllI[330] = (0x7E ^ 0x57) << "   ".length();
        Client.lIllllI[331] = 118 + 241 - 293 + 263;
        Client.lIllllI[332] = 159 + 153 - 259 + 112 << " ".length();
        Client.lIllllI[333] = ((0x8F ^ 0x9C) << " ".length()) + ((0x79 ^ 0x6E) << (" ".length() << " ".length())) - -(0x13 ^ 0x5D) + (0xB ^ 0x70);
        Client.lIllllI[334] = ((0x19 ^ 0x10) << " ".length() ^ (0x3D ^ 0x7C)) << (" ".length() << " ".length());
        Client.lIllllI[335] = 143 + 78 - 206 + 162 + ((0x3C ^ 0x6D) << (" ".length() << " ".length())) - (85 + 94 + 1 + 121) + (10 + 114 - 44 + 53);
        Client.lIllllI[336] = (0x86 ^ 0xB7) + ((0x4E ^ 0x6D) << (" ".length() << " ".length())) - ((0x76 ^ 0x61) << "   ".length()) + ((0xC0 ^ 0x91) << " ".length()) << " ".length();
        Client.lIllllI[337] = 17 + 237 - 36 + 117;
        Client.lIllllI[338] = (0x59 ^ 0x4C) << (" ".length() << (" ".length() << " ".length()));
        Client.lIllllI[339] = (0xEE ^ 0x9F) + (0x28 ^ 0x53) - (0x3A ^ 0x3) + ((0x8A ^ 0xC5) << " ".length());
        Client.lIllllI[340] = ((0x82 ^ 0xC5) << " ".length()) + (0xDF ^ 0xAE) - (163 + 213 - 230 + 97) + (96 + 122 - 62 + 1) << " ".length();
        Client.lIllllI[341] = 73 + 187 - 36 + 115;
        Client.lIllllI[342] = (0x27 ^ 0x72) << (" ".length() << " ".length());
        Client.lIllllI[343] = ((0x3B ^ 0x76) << " ".length()) + (0xA9 ^ 0xB2) - -(127 + 107 - 197 + 121) + (" ".length() << " ".length());
        Client.lIllllI[344] = (0x24 ^ 0x31) + ((0x43 ^ 0xA) << " ".length()) - ((0x46 ^ 0x4D) << " ".length()) + ((0x88 ^ 0x85) << " ".length()) << " ".length();
        Client.lIllllI[345] = 113 + 74 + 100 + 52 + (10 + 16 + 21 + 212) - (140 + 0 - 20 + 33 << " ".length()) + (0x33 ^ 0x0);
        Client.lIllllI[346] = (0xA1 ^ 0x8A) << "   ".length();
        Client.lIllllI[347] = ((0x9A ^ 0xB9) << " ".length()) + (" ".length() << (0xAF ^ 0xA8)) - -(0x8F ^ 0xB9) + (0xEC ^ 0xB1);
        Client.lIllllI[348] = 92 + 44 - 12 + 7 + (0x58 ^ 0x63) - (0xE3 ^ 0xAE) + ((0x7B ^ 0x74) << (" ".length() << " ".length())) << " ".length();
        Client.lIllllI[349] = 246 + 11 - 36 + 126;
        Client.lIllllI[350] = (0x2D ^ 0x7A) << (" ".length() << " ".length());
        Client.lIllllI[351] = 121 + 207 - 116 + 137;
        Client.lIllllI[352] = (0x2A ^ 0x49) + ((0xE ^ 0x3D) << " ".length()) - ((0x8E ^ 0xBF) << " ".length()) + ((0xB7 ^ 0xBE) << "   ".length()) << " ".length();
        Client.lIllllI[353] = 103 + 56 - 39 + 231;
        Client.lIllllI[354] = (0xBB ^ 0xB0) << (0x8B ^ 0x8E);
        Client.lIllllI[355] = (" ".length() << (" ".length() << " ".length())) + ((0x73 ^ 0x26) << " ".length()) - ((0xAB ^ 0xA6) << (" ".length() << " ".length())) + (28 + 227 - 65 + 41);
        Client.lIllllI[356] = (0x76 ^ 0x33) + ("   ".length() << (0x5B ^ 0x5E)) - ((0x1C ^ 0x11) << "   ".length()) + ((0x98 ^ 0x85) << (" ".length() << " ".length())) << " ".length();
        Client.lIllllI[357] = 314 + 268 - 529 + 286 + (48 + 88 + 46 + 65) - (196 + 101 - 160 + 96) + (" ".length() << " ".length());
        Client.lIllllI[358] = (0x12 ^ 0x4B) << (" ".length() << " ".length());
        Client.lIllllI[359] = 241 + 42 - 160 + 234;
        Client.lIllllI[360] = 162 + 145 - 303 + 175 << " ".length();
        Client.lIllllI[361] = 86 + 48 + 135 + 22 + (167 + 22 - 147 + 135) - (52 + 219 - 27 + 121) + (" ".length() << (" ".length() << "   ".length()));
        Client.lIllllI[362] = (0x65 ^ 0x48) << "   ".length();
        Client.lIllllI[363] = ((0x3D ^ 0x8) << " ".length()) + (110 + 34 - 63 + 56) - -(0x4E ^ 0x21) + (0x6A ^ 0x6D);
        Client.lIllllI[364] = 18 + 7 + 21 + 135 << " ".length();
        Client.lIllllI[365] = ((0x4F ^ 0x1A) << (" ".length() << " ".length())) + (139 + 157 - 207 + 70 << " ".length()) - ((0x4 ^ 0x47) << "   ".length()) + (69 + 141 - 83 + 114);
        Client.lIllllI[366] = (0x19 ^ 0x52 ^ " ".length() << (" ".length() << (" ".length() << " ".length()))) << (" ".length() << " ".length());
        Client.lIllllI[367] = 148 + 197 - 134 + 56 + (0x39 ^ 0x4) - (0x36 ^ 0x19) + ((0x1C ^ 0x9) << (" ".length() << " ".length()));
        Client.lIllllI[368] = ((0xE9 ^ 0xB8) << " ".length()) + ((0x19 ^ 0x28) << " ".length()) - ((0xE0 ^ 0x97) << " ".length()) + (94 + 137 - 191 + 121) << " ".length();
        Client.lIllllI[369] = ((0x6E ^ 0x5B) << (" ".length() << " ".length())) + ("   ".length() << (0x1C ^ 0x19)) - (21 + 136 + 96 + 0) + ((0x7D ^ 0x5A) << "   ".length());
        Client.lIllllI[370] = ((0x1F ^ 0x0) << " ".length() ^ (0x96 ^ 0xBF)) << (" ".length() << (" ".length() << " ".length()));
        Client.lIllllI[371] = (145 + 81 - 116 + 45 << " ".length()) + ((0x21 ^ 0x54) << " ".length()) - ((0x1A ^ 0x75) << (" ".length() << " ".length())) + (212 + 172 - 247 + 132);
        Client.lIllllI[372] = 23 + 46 + 84 + 32 << " ".length();
        Client.lIllllI[373] = 113 + 59 - 27 + 226;
        Client.lIllllI[374] = (0x57 ^ 0xA) << (" ".length() << " ".length());
        Client.lIllllI[375] = 63 + 336 - 101 + 75;
        Client.lIllllI[376] = ((0x6F ^ 0x70) << " ".length()) + (144 + 67 - 193 + 133) - ((0xF5 ^ 0xAA) << " ".length()) + ((0x4D ^ 0x64) << (" ".length() << " ".length())) << " ".length();
        Client.lIllllI[377] = 293 + 239 - 337 + 180;
        Client.lIllllI[378] = (0x68 ^ 0x47) << "   ".length();
        Client.lIllllI[379] = 85 + 1 + 6 + 95 + (0x1 ^ 0x54) - -(0xCB ^ 0x85) + (0x54 ^ 0x4F);
        Client.lIllllI[380] = 17 + 151 - 15 + 36 << " ".length();
        Client.lIllllI[381] = ((0xC8 ^ 0xBF) << " ".length()) + (49 + 55 + 64 + 3) - ((0x51 ^ 0x60) << " ".length()) + ((0x16 ^ 0x7) << (" ".length() << " ".length()));
        Client.lIllllI[382] = (31 + 121 - 151 + 240 ^ (0xFD ^ 0xAA) << " ".length()) << (" ".length() << " ".length());
        Client.lIllllI[383] = 190 + 108 - 6 + 89;
        Client.lIllllI[384] = 36 + 39 + 38 + 28 + (70 + 22 - 73 + 128) - ((0x22 ^ 0x1) << (" ".length() << " ".length())) + (0x50 ^ 0x7B) << " ".length();
        Client.lIllllI[385] = 274 + 70 - 9 + 48;
        Client.lIllllI[386] = "   ".length() << (" ".length() << (" ".length() << " ".length()) ^ "   ".length());
        Client.lIllllI[387] = (0xFA ^ 0x95) + (176 + 195 - 103 + 11) - (59 + 27 + 70 + 31) + ((0xE2 ^ 0xB9) << " ".length());
        Client.lIllllI[388] = ((0x4D ^ 0x70) << " ".length()) + ((0x89 ^ 0x86) << "   ".length()) - ((0xAF ^ 0x8A) << (" ".length() << " ".length())) + (0x35 ^ 0x56) << " ".length();
        Client.lIllllI[389] = ((0x83 ^ 0x90) << (" ".length() << (" ".length() << " ".length()))) + (92 + 69 - 2 + 142) - (63 + 85 - 133 + 112 << (" ".length() << " ".length())) + (89 + 66 - 30 + 20 << " ".length());
        Client.lIllllI[390] = (0x61 ^ 0x0) << (" ".length() << " ".length());
        Client.lIllllI[391] = 34 + 15 - 22 + 362;
        Client.lIllllI[392] = 73 + 86 - 147 + 183 << " ".length();
        Client.lIllllI[393] = 313 + 385 - 513 + 206;
        Client.lIllllI[394] = (0x7A ^ 0x4B) << "   ".length();
        Client.lIllllI[395] = 247 + 22 - 145 + 269;
        Client.lIllllI[396] = 149 + 153 - 141 + 36 << " ".length();
        Client.lIllllI[397] = 54 + 170 - 212 + 219 + (6 + 60 - 33 + 172) - ((0xA1 ^ 0x8C) << (" ".length() << " ".length())) + (68 + 123 - 144 + 92);
        Client.lIllllI[398] = (0xE0 ^ 0x83) << (" ".length() << " ".length());
        Client.lIllllI[399] = 51 + 190 - 226 + 382;
        Client.lIllllI[400] = ((0xDA ^ 0x97) << " ".length()) + ((0xD6 ^ 0x83) << " ".length()) - ((0x1F ^ 0x56) << (" ".length() << " ".length())) + (128 + 140 - 190 + 89) << " ".length();
        Client.lIllllI[401] = 66 + 339 - 401 + 395;
        Client.lIllllI[402] = (" ".length() ^ "   ".length() << "   ".length()) << (" ".length() << (" ".length() << " ".length()));
        Client.lIllllI[403] = 230 + 311 - 531 + 391;
        Client.lIllllI[404] = 28 + 151 - 73 + 95 << " ".length();
        Client.lIllllI[405] = 112 + 388 - 477 + 380;
        Client.lIllllI[406] = ((0x48 ^ 0x51) << " ".length() ^ (0xE4 ^ 0xB3)) << (" ".length() << " ".length());
        Client.lIllllI[407] = 262 + 145 - 303 + 301;
        Client.lIllllI[408] = ((0xAC ^ 0xA5) << "   ".length()) + ((0x4D ^ 0x66) << " ".length()) - (0x1D ^ 0x76) + ((0x2A ^ 0x39) << "   ".length()) << " ".length();
        Client.lIllllI[409] = ((0xB5 ^ 0xC0) << " ".length()) + ((0xDC ^ 0xC1) << " ".length()) - ((0x5D ^ 0x60) << (" ".length() << " ".length())) + (189 + 233 - 69 + 6);
        Client.lIllllI[410] = (0x3A ^ 0x9) << "   ".length();
        Client.lIllllI[411] = 274 + 320 - 375 + 190;
        Client.lIllllI[412] = 25 + 191 - 62 + 51 << " ".length();
        Client.lIllllI[413] = 369 + 377 - 539 + 204;
        Client.lIllllI[414] = (0xE3 ^ 0x84) << (" ".length() << " ".length());
        Client.lIllllI[415] = 68 + 306 - 59 + 56 + ("   ".length() << " ".length()) - ("   ".length() << "   ".length()) + ((0x69 ^ 0x66) << (" ".length() << " ".length()));
        Client.lIllllI[416] = 166 + 22 - 51 + 70 << " ".length();
        Client.lIllllI[417] = 337 + 61 - 147 + 164;
        Client.lIllllI[418] = (0x44 ^ 0x49) << (0x0 ^ 0x5);
    }
    
    private void readBinds() {
        // invokedynamic(13:(Lorg/apache/logging/log4j/Logger;Ljava/lang/String;)V, invokedynamic(12:(Lxyz/Melody/Client;)Lorg/apache/logging/log4j/Logger;, this), Client.lIlIllI[Client.lIllllI[112]])
        final List<String> lllIIllIIllIIIl = invokedynamic(203:(Ljava/lang/String;)Ljava/util/List;, Client.lIlIllI[Client.lIllllI[113]]);
        final boolean lllIIllIIlIlllI = invokedynamic(120:(Ljava/util/List;)Ljava/util/Iterator;, lllIIllIIllIIIl);
        while (llllllIl(invokedynamic(121:(Ljava/util/Iterator;)Z, lllIIllIIlIlllI))) {
            final String lllIIllIIllIIll = (String)invokedynamic(122:(Ljava/util/Iterator;)Ljava/lang/Object;, lllIIllIIlIlllI);
            final String lllIIllIIllIllI = invokedynamic(224:(Ljava/lang/String;Ljava/lang/String;)[Ljava/lang/String;, lllIIllIIllIIll, Client.lIlIllI[Client.lIllllI[114]])[Client.lIllllI[0]];
            final String lllIIllIIllIlIl = invokedynamic(224:(Ljava/lang/String;Ljava/lang/String;)[Ljava/lang/String;, lllIIllIIllIIll, Client.lIlIllI[Client.lIllllI[115]])[Client.lIllllI[2]];
            final Module lllIIllIIllIlII = invokedynamic(225:(Ljava/lang/String;)Lxyz/Melody/module/Module;, lllIIllIIllIllI);
            if (lIIIIIlIl(lllIIllIIllIlII)) {
                "".length();
                if ("   ".length() == 0) {
                    return;
                }
                continue;
            }
            else {
                // invokedynamic(74:(Lxyz/Melody/module/Module;I)V, lllIIllIIllIlII, invokedynamic(227:(Ljava/lang/String;)I, invokedynamic(226:(Ljava/lang/String;)Ljava/lang/String;, lllIIllIIllIlIl)))
                // invokedynamic(13:(Lorg/apache/logging/log4j/Logger;Ljava/lang/String;)V, invokedynamic(12:(Lxyz/Melody/Client;)Lorg/apache/logging/log4j/Logger;, this), invokedynamic(17:(Ljava/lang/StringBuilder;)Ljava/lang/String;, invokedynamic(76:(Ljava/lang/StringBuilder;I)Ljava/lang/StringBuilder;, invokedynamic(14:(Ljava/lang/StringBuilder;Ljava/lang/String;)Ljava/lang/StringBuilder;, invokedynamic(14:(Ljava/lang/StringBuilder;Ljava/lang/String;)Ljava/lang/StringBuilder;, invokedynamic(14:(Ljava/lang/StringBuilder;Ljava/lang/String;)Ljava/lang/StringBuilder;, new StringBuilder(), Client.lIlIllI[Client.lIllllI[116]]), invokedynamic(228:(Lxyz/Melody/module/Module;)Ljava/lang/String;, lllIIllIIllIlII)), Client.lIlIllI[Client.lIllllI[117]]), invokedynamic(227:(Ljava/lang/String;)I, invokedynamic(226:(Ljava/lang/String;)Ljava/lang/String;, lllIIllIIllIlIl)))))
                "".length();
                if (-" ".length() > " ".length() << (" ".length() << " ".length())) {
                    return;
                }
                continue;
            }
        }
    }
    // invokedynamic(13:(Lorg/apache/logging/log4j/Logger;Ljava/lang/String;)V, invokedynamic(12:(Lxyz/Melody/Client;)Lorg/apache/logging/log4j/Logger;, this), Client.lIlIllI[Client.lIllllI[118]])
    
    private static boolean lllllllI(final int lllIIlIIllIlIII) {
        return lllIIlIIllIlIII == 0;
    }
    
    public void saveCustomName() {
        "".length();
        String s;
        if (lIIIIIlIl(invokedynamic(209:()Ljava/lang/String;))) {
            s = Client.lIlIllI[Client.lIllllI[83]];
            "".length();
            if (((0x67 ^ 0x6A) & ~(0x60 ^ 0x6D)) != 0x0) {
                return;
            }
        }
        else {
            "".length();
            s = invokedynamic(209:()Ljava/lang/String;);
        }
        final String lllIIlllIIIIIII = s;
    }
    // invokedynamic(207:(Ljava/lang/String;Ljava/lang/String;Z)V, Client.lIlIllI[Client.lIllllI[84]], lllIIlllIIIIIII, Client.lIllllI[0])
    
    private static boolean lIIIIIlIl(final Object lllIIlIIllIllII) {
        return lllIIlIIllIllII == null;
    }
    
    public void saveCustomRank() {
        "".length();
        String s;
        if (lIIIIIlIl(invokedynamic(151:()Ljava/lang/String;))) {
            s = Client.lIlIllI[Client.lIllllI[87]];
            "".length();
            if (" ".length() == 0) {
                return;
            }
        }
        else {
            "".length();
            s = invokedynamic(151:()Ljava/lang/String;);
        }
        final String lllIIllIllIllll = s;
    }
    // invokedynamic(207:(Ljava/lang/String;Ljava/lang/String;Z)V, Client.lIlIllI[Client.lIllllI[88]], lllIIllIllIllll, Client.lIllllI[0])
    
    public static void regrabMouse() {
        if (lllllllI(invokedynamic(192:()Z))) {
            return;
        }
        invokedynamic(19:()Lnet/minecraft/client/Minecraft;).mouseHelper = invokedynamic(193:()Lnet/minecraft/util/MouseHelper;);
        if (lllllllI(invokedynamic(201:()Z))) {
        }
        // invokedynamic(202:(Lnet/minecraft/util/MouseHelper;)V, invokedynamic(194:(Lnet/minecraft/client/Minecraft;)Lnet/minecraft/util/MouseHelper;, invokedynamic(19:()Lnet/minecraft/client/Minecraft;)))
    }
    // invokedynamic(195:(Lnet/minecraft/util/MouseHelper;)V, null)
    // invokedynamic(200:(Z)V, Client.lIllllI[0])
    
    @EventHandler
    private void nmsl(final EventTick lllIlIIIIIIllIl) {
        if (lIIIIIIII(invokedynamic(115:(Lnet/minecraft/client/Minecraft;)Lnet/minecraft/client/entity/EntityPlayerSP;, invokedynamic(19:()Lnet/minecraft/client/Minecraft;))) && lIIIIIIII(invokedynamic(116:(Lnet/minecraft/client/Minecraft;)Lnet/minecraft/client/multiplayer/WorldClient;, invokedynamic(19:()Lnet/minecraft/client/Minecraft;)))) {
        }
        // invokedynamic(118:(Lxyz/Melody/Client;F)V, this, invokedynamic(117:(Lxyz/Melody/Client;)F, this))
        if (llllllIl(invokedynamic(35:(Lxyz/Melody/System/Melody/Authentication/AuthManager;)Z, invokedynamic(25:(Lxyz/Melody/Client;)Lxyz/Melody/System/Melody/Authentication/AuthManager;, invokedynamic(65:()Lxyz/Melody/Client;))))) {
            return;
        }
        // invokedynamic(57:(Lxyz/Melody/Client;)Lxyz/Melody/System/Managers/Client/ModuleManager;, this)
        "".length();
        final float lllIlIIIIIIlIll = invokedynamic(120:(Ljava/util/List;)Ljava/util/Iterator;, invokedynamic(119:()Ljava/util/List;));
        while (llllllIl(invokedynamic(121:(Ljava/util/Iterator;)Z, lllIlIIIIIIlIll))) {
            final Module lllIlIIIIIIllll = (Module)invokedynamic(122:(Ljava/util/Iterator;)Ljava/lang/Object;, lllIlIIIIIIlIll);
            if (lIIIIIIIl(invokedynamic(123:(Lxyz/Melody/module/Module;)Lxyz/Melody/module/ModuleType;, lllIlIIIIIIllll), invokedynamic(124:()Lxyz/Melody/module/ModuleType;)) && lllllllI((lllIlIIIIIIllll instanceof Sprint) ? 1 : 0)) {
                if (llllllIl((lllIlIIIIIIllll instanceof Nametags) ? 1 : 0)) {
                    "".length();
                    if (" ".length() << (" ".length() << " ".length()) <= "   ".length()) {
                        return;
                    }
                    continue;
                }
                else {
                    if (lllllllI((lllIlIIIIIIllll instanceof ClickGui) ? 1 : 0) && lllllllI((lllIlIIIIIIllll instanceof ClientCommands) ? 1 : 0) && lllllllI((lllIlIIIIIIllll instanceof HUD) ? 1 : 0) && lllllllI((lllIlIIIIIIllll instanceof OldAnimations) ? 1 : 0) && lllllllI((lllIlIIIIIIllll instanceof GhostBlock) ? 1 : 0) && lllllllI((lllIlIIIIIIllll instanceof AutoGG) ? 1 : 0) && lllllllI((lllIlIIIIIIllll instanceof Cam) ? 1 : 0) && llllllIl(invokedynamic(125:(Lxyz/Melody/module/Module;)Z, lllIlIIIIIIllll))) {
                        if (lIIIIIIII(invokedynamic(116:(Lnet/minecraft/client/Minecraft;)Lnet/minecraft/client/multiplayer/WorldClient;, invokedynamic(19:()Lnet/minecraft/client/Minecraft;))) && lIIIIIIII(invokedynamic(115:(Lnet/minecraft/client/Minecraft;)Lnet/minecraft/client/entity/EntityPlayerSP;, invokedynamic(19:()Lnet/minecraft/client/Minecraft;)))) {
                        }
                        // invokedynamic(126:(Ljava/lang/Object;)V, Client.lIlIllI[Client.lIllllI[39]])
                    }
                    // invokedynamic(127:(Lxyz/Melody/module/Module;Z)V, lllIlIIIIIIllll, Client.lIllllI[0])
                    "".length();
                    if (" ".length() << (" ".length() << " ".length()) <= "   ".length()) {
                        return;
                    }
                    continue;
                }
            }
        }
    }
    
    private void superAss() {
        // invokedynamic(6:(Lxyz/Melody/Client;Z)V, this, Client.lIllllI[2])
        if (llllllIl(invokedynamic(79:(Ljava/lang/String;Ljava/lang/Object;)Z, invokedynamic(30:(Lnet/minecraft/util/Session;)Ljava/lang/String;, invokedynamic(20:(Lnet/minecraft/client/Minecraft;)Lnet/minecraft/util/Session;, invokedynamic(19:()Lnet/minecraft/client/Minecraft;))), Client.lIlIllI[Client.lIllllI[30]]))) {
            // invokedynamic(80:(Lxyz/Melody/System/Melody/Authentication/AuthManager;Z)V, invokedynamic(25:(Lxyz/Melody/Client;)Lxyz/Melody/System/Melody/Authentication/AuthManager;, this), Client.lIllllI[2])
            // invokedynamic(6:(Lxyz/Melody/Client;Z)V, this, Client.lIllllI[0])
            return;
        }
        boolean lllIlIIIIllIIII = Client.lIllllI[0] != 0;
        boolean lllIlIIIIlIllll = Client.lIllllI[0] != 0;
        try {
            // invokedynamic(81:()V)
            while (llllllIl(invokedynamic(83:(Ljava/lang/Thread;)Z, invokedynamic(82:()Ljava/lang/Thread;)))) {
                // invokedynamic(84:(J)V, 10L)
                "".length();
                if (null != null) {
                    return;
                }
            }
            lllIlIIIIllIIII = invokedynamic(35:(Lxyz/Melody/System/Melody/Authentication/AuthManager;)Z, invokedynamic(25:(Lxyz/Melody/Client;)Lxyz/Melody/System/Melody/Authentication/AuthManager;, this));
            "".length();
            if (((0x32 ^ 0x15) << " ".length() & ~((0x9 ^ 0x2E) << " ".length())) != 0x0) {
                return;
            }
        }
        catch (Exception lllIlIIIIllIllI) {
            final Throwable lllIlIIIIlllIII = new Throwable(invokedynamic(85:(Ljava/lang/Exception;)Ljava/lang/String;, lllIlIIIIllIllI));
            final StackTraceElement[] lllIlIIIIllIlll = new StackTraceElement[Client.lIllllI[0]];
        }
        // invokedynamic(77:(Ljava/lang/Throwable;[Ljava/lang/StackTraceElement;)V, lllIlIIIIlllIII, lllIlIIIIllIlll)
        // invokedynamic(86:(Ljava/lang/Throwable;)V, lllIlIIIIlllIII)
        // invokedynamic(13:(Lorg/apache/logging/log4j/Logger;Ljava/lang/String;)V, invokedynamic(12:(Lxyz/Melody/Client;)Lorg/apache/logging/log4j/Logger;, invokedynamic(65:()Lxyz/Melody/Client;)), invokedynamic(17:(Ljava/lang/StringBuilder;)Ljava/lang/String;, invokedynamic(36:(Ljava/lang/StringBuilder;Z)Ljava/lang/StringBuilder;, invokedynamic(14:(Ljava/lang/StringBuilder;Ljava/lang/String;)Ljava/lang/StringBuilder;, new StringBuilder(), Client.lIlIllI[Client.lIllllI[31]]), lllIlIIIIllIIII)))
        if (lllllllI(lllIlIIIIllIIII ? 1 : 0)) {
            // invokedynamic(87:(Lxyz/Melody/Client;Ljava/lang/String;)V, this, Client.lIlIllI[Client.lIllllI[32]])
            try {
                final String lllIlIIIIllIlIl = invokedynamic(88:(Lxyz/Melody/System/Melody/Authentication/AuthManager;)Ljava/lang/String;, invokedynamic(25:(Lxyz/Melody/Client;)Lxyz/Melody/System/Melody/Authentication/AuthManager;, this));
                if (llllllIl(invokedynamic(91:(Ljava/lang/String;Ljava/lang/CharSequence;)Z, lllIlIIIIllIlIl, invokedynamic(90:(Lxyz/Melody/System/Melody/Authentication/UserObj;)Ljava/lang/String;, invokedynamic(89:(Lxyz/Melody/System/Melody/Authentication/AuthManager;)Lxyz/Melody/System/Melody/Authentication/UserObj;, invokedynamic(25:(Lxyz/Melody/Client;)Lxyz/Melody/System/Melody/Authentication/AuthManager;, this)))))) {
                    lllIlIIIIlIllll = (Client.lIllllI[2] != 0);
                }
                "".length();
                if (null != null) {
                    return;
                }
            }
            catch (Exception lllIlIIIIllIIlI) {
                final Throwable lllIlIIIIllIlII = new Throwable(invokedynamic(85:(Ljava/lang/Exception;)Ljava/lang/String;, lllIlIIIIllIIlI));
                final StackTraceElement[] lllIlIIIIllIIll = new StackTraceElement[Client.lIllllI[0]];
            }
            // invokedynamic(77:(Ljava/lang/Throwable;[Ljava/lang/StackTraceElement;)V, lllIlIIIIllIlII, lllIlIIIIllIIll)
            // invokedynamic(86:(Ljava/lang/Throwable;)V, lllIlIIIIllIlII)
        }
        // invokedynamic(13:(Lorg/apache/logging/log4j/Logger;Ljava/lang/String;)V, invokedynamic(12:(Lxyz/Melody/Client;)Lorg/apache/logging/log4j/Logger;, invokedynamic(65:()Lxyz/Melody/Client;)), invokedynamic(17:(Ljava/lang/StringBuilder;)Ljava/lang/String;, invokedynamic(36:(Ljava/lang/StringBuilder;Z)Ljava/lang/StringBuilder;, invokedynamic(14:(Ljava/lang/StringBuilder;Ljava/lang/String;)Ljava/lang/StringBuilder;, new StringBuilder(), Client.lIlIllI[Client.lIllllI[33]]), lllIlIIIIlIllll)))
        if (!lllllllI(lllIlIIIIllIIII ? 1 : 0) || llllllIl(lllIlIIIIlIllll ? 1 : 0)) {
        }
        // invokedynamic(80:(Lxyz/Melody/System/Melody/Authentication/AuthManager;Z)V, invokedynamic(25:(Lxyz/Melody/Client;)Lxyz/Melody/System/Melody/Authentication/AuthManager;, this), Client.lIllllI[2])
        // invokedynamic(6:(Lxyz/Melody/Client;Z)V, this, Client.lIllllI[0])
    }
    // invokedynamic(6:(Lxyz/Melody/Client;Z)V, this, Client.lIllllI[0])
}
