//Deobfuscated with https://github.com/SimplyProgrammer/Minecraft-Deobfuscator3000 using mappings "C:\Users\32302\Desktop\新建文件夹 (2)"!

//Decompiled by Procyon!

package chrriis.dj.nativeswing;

import java.awt.*;

class lIIllI extends Thread
{
    final /* synthetic */ Dialog val$d;
    final /* synthetic */ NativeSwing.NIAWTEventListener this$0;
    
    lIIllI(final NativeSwing.NIAWTEventListener this$0, final String x0, final Dialog val$d) {
        this.this$0 = this$0;
        this.val$d = val$d;
        super(x0);
    }
    
    @Override
    public void run() {
        // 
        // This method could not be decompiled.
        // 
        // Original Bytecode:
        // 
        //     3: invokestatic    chrriis/dj/nativeswing/lIIllI.sleep:(J)V
        //     6: goto            10
        //     9: astore_1       
        //    10: new             Lchrriis/dj/nativeswing/lIlIII;
        //    13: dup            
        //    14: aload_0         /* this */
        //    15: invokespecial   chrriis/dj/nativeswing/lIlIII.<init>:(Lchrriis/dj/nativeswing/lIIllI;)V
        //    18: invokestatic    javax/swing/SwingUtilities.invokeLater:(Ljava/lang/Runnable;)V
        //    21: return         
        //    StackMapTable: 00 02 49 07 00 24 00
        //    Exceptions:
        //  Try           Handler
        //  Start  End    Start  End    Type                            
        //  -----  -----  -----  -----  --------------------------------
        //  0      6      9      10     Ljava/lang/InterruptedException;
        // 
        // The error that occurred was:
        // 
        // java.lang.NullPointerException
        //     at com.strobel.decompiler.languages.java.ast.AstBuilder.convertType(AstBuilder.java:344)
        //     at com.strobel.decompiler.languages.java.ast.AstBuilder.convertType(AstBuilder.java:173)
        //     at com.strobel.decompiler.languages.java.ast.AstMethodBodyBuilder.transformCall(AstMethodBodyBuilder.java:1119)
        //     at com.strobel.decompiler.languages.java.ast.AstMethodBodyBuilder.transformByteCode(AstMethodBodyBuilder.java:1009)
        //     at com.strobel.decompiler.languages.java.ast.AstMethodBodyBuilder.transformExpression(AstMethodBodyBuilder.java:540)
        //     at com.strobel.decompiler.languages.java.ast.AstMethodBodyBuilder.transformByteCode(AstMethodBodyBuilder.java:554)
        //     at com.strobel.decompiler.languages.java.ast.AstMethodBodyBuilder.transformExpression(AstMethodBodyBuilder.java:540)
        //     at com.strobel.decompiler.languages.java.ast.AstMethodBodyBuilder.transformNode(AstMethodBodyBuilder.java:392)
        //     at com.strobel.decompiler.languages.java.ast.AstMethodBodyBuilder.transformBlock(AstMethodBodyBuilder.java:333)
        //     at com.strobel.decompiler.languages.java.ast.AstMethodBodyBuilder.createMethodBody(AstMethodBodyBuilder.java:294)
        //     at com.strobel.decompiler.languages.java.ast.AstMethodBodyBuilder.createMethodBody(AstMethodBodyBuilder.java:99)
        //     at com.strobel.decompiler.languages.java.ast.AstBuilder.createMethodBody(AstBuilder.java:782)
        //     at com.strobel.decompiler.languages.java.ast.AstBuilder.createMethod(AstBuilder.java:675)
        //     at com.strobel.decompiler.languages.java.ast.AstBuilder.addTypeMembers(AstBuilder.java:552)
        //     at com.strobel.decompiler.languages.java.ast.AstBuilder.createTypeCore(AstBuilder.java:519)
        //     at com.strobel.decompiler.languages.java.ast.AstBuilder.createTypeNoCache(AstBuilder.java:161)
        //     at com.strobel.decompiler.languages.java.ast.AstBuilder.createType(AstBuilder.java:150)
        //     at com.strobel.decompiler.languages.java.ast.AstBuilder.addType(AstBuilder.java:125)
        //     at com.strobel.decompiler.languages.java.JavaLanguage.buildAst(JavaLanguage.java:71)
        //     at com.strobel.decompiler.languages.java.JavaLanguage.decompileType(JavaLanguage.java:59)
        //     at com.strobel.decompiler.Decompiler.decompile(Decompiler.java:70)
        //     at org.ugp.mc.deobfuscator.Deobfuscator3000.decompile(Deobfuscator3000.java:538)
        //     at org.ugp.mc.deobfuscator.Deobfuscator3000.decompileAndDeobfuscate(Deobfuscator3000.java:552)
        //     at org.ugp.mc.deobfuscator.Deobfuscator3000.processMod(Deobfuscator3000.java:510)
        //     at org.ugp.mc.deobfuscator.Deobfuscator3000.lambda$21(Deobfuscator3000.java:329)
        //     at java.base/java.lang.Thread.run(Unknown Source)
        // 
        throw new IllegalStateException("An error occurred while decompiling this method.");
    }
}
